Workbook

Sheet Itinerary
A1: Date | B1: Main Itinerary | C1: Optional Activities | E1: Outfits
A2: 45897 | B2: Fly to Naples 4:46 Take off (SYR - ORD, 2H35M, ORD - NAP, AA 4134, AA 180) | C2: Packing List
A3: =A2+1 -> 45898 | B3: Arrive Naples 1:00 PM 2:00 PM - Welcome Pickups to hotel (reservation) Check into Relais sul Mare Boutique Hotel 3:00 PM (reservation) TODO: Find nearby attractions and pizza spots Dinner (7:30) 50 Kalò - Piazza della Repubblica (reservation) | C3: welcomepickups | D3: Dinner Options: Palazzo Petrucci Ristorante Il Miracolo dei Pesci Ristorante Reginella La Scialuppa 50 kalo
A4: =A3+1 -> 45899 | B4: Naples/Capri 8:10 board ferry to Capri (reservation, boards 8:40, leaves 9:10) - Depart from Molo Beverello Check out of Relais sul Mare 11:30 AM Check into La Residenza Capri 3:00 PM (reservation)? Buy wine and snacks for boat day tomorrow (bring in discreet tote) Dinner (8 PM) at Villa Margherita (reservation) | C4: Cafe: Cafe Caso Hike: Gardens of Augustus Hike: Via Krupp Shop: Via Camerelle Boat Provisions: Enoteca La Vineria, Other Recommendations Pool: Hotel
A5: =A4+1 -> 45900 | B5: Capri Boat Day 9:00 AM - 4:00 PM - Marina Piccola (ticket, reservation) TODO: Find landmarks Dinner (8 PM) at Da Paolino (reservation) | E5: Linen pants, Rag & Bone polo, leather loafers
A6: =A5+1 -> 45901 | B6: Capri La Fontelina (reservation, opens 9:30 AM, lunch 1PM, must check in before 1 PM) Dinner (7:00 PM) at Pullali (reservation) | C6: Night Club: Anema e Core
A7: =A6+1 -> 45902 | B7: Capri to Ravello Check out of La Residenza Capri 11:00 AM 10:45 board Ferry leaving at 11:45 to Amalfi (reservation) Ride from Giancarlo +393394432880 to Ravello (75 euro) (email) Check into Hotel Rufolo 2:00 PM (Reservation, King Size Bed Confirmation) TODO: Find Dinner | C7: Pool: Hotel
A8: =A7+1 -> 45903 | B8: Ravello Dinner (7:30 PM) at Rossellinis (reservation) | C8: Garden: Giardini Principessa di Piemonte Shopping: Local Artisan Shops Wine Bar: Enotavola Wine Bar
A9: =A8+1 -> 45904 | B9: Ravello to Positano Check out of Hotel Rufolo 11:00 AM Mamma Agata (bring 720 Euro, 9:45 AM - 4 PM, reservation, vegetarian option confirmation) TOOD: Book driver to Praiano (4:30 recommended by Mamma Agata) Check into Hotel Savoia 2:00 PM (Reservation) Dinner: See casual options on Right | C9: Dinner: Casual nearby options | D9: Dinner Options: Ristorante La Cambusa Casa e Bottega Ristorante Il Capitano Valle dei Mulini Ristorante Da Bruno Il Tridente Positano | F9: Zass Ristorante Bruno Chez Black
A10: =A9+1 -> 45905 | B10: Positano Arienzo beach club Beach time 11:10 AM, Lunch Time 2:30 PM (times adjustable, Reservation: PVTPTL) Dinner: 8:00 PM at Buca di Bacco (reservation) | C10: Booking Link
A11: =A10+1 -> 45906 | B11: Positano Boat day 2: 9:00 AM - 1:00 PM Grassi Junior Boats (reservation, ticket) Cruise toward the Fjord of Furore, Conca dei Marini, or around Li Galli Islands TODO: Add boat day spots to map TODO: Da Adolfo lunch reservation Dinner: Rada at 9:00 PM (reservation) requested outdoor seating with a view (email) | C11: Night Club: Music on the Rocks Rooftop Cocktail: Frano's Bar (if open) Booking Link
A12: =A11+1 -> 45907 | B12: Positano Lunch: Il Pirata at 1:00 PM (reservation) TODO: Plan day - options Vespa day? Hiking day? Dinner: Adamo ed Eva at 7:00 PM (reservation) requested outdoor seating with a view (email) | C12: Options for Day Hike: Path of the gods Vespa: Destination options Farm: Limoncello Tour
A13: =A12+1 -> 45908 | B13: Check out of Hotel Savoia 11:00 AM TODO: Book car from hotel to Airport 12:00 PM Take off (NAP - PHL 3H - SYR, AA 781, AA 5950)
B17: :)

Sheet Chelsea
A1: https://sierrainthecity.com/best-restaurants-in-positano/
A2: chat gpt
A3: manus

Sheet Amalfi
A1: 45817 | B1: Map | E1: Todo Immediate | F1: Major Items to Book | G1: Status | I1: Ideas | J1: Status | M1: Capri Hotels | R1: Paiano/Positano Hotels | V1: TODO | W1: Spots
A2: 45817 | B2: Travel Assistant | E2: Capri boat dat | F2: La Fontelina (Capri) | G2: Booked for Mon 9/1 | I2: L'Olivo and Mote Solare Chair Lift (Capri) | M2: Sina Flora | N2: 3071 | O2: Booked, free cancellation before Aug 23 | Q2: Praiano | R2: Casa Angelina | S2: Near One Fire Beach Club | V2: Find spots for Capri | W2: Cafes
A3: 45818 | B3: Naples HoodMap | E3: Da Luigis | F3: La Tagliata (Positano) | G3: Requested 6/17 | L3: A little far | M3: Villa Marini | N3: 2883 | Q3: Positano | R3: Casa Nilde | S3: BnB | T3: Booked, cancel before Aug 21 | V3: Find spots for Ravello | W3: Aperitivo
A4: 45817 | B4: ChatGPT: Amafli Deep-Dive | E4: Restaurants in capri | F4: Ristorante Il Pirata (Praiano) | L4: 1. Delux suite wtih spa bath is sick | M4: Palazzo M Capri | N4: 4398 | O4: No pool? | Q4: Positano | R4: Your home in the heart of Positano - centralissima | V4: Find spots for Positano | W4: Rooftop bar
A5: 45813 | B5: Apple Notes: Activity Ideas | F5: da Paolino | G5: Booked for Sun Aug 31 | L5: Anacapri | M5: Boutique Hotel Casa Mariantonia | N5: 1833 | Q5: Positano | R5: Villa Joseph Talamo | W5: Gardens/Vistas
A6: 45817 | B6: ChatGPT (Live): Casual discussion about beach clubs | F6: Capri Boat day | G6: Booked for Sun Aug 31 | L6: Dated | M6: Grand Hotel Quisisana | N6: 3584 | O6: No sea view | Q6: Positano | R6: Hotel Poseidon | W6: Hikes
A7: 45817 | B7: Packing List | F7: Mamma Agata | G7: Booked for Thu 9/4 | L7: Exceptional | M7: Pazziella Garden & Suites | N7: 3875 | O7: Chase | Q7: Positano | R7: Hotel Savoia | W7: Wine bar
A8: 45818 | B8: Manus: Itinerary | F8: Rossellini's, Palazzo Avino | G8: Booked for Wed 9/3 | L8: 2. Cool ground | M8: Villa Certosa | N8: 3702 | O8: Chase is better | Q8: Positano | R8: La Caravella di Positano | W8: Wine tasting
F9: Boat day in Praiano? | M9: Hotel Villa Ceselle (Value Option) | Q9: Positano | R9: Hotel Montemare | S9: Via Pasitea 119, 84017 Positano, Italy | W9: Lunch spots
F10: Naples Hotel | G10: Booked Relais sul Mare | J10: Todo tm: | L10: Wonderful | M10: Capri Tiberio Palace | N10: 4065 | Q10: Positano | R10: Villa Joseph Talamo | S10: 41 Via Guglielmo Marconi, 84017 Positano, Italy | W10: Beaches
B11: Positano Todo | D11: Important nearby: | F11: Da Luigis in Capri | I11: Done | J11: Figure out dates there | L11: Seaside, far, free cancellation | M11: Jumeirah Capri Palace | N11: 4685 | Q11: Positano | R11: Villa Dani | S11: Via del Saracino, 84017 Positano, Italy | W11: Shopping areas
B12: Drink Spot reservations | D12: Cafes | F12: Travel Insurance | I12: Done | J12: Start requesting restaurants on left | L12: Apartment | M12: Sunbliss Capri | N12: 1194 | W12: Historical sites
B13: Hotel | D13: Sandwich/Pastry Shops | F13: Arienzo in Positano | G13: Booked for 9/5 | I13: Done | J13: Ask how to best book boat day, where, cost, and type (blue grotto, personal boat, private tours?) | M13: Punta Tragara | N13: 10237
B14: Rooftop cocktails at Hotel Le Sirenuse | D14: Gelaterias | F14: Spiaggia di Playa in Positano | I14: Done | J14: Book hotel for Capri | M14: Villa Marina Capri
B15: Sunset dinners in Positano | D15: Rooftop/Waterfront/Scenic drinks | F15: Add Buca di Bacco to Dining List | G15: Added to consolidated map, reservations available | I15: Done | J15: Add flight times to itinerary | M15: Hotel La Vega | O15: Booking.com only
D16: Wine bars | F16: Finalize Capri dining | I16: Done | J16: Book hotel for Naples | K16: Grand Hotel Parkers | M16: La Residenza Capri
D17: Walks/Hikes | F17: Find nearby lunch spots, walks, attractions | J17: Book dinner for Naples night 1
A18: Cost Tracker | D18: Night Clubs/Night Life
A19: Relais sul Mare | F19: To Factor In | M19: Chiaia Hotels
A20: Hotel Savoia | D20: Map Layers: | F20: Fiordo di Furore | M20: Grand Hotel Santa Lucia
A21: La Fontelina | D21: Main Events | F21: Marina di Praia | M21: Caruso Place Boutique & Wellness Suites
A22: Arienzo | D22: Curated Options | M22: Relais sul Mare Boutique Hotel | N22: Cheap sea view
A23: Capri Blue Boats | D23: All | F23: Other small todo
A24: Grassi Junior Boats | F24: Find cafes nearby to hotels for coffee/breakfast | M24: Paiano/Positano Hotels
A25: Mamma Agata | F25: Find lunch spots nearby to hotels | L25: Praiano | M25: Casa Angelina | N25: Near One Fire Beach Club
A26: Da Paolino | F26: Find a few casual dinner spots | L26: Positano | M26: Casa Nilde | N26: BnB
A27: Rosselinis | F27: Find "optional" nearby attractions (e.g. villas to explore)
F28: Book transportation between hotels
F29: Le Monzù, Capri
F30: L'Olivo, Capri
A31: Prompts | F31: Vespa day in Praiano?
A32: Itinerary | B32: Hi! My girlfriend (29F) and I (33M) are planning a romantic trip to the Amalfi Coast from August 30 to September 8 (9 nights, 10 days). It’s our first time in Italy, and we’re prioritizing relaxation, scenic beauty, romance, and well-curated experiences over high-effort city touring. We’re New Yorkers, so we want to avoid anything that feels like a Times Square/cruise ship/tourist trap vibe — no cheap souvenir stands, no English-only menus, no tourist junk zones. That said, we’re totally fine with places that are popular or Instagrammable as long as they’re visually stunning, tasteful, and offer a genuine or luxurious experience (like a cliffside restaurant or a boutique hotel with views). We’d like to: Fly into Naples (arriving Aug 30), spend 1 night for the culture and pizza Ferry to Capri for 1-3 nights to explore beaches, views, and maybe a boat day. Ferry to the Amalfi Coast, staying the reset of our nights in scenic towns like Ravello, Praiano, or Conca dei Marini — open to mixing between them. Fly out of Naples on Sept 8. We’re open to renting a car if it makes things easier, but it seems ferries with a mix of private transfers and vespas might be the simplest route. We’d love help finalizing: Which towns to base ourselves in (and for how long). A day-by-day structure using “anchor activities” and optional extras. Boutique hotel or lodging suggestions in each area. Restaurant, beach club, or boat day ideas that match our taste. Best use of ferries, private drivers, or transfer timing. Here were some high-level things we were interested in generally before settling on Amalfi as our destination: - [ ] Beach day (e.g. one lined with umbrellas) - [ ] Beach club - [ ] Vespa riding - [ ] Wine tasting tour (foot, bike, or vespa, or one single location without movement if easier) - [ ] Grotta Palazzese dinner (this is in Puglia, but we'd love something with a similar memorable stunning view) - [ ] Boat day - [ ] Aperol spritz rooftop sunset - [ ] Good authentic local food - [ ] Cooking class (normal/authentic or crazy and fun like La Tagliata cooking class in Positano) - [ ] Hike (e.g. along costal cliffside or in historic towns) - [ ] If there are any notable spas, thermal pools, or ancient bath houses in the region we might be up for checking them out but that's not a priority for diverting travel When planning think: romantic, adventurous, beautiful, and upscale — but never tacky. Thanks! | F32: L'Olivo and Mote Solare Chair Lift (Capri)
A33: Maps | B33: Thanks, can you compile all the places you recommended into a table with the following columns: Name: The name of the location Region: The town, city, neighborhood, or region Type: The type of location (e.g. hotel, Restaurant (lunch), Restaurant (dinner) Cafe, Gelateria, Rooftop Bar, Speakeasy, etc) Emoji: A representative emoji to be used on the map as an icon. Description: A description of the spot and its general vibe Special Notes: Any special considerations (must order items, dress code, cool historical facts, etc) Hours: Hours of operation (if applicable) Cost Range: Indication of how much 2 people would be expected to spend in a visit (in USD) Address: The full address (including country) if available LatLong: The latitude and Longitude separated by a comma and space
A34: Map Options | B34: Can you also recommend a mix of spots nearby that are in our general area and might be good to know about in case we are feeling spontaneous (so not as itinerary-oriented and more options list). Feel free to use my list or sprinkle in things we don't know about. Think places like renowned cafes, pizzerias, gelato shops, shopping places, wine windows, rooftop bars, wine bars, etc. Anything casual that might be fun to visit quickly while attending to a larger agenda. Can you come up with at least three (but preferably more) recommendations for each?
A35: Chiaia | B35: My girlfriend (29F) and I (33M) are staying a night or two in the Chiaia region of Naples before leaving to Capri for a few days. We are from NYC and like good food, good drinks, romantic scenery, exploring, and adventure. Can you recommend some hotels in the ~$200 to ~$400 USD range that are nice to stay in for dates 8/28 to 8/30? Can you also compile a list of good restaurants (pref a few on the water and a few inland that stand on their own merit), cool bars, cool cafes, cool rooftops for drinks, gelato spots, pizza spots, nightlife, and anything else that is a cool cultural experience for the area (or immediately adjacent) that we can explore while waiting to go to Capri? Think recommendations that would be suitable for theinfatuation.com, eater.com, or a well-regarded and chic travel blog or Instagram account.
A36: Maps 2

Sheet Consolidated Map
A1: Name | B1: Region | C1: Type | D1: Emoji | E1: Description | F1: Special Notes | G1: Hours | H1: Cost Range | I1: Address | J1: LatLong | K1: Latitude | L1: Longitude | M1: Google Maps | N1: Recommended By | O1: Plan | P1: Trip Segment | Q1: Hotel | R1: Walking Distance | S1: Driving Distance | T1: Curated
A2: Buonocore Gelateria & Bakery | B2: Capri town | C2: Bakery / Gelateria / Cafe | D2: 🍦 | E2: Famous bakery and gelateria with fresh panini, focaccia, and pastries. Very popular with locals and tourists alike. | F2: Smell the waffle cones to find it. Great for takeaway. Try the lemon granita or focaccia. | G2: 10:00–23:00 | H2: $10–$25 | I2: Via Vittorio Emanuele, 35, 80073 Capri NA, Italy | J2: 40.5504793, 14.2435663 | K2: 40.550479 | L2: 14.243566 | M2: https://www.google.com/maps/search/Buonocore%20Gelateria%20%26%20Bakery%2C%20Capri%2C%20Italy | N2: ChatGPT | O2: ChatGPT Capri Boat Day Wine Shops and Bakeries | P2: =VLOOKUP(B2,$V$3:$W$100,2,0) -> Capri | Q2: =VLOOKUP(P2,$X$3:$Y$6,2,0)&", "&P2&", Italy" -> La Residenza, Capri, Italy | R2: =VLOOKUP(A2,'Travel Times'!$A$1:$E$1000,4,0) -> 3 mins | S2: =VLOOKUP(A2,'Travel Times'!$A$1:$E$1000,5,0) -> 1 min
A3: Ristorante Lo Sfizio | B3: Capri (Via Tiberio) | C3: Casual Eatery / Bakery | D3: 🥪 | E3: Local favorite for rustic sandwiches, pizza by the slice, and simple, hearty baked goods. | F3: Perfect for takeaway or a quick bite. Affordable and local vibe. | G3: 12:00–15:00, 19:00–23:00 (closed Tuesdays) | H3: $20–$40 | I3: Via Tiberio, 7/e, 80073 Capri NA, Italy | J3: 40.552373, 14.250934 | K3: 40.552373 | L3: 14.250934 | M3: https://www.google.com/maps/search/Ristorante%20Lo%20Sfizio%2C%20Capri%2C%20Italy | N3: ChatGPT | O3: ChatGPT Capri Boat Day Wine Shops and Bakeries | P3: =VLOOKUP(B3,$V$3:$W$100,2,0) -> Capri | Q3: =VLOOKUP(P3,$X$3:$Y$6,2,0)&", "&P3&", Italy" -> La Residenza, Capri, Italy | R3: =VLOOKUP(A3,'Travel Times'!$A$1:$E$1000,4,0) -> 14 mins | S3: =VLOOKUP(A3,'Travel Times'!$A$1:$E$1000,5,0) -> 6 mins | V3: Capri town | W3: Capri | X3: Capri | Y3: La Residenza
A4: Caffè Caso | B4: Capri town | C4: Cafe | D4: ☕ | E4: Charming sidewalk café with espresso, croissants, and light snacks. | F4: Good for a quick stop before heading to the marina. Get the cornetto al limone. | G4: 07:30–21:00 | H4: $10–$20 | I4: Piazza Umberto I, 4, 80073 Capri NA, Italy | J4: 40.5508286, 14.2427963 | K4: 40.550829 | L4: 14.242796 | M4: https://www.google.com/maps/search/Caff%C3%A8%20Caso%2C%20Capri%2C%20Italy | N4: ChatGPT | O4: ChatGPT Capri Boat Day Wine Shops and Bakeries | P4: =VLOOKUP(B4,$V$3:$W$100,2,0) -> Capri | Q4: =VLOOKUP(P4,$X$3:$Y$6,2,0)&", "&P4&", Italy" -> La Residenza, Capri, Italy | R4: =VLOOKUP(A4,'Travel Times'!$A$1:$E$1000,4,0) -> 4 mins | S4: =VLOOKUP(A4,'Travel Times'!$A$1:$E$1000,5,0) -> 1 min | V4: Capri (Via Tiberio) | W4: Capri | X4: Naples | Y4: Relais sul Mare Boutique Hotel
A5: Panificio Fornaretto | B5: Capri town | C5: Bakery | D5: 🍞 | E5: Rustic neighborhood bakery specializing in fresh bread, pizza bianca, and taralli. | F5: No frills but great for boat snacks and local baked goods. | G5: 07:00–14:00, 17:00–20:00 | H5: $10–$20 | I5: Via Trieste e Trento, 20, 80071 Anacapri NA, Italy | J5: 40.55462790000001, 14.2168974 | K5: 40.554628 | L5: 14.216897 | M5: https://www.google.com/maps/search/Panificio%20Fornaretto%2C%20Capri%2C%20Italy | N5: ChatGPT | O5: ChatGPT Capri Boat Day Wine Shops and Bakeries | P5: =VLOOKUP(B5,$V$3:$W$100,2,0) -> Capri | Q5: =VLOOKUP(P5,$X$3:$Y$6,2,0)&", "&P5&", Italy" -> La Residenza, Capri, Italy | R5: =VLOOKUP(A5,'Travel Times'!$A$1:$E$1000,4,0) -> 52 mins | S5: =VLOOKUP(A5,'Travel Times'!$A$1:$E$1000,5,0) -> 11 mins | V5: Marina Grande | W5: Capri | X5: Ravello | Y5: Hotel Rufolo
A6: Enoteca Truglio | B6: Capri town | C6: Wine Shop | D6: 🍷 | E6: Local wine shop offering a curated selection of Campania wines, prosecco, and local snacks. | F6: Staff can recommend wine for boat days. Ask for Falanghina or Biancolella. | G6: 09:00–13:00, 16:30–20:00 | H6: $20–$60 | I6: 80076 Capri, Metropolitan City of Naples, Italy | J6: 40.5542182, 14.2400251 | K6: 40.554218 | L6: 14.240025 | M6: https://www.google.com/maps/search/Enoteca%20Truglio%2C%20Capri%2C%20Italy | N6: ChatGPT | O6: ChatGPT Capri Boat Day Wine Shops and Bakeries | P6: =VLOOKUP(B6,$V$3:$W$100,2,0) -> Capri | Q6: =VLOOKUP(P6,$X$3:$Y$6,2,0)&", "&P6&", Italy" -> La Residenza, Capri, Italy | R6: =VLOOKUP(A6,'Travel Times'!$A$1:$E$1000,4,0) -> 16 mins | S6: =VLOOKUP(A6,'Travel Times'!$A$1:$E$1000,5,0) -> 7 mins | V6: Matermania/Arco Naturale | W6: Capri | X6: Positano | Y6: Hotel Savoia
A7: Enoteca La Vineria | B7: Capri town | C7: Wine Shop | D7: 🥂 | E7: Upscale wine shop near the Piazzetta with excellent white wines, prosecco, and picnic-ready options. | F7: Offers chilled bottles. Great for romantic boat provisioning. | G7: 10:00–13:00, 16:00–20:00 | H7: $30–$80 | I7: Via Gino Alfani, 39, 80058 Torre Annunziata NA, Italy | J7: 40.5507259, 14.2429 | K7: 40.550726 | L7: 14.2429 | M7: https://www.google.com/maps/search/Enoteca%20La%20Vineria%2C%20Capri%2C%20Italy | N7: ChatGPT | O7: ChatGPT Capri Boat Day Wine Shops and Bakeries | P7: =VLOOKUP(B7,$V$3:$W$100,2,0) -> Capri | Q7: =VLOOKUP(P7,$X$3:$Y$6,2,0)&", "&P7&", Italy" -> La Residenza, Capri, Italy | R7: =VLOOKUP(A7,'Travel Times'!$A$1:$E$1000,4,0) -> 4 mins | S7: =VLOOKUP(A7,'Travel Times'!$A$1:$E$1000,5,0) -> 1 min | V7: Capri | W7: Capri
A8: Da Giorgio | B8: Capri Town | C8: Restaurant (Lunch/Dinner) | D8: 🍽️ | E8: Reddit favorite with amazing view of Capri harbor, Mount Vesuvius, and the coast. Decades of delicious dishes, excellent seafood delicacies | F8: Recommended by local hotel owners, 7-minute taxi from Marina Grande, stunning Bay of Naples views | G8: 12:00 PM - 3:00 PM & 7:00 PM - 11:00 PM | H8: $80-120 USD for 2 | I8: Via Roma, 34, 80076 Capri NA, Italy | J8: 40.55018400000001, 14.241639 | K8: 40.550184 | L8: 14.241639 | M8: https://www.google.com/maps/search/Da%20Giorgio%2C%20Capri%2C%20Italy | N8: Manus | O8: Manus Capri Restaurants | P8: =VLOOKUP(B8,$V$3:$W$100,2,0) -> Capri | Q8: =VLOOKUP(P8,$X$3:$Y$6,2,0)&", "&P8&", Italy" -> La Residenza, Capri, Italy | R8: =VLOOKUP(A8,'Travel Times'!$A$1:$E$1000,4,0) -> 6 mins | S8: =VLOOKUP(A8,'Travel Times'!$A$1:$E$1000,5,0) -> 1 min | V8: Naples | W8: Naples
A9: Aurora | B9: Capri Town | C9: Restaurant (Dinner) | D9: 🍽️ | E9: Historic gastronomic museum with fun loud singalong atmosphere. Truffle pizzas, delicate pastas, classic seafood dishes. Oldest restaurant in Capri | F9: Must try the cataloni dish, lively metro vibe, walls adorned with photographs, more than a restaurant | G9: 7:00 PM - 11:30 PM | H9: $90-140 USD for 2 | I9: Via Fuorlovado, 18, 80073 Capri NA, Italy | J9: 40.550878, 14.2450572 | K9: 40.550878 | L9: 14.245057 | M9: https://www.google.com/maps/search/Aurora%2C%20Capri%2C%20Italy | N9: Manus | O9: Manus Capri Restaurants | P9: =VLOOKUP(B9,$V$3:$W$100,2,0) -> Capri | Q9: =VLOOKUP(P9,$X$3:$Y$6,2,0)&", "&P9&", Italy" -> La Residenza, Capri, Italy | R9: =VLOOKUP(A9,'Travel Times'!$A$1:$E$1000,4,0) -> 5 mins | S9: =VLOOKUP(A9,'Travel Times'!$A$1:$E$1000,5,0) -> 1 min | V9: Ravello | W9: Ravello
A10: Da Gemma | B10: Marina Grande | C10: Restaurant (Lunch/Dinner) | D10: 🍽️ | E10: #1 rated restaurant on TripAdvisor with 4.7/5 rating from 1,513 reviews. Seafood and Mediterranean cuisine, homemade pasta | F10: Consistently highest-rated, family-owned, reliable excellence, proven track record | G10: 12:00 PM - 3:00 PM & 7:00 PM - 11:00 PM | H10: $70-110 USD for 2 | I10: Via Cristoforo Colombo, 7, 80073 Capri NA, Italy | J10: 40.5562249, 14.2388268 | K10: 40.556225 | L10: 14.238827 | M10: https://www.google.com/maps/search/Da%20Gemma%2C%20Capri%2C%20Italy | N10: Manus | O10: Manus Capri Restaurants | P10: =VLOOKUP(B10,$V$3:$W$100,2,0) -> Capri | Q10: =VLOOKUP(P10,$X$3:$Y$6,2,0)&", "&P10&", Italy" -> La Residenza, Capri, Italy | R10: =VLOOKUP(A10,'Travel Times'!$A$1:$E$1000,4,0) -> 23 mins | S10: =VLOOKUP(A10,'Travel Times'!$A$1:$E$1000,5,0) -> 9 mins | V10: Wine Experience, Ravello | W10: Ravello
A11: Le Grottelle | B11: Matermania/Arco Naturale | C11: Restaurant (Dinner) | D11: 🍽️ | E11: Hidden gem nestled inside natural caves near Arco Naturale. Dining experience like no other, 20-minute walk from main tourist hub | F11: Special occasion dinner, unique cave dining experience, off the beaten path, advance reservations essential | G11: 7:00 PM - 11:00 PM | H11: $100-150 USD for 2 | I11: Via Arco Naturale, 13, 80073 Capri NA, Italy | J11: 40.5494786, 14.2541823 | K11: 40.549479 | L11: 14.254182 | M11: https://www.google.com/maps/search/Le%20Grottelle%2C%20Capri%2C%20Italy | N11: Manus | O11: Manus Capri Restaurants | P11: =VLOOKUP(B11,$V$3:$W$100,2,0) -> Capri | Q11: =VLOOKUP(P11,$X$3:$Y$6,2,0)&", "&P11&", Italy" -> La Residenza, Capri, Italy | R11: =VLOOKUP(A11,'Travel Times'!$A$1:$E$1000,4,0) -> 20 mins | S11: =VLOOKUP(A11,'Travel Times'!$A$1:$E$1000,5,0) -> #ERROR! | V11: Praiano | W11: Positano
A12: Villa Verde | B12: Capri Town | C12: Restaurant (Dinner) | D12: 🍽️ | E12: White table-clothed restaurant in old town great for big groups. Combines dinner with nightlife, beautiful outdoor patio dining | F12: Great for groups, evening entertainment with dinner, away from crowds, lively evening scene | G12: 7:00 PM - 12:00 AM | H12: $90-130 USD for 2 | I12: Via Sella Orta, 6, 80073 Capri NA, Italy | J12: 40.55006849999999, 14.2445107 | K12: 40.550069 | L12: 14.244511 | M12: https://www.google.com/maps/search/Villa%20Verde%2C%20Capri%2C%20Italy | N12: Manus | O12: Manus Capri Restaurants | P12: =VLOOKUP(B12,$V$3:$W$100,2,0) -> Capri | Q12: =VLOOKUP(P12,$X$3:$Y$6,2,0)&", "&P12&", Italy" -> La Residenza, Capri, Italy | R12: =VLOOKUP(A12,'Travel Times'!$A$1:$E$1000,4,0) -> 2 mins | S12: =VLOOKUP(A12,'Travel Times'!$A$1:$E$1000,5,0) -> 1 min | T12: Lunch: selected by Chelsea | V12: Conca dei Marini | W12: Positano
A13: Lo Smeraldo | B13: Marina Grande | C13: Restaurant (Lunch/Dinner) | D13: 🍽️ | E13: Family-owned seaside restaurant with patio overlooking the water. Amazing coastline views, fresh seafood specialties | F13: Unbeatable seaside dining, patio over the water, romantic seafood dinner with water views | G13: 12:00 PM - 3:00 PM & 7:00 PM - 10:30 PM | H13: $80-120 USD for 2 | I13: Piazza Vittoria, 1, 80073 Capri NA, Italy | J13: 40.5504764, 14.243448 | K13: 40.550476 | L13: 14.243448 | M13: https://www.google.com/maps/search/Lo%20Smeraldo%2C%20Capri%2C%20Italy | N13: Manus | O13: Manus Capri Restaurants | P13: =VLOOKUP(B13,$V$3:$W$100,2,0) -> Capri | Q13: =VLOOKUP(P13,$X$3:$Y$6,2,0)&", "&P13&", Italy" -> La Residenza, Capri, Italy | R13: =VLOOKUP(A13,'Travel Times'!$A$1:$E$1000,4,0) -> 22 mins | S13: =VLOOKUP(A13,'Travel Times'!$A$1:$E$1000,5,0) -> 10 mins | V13: Monastero Santa Rosa | W13: Positano
A14: Pescheria Le Botteghe | B14: Capri Town | C14: Restaurant (Lunch) | D14: 🍽️ | E14: Fish market that also serves incredibly fresh seafood. Buy fresh fish and have it prepared on-site, market-to-table concept | F14: Freshest possible seafood, authentic local experience, not touristy, ultimate freshness for seafood lovers | G14: 10:00 AM - 3:00 PM | H14: $60-90 USD for 2 | I14: Via le Botteghe, 19, 80076 Capri NA, Italy | J14: 40.550782, 14.2433042 | K14: 40.550782 | L14: 14.243304 | M14: https://www.google.com/maps/search/Pescheria%20Le%20Botteghe%2C%20Capri%2C%20Italy | N14: Manus | O14: Manus Capri Restaurants | P14: =VLOOKUP(B14,$V$3:$W$100,2,0) -> Capri | Q14: =VLOOKUP(P14,$X$3:$Y$6,2,0)&", "&P14&", Italy" -> La Residenza, Capri, Italy | R14: =VLOOKUP(A14,'Travel Times'!$A$1:$E$1000,4,0) -> 4 mins | S14: =VLOOKUP(A14,'Travel Times'!$A$1:$E$1000,5,0) -> 1 min | V14: Positano | W14: Positano
A15: Lo Sfizio | B15: Capri Town | C15: Restaurant (Lunch/Dinner) | D15: 🥪 | E15: Local favorite mentioned in food tours, authentic neighborhood spot. Traditional Italian dishes with good value | F15: Casual authentic meal, frequented by locals, less touristy atmosphere, good value dining | G15: 12:00 PM - 3:00 PM & 7:00 PM - 10:30 PM | H15: $50-80 USD for 2 | I15: Via Tiberio, 7/e, 80073 Capri NA, Italy | J15: 40.552373, 14.250934 | K15: 40.552373 | L15: 14.250934 | M15: https://www.google.com/maps/search/Lo%20Sfizio%2C%20Capri%2C%20Italy | N15: Manus | O15: Manus Capri Restaurants | P15: =VLOOKUP(B15,$V$3:$W$100,2,0) -> Capri | Q15: =VLOOKUP(P15,$X$3:$Y$6,2,0)&", "&P15&", Italy" -> La Residenza, Capri, Italy | R15: =VLOOKUP(A15,'Travel Times'!$A$1:$E$1000,4,0) -> 14 mins | S15: =VLOOKUP(A15,'Travel Times'!$A$1:$E$1000,5,0) -> 6 mins | T15: Lunch: Chelsea said looks good for pizza, as ChaptGPT recommended | V15: Anacapri | W15: Capri
A16: Ristorante Pulalli | B16: Capri | C16: Restaurant (Dinner) | D16: 🍽️ | E16: Traditional Capri cuisine with well-executed classics. Established restaurant with reliable quality | F16: Solid reputation among travel guides, traditional Capri dining, reliable choice | G16: 7:00 PM - 11:00 PM | H16: $70-100 USD for 2 | I16: Piazza Umberto I, 4, 80073 Capri NA, Italy | J16: 40.5508286, 14.2427963 | K16: 40.550829 | L16: 14.242796 | M16: https://www.google.com/maps/search/Ristorante%20Pulalli%2C%20Capri%2C%20Italy | N16: Manus | O16: Manus Capri Restaurants | P16: =VLOOKUP(B16,$V$3:$W$100,2,0) -> Capri | Q16: =VLOOKUP(P16,$X$3:$Y$6,2,0)&", "&P16&", Italy" -> La Residenza, Capri, Italy | R16: =VLOOKUP(A16,'Travel Times'!$A$1:$E$1000,4,0) -> 4 mins | S16: =VLOOKUP(A16,'Travel Times'!$A$1:$E$1000,5,0) -> 1 min | T16: Dinner: Reserved | V16: Amalfi | W16: Positano
A17: Gennaro Amitrano | B17: Capri | C17: Restaurant (Dinner) | D17: 🍽️ | E17: Family-run establishment with authentic Italian family hospitality. Home-style cooking with traditional recipes | F17: Personal service, family atmosphere, authentic family dining experience | G17: 7:00 PM - 10:30 PM | H17: $60-90 USD for 2 | I17: Via Marina Piccola, 120, 80073 Capri NA, Italy | J17: 40.545691, 14.2355518 | K17: 40.545691 | L17: 14.235552 | M17: https://www.google.com/maps/search/Gennaro%20Amitrano%2C%20Capri%2C%20Italy | N17: Manus | O17: Manus Capri Restaurants | P17: =VLOOKUP(B17,$V$3:$W$100,2,0) -> Capri | Q17: =VLOOKUP(P17,$X$3:$Y$6,2,0)&", "&P17&", Italy" -> La Residenza, Capri, Italy | R17: =VLOOKUP(A17,'Travel Times'!$A$1:$E$1000,4,0) -> 22 mins | S17: =VLOOKUP(A17,'Travel Times'!$A$1:$E$1000,5,0) -> 8 mins | V17: Amalfi Coast | W17: Positano
A18: Ziqù Restaurant | B18: Capri | C18: Restaurant (Dinner) | D18: 🍽️ | E18: Highest rated restaurant with 4.9/5 from 269 reviews. Italian and seafood cuisine, exceptional quality | F18: Limited reviews suggest exclusivity, highest rating on TripAdvisor, exceptional quality | G18: 7:00 PM - 11:00 PM | H18: $150-200+ USD for 2 | I18: Via Marina Grande, 191, 80073 Capri NA, Italy | J18: 40.55633, 14.2361122 | K18: 40.55633 | L18: 14.236112 | M18: https://www.google.com/maps/search/Ziq%C3%B9%20Restaurant%2C%20Capri%2C%20Italy | N18: Manus | O18: Manus Capri Restaurants | P18: =VLOOKUP(B18,$V$3:$W$100,2,0) -> Capri | Q18: =VLOOKUP(P18,$X$3:$Y$6,2,0)&", "&P18&", Italy" -> La Residenza, Capri, Italy | R18: =VLOOKUP(A18,'Travel Times'!$A$1:$E$1000,4,0) -> 19 mins | S18: =VLOOKUP(A18,'Travel Times'!$A$1:$E$1000,5,0) -> 7 mins | V18: Furore | W18: Positano
A19: Da Tonino | B19: Capri | C19: Restaurant (Lunch/Dinner) | D19: 🍽️ | E19: Established local favorite with 1,304 reviews. Consistently good quality, dependable dining option | F19: Reliable choice, established reputation, consistent quality | G19: 12:00 PM - 3:00 PM & 7:00 PM - 10:30 PM | H19: $70-100 USD for 2 | I19: Via Dentecale, 14, 80073 Capri NA, Italy | J19: 40.5497881, 14.2450745 | K19: 40.549788 | L19: 14.245074 | M19: https://www.google.com/maps/search/Da%20Tonino%2C%20Capri%2C%20Italy | N19: Manus | O19: Manus Capri Restaurants | P19: =VLOOKUP(B19,$V$3:$W$100,2,0) -> Capri | Q19: =VLOOKUP(P19,$X$3:$Y$6,2,0)&", "&P19&", Italy" -> La Residenza, Capri, Italy | R19: =VLOOKUP(A19,'Travel Times'!$A$1:$E$1000,4,0) -> 18 mins | S19: =VLOOKUP(A19,'Travel Times'!$A$1:$E$1000,5,0) -> 6 mins | V19: Bomerano (start) to Nocelle (end) | W19: Positano
A20: Artemisia Domus (Naples) | B20: =substitute(RIGHT(A20,len(A20)-FIND("(",A20)),")","") -> Naples | C20: Hotel | D20: 🏨 | E20: Boutique hotel in central Naples with elegant design and great breakfast. | F20: Boutique B&B with stylish rooms; complimentary breakfast and pre-arrival concierge. | G20: 24/7 (hotel) | H20: $900 for two | I20: Via dei Carrozzieri a Monteoliveto 13, 80134 Napoli, Italy | J20: 40.845634, 14.2517054 | K20: =IFERROR(__xludf.DUMMYFUNCTION("SPLIT(J20,"", "")"),40.845634) -> 40.845634 | L20: =IFERROR(__xludf.DUMMYFUNCTION("""COMPUTED_VALUE"""),14.2517054) -> 14.251705 | M20: =HYPERLINK("https://www.google.com/maps/search/"&ENCODEURL(A20&", "&21&", Italy")) -> https://www.google.com/maps/search/Artemisia%20Domus%20%28Naples%29%2C%2021%2C%20Italy | N20: ChatGPT - https://chatgpt.com/c/6846f0da-7884-8009-ad13-dba01dfa021d | O20: ChatGPT Itinerary 1 | P20: =VLOOKUP(B20,$V$3:$W$100,2,0) -> Naples | Q20: =VLOOKUP(P20,$X$3:$Y$6,2,0)&", "&P20&", Italy" -> Relais sul Mare Boutique Hotel, Naples, Italy | R20: =VLOOKUP(A20,'Travel Times'!$A$1:$E$1000,4,0) -> 29 mins | S20: =VLOOKUP(A20,'Travel Times'!$A$1:$E$1000,5,0) -> 9 mins | V20: Praiano-Positano | W20: Positano
A21: The Britannique by Hilton (Naples) | B21: =substitute(RIGHT(A21,len(A21)-FIND("(",A21)),")","") -> Naples | C21: Hotel | D21: 🏨 | E21: Modern hotel in Naples with panoramic rooftop bar and sea views. | F21: Modern hotel with rooftop bar & spa; reserve for sunset cocktails. | G21: 24/7 (hotel) | H21: $500 for two | I21: C.so Vittorio Emanuele, 133, 80121 Napoli NA, Italy | J21: 40.836915, 14.2296809 | K21: =IFERROR(__xludf.DUMMYFUNCTION("SPLIT(J21,"", "")"),40.836915) -> 40.836915 | L21: =IFERROR(__xludf.DUMMYFUNCTION("""COMPUTED_VALUE"""),14.2296809) -> 14.229681 | M21: =HYPERLINK("https://www.google.com/maps/search/"&ENCODEURL(A21&", "&21&", Italy")) -> https://www.google.com/maps/search/The%20Britannique%20by%20Hilton%20%28Naples%29%2C%2021%2C%20Italy | N21: ChatGPT - https://chatgpt.com/c/6846f0da-7884-8009-ad13-dba01dfa021d | O21: ChatGPT Itinerary 1 | P21: =VLOOKUP(B21,$V$3:$W$100,2,0) -> Naples | Q21: =VLOOKUP(P21,$X$3:$Y$6,2,0)&", "&P21&", Italy" -> Relais sul Mare Boutique Hotel, Naples, Italy | R21: =VLOOKUP(A21,'Travel Times'!$A$1:$E$1000,4,0) -> 39 mins | S21: =VLOOKUP(A21,'Travel Times'!$A$1:$E$1000,5,0) -> 11 mins | V21: Montepertuso (above Positano) | W21: Positano
A22: Gino Sorbillo (Naples) | B22: =substitute(RIGHT(A22,len(A22)-FIND("(",A22)),")","") -> Naples | C22: Restaurant | D22: 🍕 | E22: One of Naples’ most iconic pizzerias in the historic center. | F22: Famous Neapolitan pizza, long lines – best to arrive just before opening; try their pineapple pizza. | G22: Mon–Sat 12:00–15:30 & 19:00–23:30; Sun closed (fontelina-capri.com, happycow.net, perplexity.ai, tripadvisor.com) | H22: $70 for two | I22: Via dei Tribunali 32, 80138 Napoli, Italy | J22: 40.850421, 14.2553143 | K22: =IFERROR(__xludf.DUMMYFUNCTION("SPLIT(J22,"", "")"),40.850421) -> 40.850421 | L22: =IFERROR(__xludf.DUMMYFUNCTION("""COMPUTED_VALUE"""),14.2553143) -> 14.255314 | M22: =HYPERLINK("https://www.google.com/maps/search/"&ENCODEURL(A22&", "&21&", Italy")) -> https://www.google.com/maps/search/Gino%20Sorbillo%20%28Naples%29%2C%2021%2C%20Italy | N22: ChatGPT - https://chatgpt.com/c/6846f0da-7884-8009-ad13-dba01dfa021d | O22: ChatGPT Itinerary 1 | P22: =VLOOKUP(B22,$V$3:$W$100,2,0) -> Naples | Q22: =VLOOKUP(P22,$X$3:$Y$6,2,0)&", "&P22&", Italy" -> Relais sul Mare Boutique Hotel, Naples, Italy | R22: =VLOOKUP(A22,'Travel Times'!$A$1:$E$1000,4,0) -> 39 mins | S22: =VLOOKUP(A22,'Travel Times'!$A$1:$E$1000,5,0) -> 23 mins
A23: L’Antica Pizzeria da Michele (Naples) | B23: =substitute(RIGHT(A23,len(A23)-FIND("(",A23)),")","") -> Naples | C23: Restaurant | D23: 🍕 | E23: Historic, no-frills spot for some of Naples’ best traditional pizza. | F23: Historic classic; very simple menu (Margherita/Marinara only). | G23: Typically 11:00–23:00, often closes Mon (confirm) | H23: $70 for two | I23: Via Cesare Sersale 1, 80139 Napoli | J23: 40.8497752, 14.2632371 | K23: =IFERROR(__xludf.DUMMYFUNCTION("SPLIT(J23,"", "")"),40.8497752) -> 40.849775 | L23: =IFERROR(__xludf.DUMMYFUNCTION("""COMPUTED_VALUE"""),14.2632371) -> 14.263237 | M23: =HYPERLINK("https://www.google.com/maps/search/"&ENCODEURL(A23&", "&21&", Italy")) -> https://www.google.com/maps/search/L%E2%80%99Antica%20Pizzeria%20da%20Michele%20%28Naples%29%2C%2021%2C%20Italy | N23: ChatGPT - https://chatgpt.com/c/6846f0da-7884-8009-ad13-dba01dfa021d | O23: ChatGPT Itinerary 1 | P23: =VLOOKUP(B23,$V$3:$W$100,2,0) -> Naples | Q23: =VLOOKUP(P23,$X$3:$Y$6,2,0)&", "&P23&", Italy" -> Relais sul Mare Boutique Hotel, Naples, Italy | R23: =VLOOKUP(A23,'Travel Times'!$A$1:$E$1000,4,0) -> 39 mins | S23: =VLOOKUP(A23,'Travel Times'!$A$1:$E$1000,5,0) -> 13 mins
A24: Gay‑Odin (Naples) | B24: =substitute(RIGHT(A24,len(A24)-FIND("(",A24)),")","") -> Naples | C24: Shop | D24: 🍦 | E24: Artisanal chocolate shop famous for its gelato and heritage sweets. | F24: Artisanal chocolates & gelato; great for gifting or a quick treat. | G24: 10:00–20:00 daily | H24: $60 for two | I24: Via San Biagio dei Librai 44, 80138 Napoli | J24: 40.84968560000001, 14.2589603 | K24: =IFERROR(__xludf.DUMMYFUNCTION("SPLIT(J24,"", "")"),40.8496856) -> 40.849686 | L24: =IFERROR(__xludf.DUMMYFUNCTION("""COMPUTED_VALUE"""),14.2589603) -> 14.25896 | M24: =HYPERLINK("https://www.google.com/maps/search/"&ENCODEURL(A24&", "&21&", Italy")) -> https://www.google.com/maps/search/Gay%E2%80%91Odin%20%28Naples%29%2C%2021%2C%20Italy | N24: ChatGPT - https://chatgpt.com/c/6846f0da-7884-8009-ad13-dba01dfa021d | O24: ChatGPT Itinerary 1 | P24: =VLOOKUP(B24,$V$3:$W$100,2,0) -> Naples | Q24: =VLOOKUP(P24,$X$3:$Y$6,2,0)&", "&P24&", Italy" -> Relais sul Mare Boutique Hotel, Naples, Italy | R24: =VLOOKUP(A24,'Travel Times'!$A$1:$E$1000,4,0) -> 44 mins | S24: =VLOOKUP(A24,'Travel Times'!$A$1:$E$1000,5,0) -> 11 mins
A25: Hotel Villa Brunella (Capri) | B25: =substitute(RIGHT(A25,len(A25)-FIND("(",A25)),")","") -> Capri | C25: Hotel | D25: 🏨 | E25: Romantic and quiet boutique hotel with stunning terrace views. | F25: Terrace views over Marina Piccola; request sea-view rooms and private shuttle to Capri town. | G25: 24/7 (hotel) | H25: 3000 | I25: 80073, Via Tragara, 24a, 80073 Capri NA, Italy | J25: 40.5461439, 14.2495769 | K25: =IFERROR(__xludf.DUMMYFUNCTION("SPLIT(J25,"", "")"),40.5461439) -> 40.546144 | L25: =IFERROR(__xludf.DUMMYFUNCTION("""COMPUTED_VALUE"""),14.2495769) -> 14.249577 | M25: =HYPERLINK("https://www.google.com/maps/search/"&ENCODEURL(A25&", "&21&", Italy")) -> https://www.google.com/maps/search/Hotel%20Villa%20Brunella%20%28Capri%29%2C%2021%2C%20Italy | N25: ChatGPT - https://chatgpt.com/c/6846f0da-7884-8009-ad13-dba01dfa021d | O25: ChatGPT Itinerary 1 | P25: =VLOOKUP(B25,$V$3:$W$100,2,0) -> Capri | Q25: =VLOOKUP(P25,$X$3:$Y$6,2,0)&", "&P25&", Italy" -> La Residenza, Capri, Italy | R25: =VLOOKUP(A25,'Travel Times'!$A$1:$E$1000,4,0) -> 12 mins | S25: =VLOOKUP(A25,'Travel Times'!$A$1:$E$1000,5,0) -> 1 min
A26: JK Place Capri (Capri) | B26: =substitute(RIGHT(A26,len(A26)-FIND("(",A26)),")","") -> Capri | C26: Hotel | D26: 🏨 | E26: Luxury waterfront hotel near Marina Grande with impeccable service. | F26: Luxury beachfront hotel; ideal for romantic dinners by the sea. | G26: 24/7 (hotel) | H26: 3000 | I26: Via Roma 71, 80073 Capri NA, Italy | J26: 40.54987939999999, 14.2401657 | K26: =IFERROR(__xludf.DUMMYFUNCTION("SPLIT(J26,"", "")"),40.5498793999999) -> 40.549879 | L26: =IFERROR(__xludf.DUMMYFUNCTION("""COMPUTED_VALUE"""),14.2401657) -> 14.240166 | M26: =HYPERLINK("https://www.google.com/maps/search/"&ENCODEURL(A26&", "&21&", Italy")) -> https://www.google.com/maps/search/JK%20Place%20Capri%20%28Capri%29%2C%2021%2C%20Italy | N26: ChatGPT - https://chatgpt.com/c/6846f0da-7884-8009-ad13-dba01dfa021d | O26: ChatGPT Itinerary 1 | P26: =VLOOKUP(B26,$V$3:$W$100,2,0) -> Capri | Q26: =VLOOKUP(P26,$X$3:$Y$6,2,0)&", "&P26&", Italy" -> La Residenza, Capri, Italy | R26: =VLOOKUP(A26,'Travel Times'!$A$1:$E$1000,4,0) -> 23 mins | S26: =VLOOKUP(A26,'Travel Times'!$A$1:$E$1000,5,0) -> 8 mins
A27: La Fontelina (Capri) | B27: =substitute(RIGHT(A27,len(A27)-FIND("(",A27)),")","") -> Capri | C27: Beach Club | D27: ⛱️ | E27: Iconic beach club near Faraglioni rocks with chic loungers and fresh seafood. | F27: Lunch-only in summer; €190 p.p. min. spend in high season; shuttle boat returns 15:00–18:30. | G27: Beach: 9:00–19:00; Restaurant: 12:30–16:00 daily | H27: $200 for two | I27: Località Faraglioni, 80073 Capri NA, Italy | J27: 40.5434303, 14.2523999 | K27: =IFERROR(__xludf.DUMMYFUNCTION("SPLIT(J27,"", "")"),40.5434303) -> 40.54343 | L27: =IFERROR(__xludf.DUMMYFUNCTION("""COMPUTED_VALUE"""),14.2523999) -> 14.2524 | M27: =HYPERLINK("https://www.google.com/maps/search/"&ENCODEURL(A27&", "&21&", Italy")) -> https://www.google.com/maps/search/La%20Fontelina%20%28Capri%29%2C%2021%2C%20Italy | N27: ChatGPT - https://chatgpt.com/c/6846f0da-7884-8009-ad13-dba01dfa021d | O27: ChatGPT Itinerary 1 | P27: =VLOOKUP(B27,$V$3:$W$100,2,0) -> Capri | Q27: =VLOOKUP(P27,$X$3:$Y$6,2,0)&", "&P27&", Italy" -> La Residenza, Capri, Italy | R27: =VLOOKUP(A27,'Travel Times'!$A$1:$E$1000,4,0) -> 23 mins | S27: =VLOOKUP(A27,'Travel Times'!$A$1:$E$1000,5,0) -> 1 min
A28: Da Gelsomina (Capri) | B28: =substitute(RIGHT(A28,len(A28)-FIND("(",A28)),")","") -> Capri | C28: Restaurant | D28: 🍷 | E28: Charming vineyard-side restaurant in Anacapri with local dishes and wine. | F28: Hilltop Anacapri vineyard spot; dress smart-casual. | G28: ~12:00–15:00 & 19:00–22:00 | H28: $100 for two | I28: Via Migliara, 72, 80071 Anacapri NA, Italy | J28: 40.5409493, 14.2102105 | K28: =IFERROR(__xludf.DUMMYFUNCTION("SPLIT(J28,"", "")"),40.5409493) -> 40.540949 | L28: =IFERROR(__xludf.DUMMYFUNCTION("""COMPUTED_VALUE"""),14.2102105) -> 14.210211 | M28: =HYPERLINK("https://www.google.com/maps/search/"&ENCODEURL(A28&", "&21&", Italy")) -> https://www.google.com/maps/search/Da%20Gelsomina%20%28Capri%29%2C%2021%2C%20Italy | N28: ChatGPT - https://chatgpt.com/c/6846f0da-7884-8009-ad13-dba01dfa021d | O28: ChatGPT Itinerary 1 | P28: =VLOOKUP(B28,$V$3:$W$100,2,0) -> Capri | Q28: =VLOOKUP(P28,$X$3:$Y$6,2,0)&", "&P28&", Italy" -> La Residenza, Capri, Italy | R28: =VLOOKUP(A28,'Travel Times'!$A$1:$E$1000,4,0) -> 1 hour 14 mins | S28: =VLOOKUP(A28,'Travel Times'!$A$1:$E$1000,5,0) -> 19 mins
A29: Belmond Hotel Caruso (Ravello) | B29: =substitute(RIGHT(A29,len(A29)-FIND("(",A29)),")","") -> Ravello | C29: Hotel | D29: 🏨 | E29: Historic palace hotel with an infinity pool overlooking the Amalfi Coast. | F29: Iconic infinity pool; spa and morning yoga available. | G29: Hotel: 24/7; Pool: 08:00–19:00 | H29: 5000 | I29: Piazza San Giovanni del Toro 2, 84010 Ravello (SA), Italy | J29: 40.6514101, 14.6129723 | K29: =IFERROR(__xludf.DUMMYFUNCTION("SPLIT(J29,"", "")"),40.6514101) -> 40.65141 | L29: =IFERROR(__xludf.DUMMYFUNCTION("""COMPUTED_VALUE"""),14.6129723) -> 14.612972 | M29: =HYPERLINK("https://www.google.com/maps/search/"&ENCODEURL(A29&", "&21&", Italy")) -> https://www.google.com/maps/search/Belmond%20Hotel%20Caruso%20%28Ravello%29%2C%2021%2C%20Italy | N29: ChatGPT - https://chatgpt.com/c/6846f0da-7884-8009-ad13-dba01dfa021d | O29: ChatGPT Itinerary 1 | P29: =VLOOKUP(B29,$V$3:$W$100,2,0) -> Ravello | Q29: =VLOOKUP(P29,$X$3:$Y$6,2,0)&", "&P29&", Italy" -> Hotel Rufolo, Ravello, Italy | R29: =VLOOKUP(A29,'Travel Times'!$A$1:$E$1000,4,0) -> 8 mins | S29: =VLOOKUP(A29,'Travel Times'!$A$1:$E$1000,5,0) -> 3 mins
A30: Villa Maria Ravello | B30: Ravello | C30: Hotel | D30: 🏨 | E30: Peaceful hotel with garden terraces and a focus on local cuisine. | F30: Quiet boutique hotel; known for homegrown lemon-themed dishes. | G30: 24/7 (hotel); breakfast until ~10:30 | H30: $3000 for two | I30: Via Santa Chiara, 2, 84010 Ravello SA, Italy | J30: 40.6468104, 14.6103006 | K30: =IFERROR(__xludf.DUMMYFUNCTION("SPLIT(J30,"", "")"),40.6468104) -> 40.64681 | L30: =IFERROR(__xludf.DUMMYFUNCTION("""COMPUTED_VALUE"""),14.6103006) -> 14.610301 | M30: =HYPERLINK("https://www.google.com/maps/search/"&ENCODEURL(A30&", "&21&", Italy")) -> https://www.google.com/maps/search/Villa%20Maria%20Ravello%2C%2021%2C%20Italy | N30: ChatGPT - https://chatgpt.com/c/6846f0da-7884-8009-ad13-dba01dfa021d | O30: ChatGPT Itinerary 1 | P30: =VLOOKUP(B30,$V$3:$W$100,2,0) -> Ravello | Q30: =VLOOKUP(P30,$X$3:$Y$6,2,0)&", "&P30&", Italy" -> Hotel Rufolo, Ravello, Italy | R30: =VLOOKUP(A30,'Travel Times'!$A$1:$E$1000,4,0) -> 4 mins | S30: =VLOOKUP(A30,'Travel Times'!$A$1:$E$1000,5,0) -> 1 min
A31: Villa Rufolo (Ravello) | B31: =substitute(RIGHT(A31,len(A31)-FIND("(",A31)),")","") -> Ravello | C31: Attraction | D31: 🏛️ | E31: Historic villa and gardens with panoramic views and concerts. | F31: Historic gardens with panoramic terrace; host of summer music festivals. | G31: Gardens: ~09:00–19:00 | H31: $120 for two | I31: Piazza Duomo, 84010 Ravello (SA), Italy | J31: 40.6491825, 14.6116481 | K31: =IFERROR(__xludf.DUMMYFUNCTION("SPLIT(J31,"", "")"),40.6491825) -> 40.649183 | L31: =IFERROR(__xludf.DUMMYFUNCTION("""COMPUTED_VALUE"""),14.6116481) -> 14.611648 | M31: =HYPERLINK("https://www.google.com/maps/search/"&ENCODEURL(A31&", "&21&", Italy")) -> https://www.google.com/maps/search/Villa%20Rufolo%20%28Ravello%29%2C%2021%2C%20Italy | N31: ChatGPT - https://chatgpt.com/c/6846f0da-7884-8009-ad13-dba01dfa021d | O31: ChatGPT Itinerary 1 | P31: =VLOOKUP(B31,$V$3:$W$100,2,0) -> Ravello | Q31: =VLOOKUP(P31,$X$3:$Y$6,2,0)&", "&P31&", Italy" -> Hotel Rufolo, Ravello, Italy | R31: =VLOOKUP(A31,'Travel Times'!$A$1:$E$1000,4,0) -> 2 mins | S31: =VLOOKUP(A31,'Travel Times'!$A$1:$E$1000,5,0) -> 1 min
A32: Wagner Tours (Wine Experience, Ravello) | B32: =substitute(RIGHT(A32,len(A32)-FIND("(",A32)),")","") -> Wine Experience, Ravello | C32: Wine Tour | D32: 🍇 | E32: Guided wine experiences and tastings in Ravello. | F32: Boutique, garden-based tastings; reserve in advance. | G32: Wine tastings by appointment (~11:00–17:00) | H32: $200 for two | I32: Via del Santuario, 84010 Ravello SA, Italy | J32: 40.6515802, 14.6140606 | K32: =IFERROR(__xludf.DUMMYFUNCTION("SPLIT(J32,"", "")"),40.6515802) -> 40.65158 | L32: =IFERROR(__xludf.DUMMYFUNCTION("""COMPUTED_VALUE"""),14.6140606) -> 14.614061 | M32: =HYPERLINK("https://www.google.com/maps/search/"&ENCODEURL(A32&", "&21&", Italy")) -> https://www.google.com/maps/search/Wagner%20Tours%20%28Wine%20Experience%2C%20Ravello%29%2C%2021%2C%20Italy | N32: ChatGPT - https://chatgpt.com/c/6846f0da-7884-8009-ad13-dba01dfa021d | O32: ChatGPT Itinerary 1 | P32: =VLOOKUP(B32,$V$3:$W$100,2,0) -> Ravello | Q32: =VLOOKUP(P32,$X$3:$Y$6,2,0)&", "&P32&", Italy" -> Hotel Rufolo, Ravello, Italy | R32: =VLOOKUP(A32,'Travel Times'!$A$1:$E$1000,4,0) -> 1 min | S32: =VLOOKUP(A32,'Travel Times'!$A$1:$E$1000,5,0) -> 1 min
A33: Rossellinis at Palazzo Avino (Ravello) | B33: =substitute(RIGHT(A33,len(A33)-FIND("(",A33)),")","") -> Ravello | C33: Restaurant | D33: 🍽️ | E33: Michelin-starred restaurant with romantic cliffside dining. | F33: 1-Michelin star; dress upscale; Chef’s & Sommelier’s Tables available. | G33: Lunch: 12:30–17:00; Dinner: 18:30–22:30; closed Nov–Mar | H33: $400 for two | I33: Via San Giovanni del Toro, 84010 Ravello SA, Italy | J33: 40.6504913, 14.6129035 | K33: =IFERROR(__xludf.DUMMYFUNCTION("SPLIT(J33,"", "")"),40.6504913) -> 40.650491 | L33: =IFERROR(__xludf.DUMMYFUNCTION("""COMPUTED_VALUE"""),14.6129035) -> 14.612903 | M33: =HYPERLINK("https://www.google.com/maps/search/"&ENCODEURL(A33&", "&21&", Italy")) -> https://www.google.com/maps/search/Rossellinis%20at%20Palazzo%20Avino%20%28Ravello%29%2C%2021%2C%20Italy | N33: ChatGPT - https://chatgpt.com/c/6846f0da-7884-8009-ad13-dba01dfa021d | O33: ChatGPT Itinerary 1 | P33: =VLOOKUP(B33,$V$3:$W$100,2,0) -> Ravello | Q33: =VLOOKUP(P33,$X$3:$Y$6,2,0)&", "&P33&", Italy" -> Hotel Rufolo, Ravello, Italy | R33: =VLOOKUP(A33,'Travel Times'!$A$1:$E$1000,4,0) -> 8 mins | S33: =VLOOKUP(A33,'Travel Times'!$A$1:$E$1000,5,0) -> 2 mins
A34: Casa Angelina (Praiano) | B34: =substitute(RIGHT(A34,len(A34)-FIND("(",A34)),")","") -> Praiano | C34: Hotel | D34: 🏨 | E34: Minimalist, adults-only luxury hotel with modern art and sea views. | F34: Adults-only, minimalist luxury; great for spa days and rooftop cocktails. | G34: Hotel: 24/7; Pool: ~08:00–19:00 | H34: $5000 for two | I34: Piazza Antiche Mura, 22, 84010 Praiano SA, Italy | J34: 40.6117319, 14.5335099 | K34: =IFERROR(__xludf.DUMMYFUNCTION("SPLIT(J34,"", "")"),40.6117319) -> 40.611732 | L34: =IFERROR(__xludf.DUMMYFUNCTION("""COMPUTED_VALUE"""),14.5335099) -> 14.53351 | M34: =HYPERLINK("https://www.google.com/maps/search/"&ENCODEURL(A34&", "&21&", Italy")) -> https://www.google.com/maps/search/Casa%20Angelina%20%28Praiano%29%2C%2021%2C%20Italy | N34: ChatGPT - https://chatgpt.com/c/6846f0da-7884-8009-ad13-dba01dfa021d | O34: ChatGPT Itinerary 1 | P34: =VLOOKUP(B34,$V$3:$W$100,2,0) -> Positano | Q34: =VLOOKUP(P34,$X$3:$Y$6,2,0)&", "&P34&", Italy" -> Hotel Savoia, Positano, Italy | R34: =VLOOKUP(A34,'Travel Times'!$A$1:$E$1000,4,0) -> 1 hour 21 mins | S34: =VLOOKUP(A34,'Travel Times'!$A$1:$E$1000,5,0) -> 13 mins
A35: Monastero Santa Rosa Hotel (Conca dei Marini) | B35: =substitute(RIGHT(A35,len(A35)-FIND("(",A35)),")","") -> Conca dei Marini | C35: Hotel | D35: 🏨 | E35: 5-star cliffside monastery-turned-hotel with a world-class spa. | F35: Ex-monastery with cliffside spa; Il Refettorio located onsite. | G35: Hotel: 24/7; Spa & pool open ~09:00–19:00 | H35: 3000 | I35: Via Krupp, 11, 84010 Conca dei Marini SA, Italy | J35: 40.6163236, 14.5753912 | K35: =IFERROR(__xludf.DUMMYFUNCTION("SPLIT(J35,"", "")"),40.6163236) -> 40.616324 | L35: =IFERROR(__xludf.DUMMYFUNCTION("""COMPUTED_VALUE"""),14.5753912) -> 14.575391 | M35: =HYPERLINK("https://www.google.com/maps/search/"&ENCODEURL(A35&", "&21&", Italy")) -> https://www.google.com/maps/search/Monastero%20Santa%20Rosa%20Hotel%20%28Conca%20dei%20Marini%29%2C%2021%2C%20Italy | N35: ChatGPT - https://chatgpt.com/c/6846f0da-7884-8009-ad13-dba01dfa021d | O35: ChatGPT Itinerary 1 | P35: =VLOOKUP(B35,$V$3:$W$100,2,0) -> Positano | Q35: =VLOOKUP(P35,$X$3:$Y$6,2,0)&", "&P35&", Italy" -> Hotel Savoia, Positano, Italy | R35: =VLOOKUP(A35,'Travel Times'!$A$1:$E$1000,4,0) -> 4 hours 42 mins | S35: =VLOOKUP(A35,'Travel Times'!$A$1:$E$1000,5,0) -> 39 mins
A36: One Fire Beach Club (Praiano) | B36: =substitute(RIGHT(A36,len(A36)-FIND("(",A36)),")","") -> Praiano | C36: Beach Club | D36: ⛱️ | E36: Laid-back beach club known for music, fire shows, and chill vibes. | F36: Casual beach club with fire shows & DJ sets; bring cash. | G36: ~09:00–18:00 | H36: $200 for two | I36: Marina di Praia, 84017 Praiano SA, Italy | J36: 40.6134729, 14.5394424 | K36: =IFERROR(__xludf.DUMMYFUNCTION("SPLIT(J36,"", "")"),40.6134729) -> 40.613473 | L36: =IFERROR(__xludf.DUMMYFUNCTION("""COMPUTED_VALUE"""),14.5394424) -> 14.539442 | M36: =HYPERLINK("https://www.google.com/maps/search/"&ENCODEURL(A36&", "&21&", Italy")) -> https://www.google.com/maps/search/One%20Fire%20Beach%20Club%20%28Praiano%29%2C%2021%2C%20Italy | N36: ChatGPT - https://chatgpt.com/c/6846f0da-7884-8009-ad13-dba01dfa021d | O36: ChatGPT Itinerary 1 | P36: =VLOOKUP(B36,$V$3:$W$100,2,0) -> Positano | Q36: =VLOOKUP(P36,$X$3:$Y$6,2,0)&", "&P36&", Italy" -> Hotel Savoia, Positano, Italy | R36: =VLOOKUP(A36,'Travel Times'!$A$1:$E$1000,4,0) -> 1 hour 27 mins | S36: =VLOOKUP(A36,'Travel Times'!$A$1:$E$1000,5,0) -> 13 mins
A37: Lido degli Artisti (Praiano) | B37: =substitute(RIGHT(A37,len(A37)-FIND("(",A37)),")","") -> Praiano | C37: Beach Club | D37: ⛱️ | E37: Cozy beach with sunbeds and a dramatic cliff backdrop. | F37: Cliffside sunbeds for rent; small snack kiosk; relaxed vibe. | G37: ~09:00–18:00 | H37: $500 for two | I37: Località La Gavitella, 84017 Praiano SA, Italy | J37: 40.6138362, 14.5204525 | K37: =IFERROR(__xludf.DUMMYFUNCTION("SPLIT(J37,"", "")"),40.6138362) -> 40.613836 | L37: =IFERROR(__xludf.DUMMYFUNCTION("""COMPUTED_VALUE"""),14.5204525) -> 14.520452 | M37: =HYPERLINK("https://www.google.com/maps/search/"&ENCODEURL(A37&", "&21&", Italy")) -> https://www.google.com/maps/search/Lido%20degli%20Artisti%20%28Praiano%29%2C%2021%2C%20Italy | N37: ChatGPT - https://chatgpt.com/c/6846f0da-7884-8009-ad13-dba01dfa021d | O37: ChatGPT Itinerary 1 | P37: =VLOOKUP(B37,$V$3:$W$100,2,0) -> Positano | Q37: =VLOOKUP(P37,$X$3:$Y$6,2,0)&", "&P37&", Italy" -> Hotel Savoia, Positano, Italy | R37: =VLOOKUP(A37,'Travel Times'!$A$1:$E$1000,4,0) -> 4 hours 40 mins | S37: =VLOOKUP(A37,'Travel Times'!$A$1:$E$1000,5,0) -> 38 mins
A38: Il Refettorio (Monastero Santa Rosa) | B38: =substitute(RIGHT(A38,len(A38)-FIND("(",A38)),")","") -> Monastero Santa Rosa | C38: Restaurant | D38: 🍽️ | E38: Michelin-starred dining within the Monastero Santa Rosa Hotel. | F38: Michelin-starred in monastery; dress smart-casual, reservations required. | G38: Dinner only, ~19:00–22:00 | H38: $200 for two | I38: Via Krupp, 11, 84010 Conca dei Marini SA, Italy | J38: 40.6163236, 14.5753912 | K38: =IFERROR(__xludf.DUMMYFUNCTION("SPLIT(J38,"", "")"),40.6163236) -> 40.616324 | L38: =IFERROR(__xludf.DUMMYFUNCTION("""COMPUTED_VALUE"""),14.5753912) -> 14.575391 | M38: =HYPERLINK("https://www.google.com/maps/search/"&ENCODEURL(A38&", "&21&", Italy")) -> https://www.google.com/maps/search/Il%20Refettorio%20%28Monastero%20Santa%20Rosa%29%2C%2021%2C%20Italy | N38: ChatGPT - https://chatgpt.com/c/6846f0da-7884-8009-ad13-dba01dfa021d | O38: ChatGPT Itinerary 1 | P38: =VLOOKUP(B38,$V$3:$W$100,2,0) -> Positano | Q38: =VLOOKUP(P38,$X$3:$Y$6,2,0)&", "&P38&", Italy" -> Hotel Savoia, Positano, Italy | R38: =VLOOKUP(A38,'Travel Times'!$A$1:$E$1000,4,0) -> 4 hours 42 mins | S38: =VLOOKUP(A38,'Travel Times'!$A$1:$E$1000,5,0) -> 39 mins
A39: Kasai (Praiano) | B39: =substitute(RIGHT(A39,len(A39)-FIND("(",A39)),")","") -> Praiano | C39: Restaurant | D39: 🍝 | E39: Locally loved spot with fresh seafood and sunset views. | F39: Fresh seafood & sushi fusion; sunset tables book fast. | G39: ~12:00–15:00 & 19:00–22:00 | H39: $2000 for two | I39: Via G. Capriglione, 2, 84017 Praiano SA, Italy | J39: 40.6087328, 14.5268626 | K39: =IFERROR(__xludf.DUMMYFUNCTION("SPLIT(J39,"", "")"),40.6087328) -> 40.608733 | L39: =IFERROR(__xludf.DUMMYFUNCTION("""COMPUTED_VALUE"""),14.5268626) -> 14.526863 | M39: =HYPERLINK("https://www.google.com/maps/search/"&ENCODEURL(A39&", "&21&", Italy")) -> https://www.google.com/maps/search/Kasai%20%28Praiano%29%2C%2021%2C%20Italy | N39: ChatGPT - https://chatgpt.com/c/6846f0da-7884-8009-ad13-dba01dfa021d | O39: ChatGPT Itinerary 1 | P39: =VLOOKUP(B39,$V$3:$W$100,2,0) -> Positano | Q39: =VLOOKUP(P39,$X$3:$Y$6,2,0)&", "&P39&", Italy" -> Hotel Savoia, Positano, Italy | R39: =VLOOKUP(A39,'Travel Times'!$A$1:$E$1000,4,0) -> 1 hour 42 mins | S39: =VLOOKUP(A39,'Travel Times'!$A$1:$E$1000,5,0) -> 15 mins
A40: La Tagliata (Positano) | B40: =substitute(RIGHT(A40,len(A40)-FIND("(",A40)),")","") -> Positano | C40: Cooking Class | D40: 👩‍🍳 | E40: Rustic, family-run restaurant offering fun and hearty cooking classes. | F40: Rustic family meal & cooking class; farm-fresh ingredients; open-air terrace. | G40: Lunch & Dinner (check seasonally) | H40: $150 for two | I40: Via Tagliata, 1, 84017 Positano SA, Italy | J40: 40.6332256, 14.4930882 | K40: =IFERROR(__xludf.DUMMYFUNCTION("SPLIT(J40,"", "")"),40.6332256) -> 40.633226 | L40: =IFERROR(__xludf.DUMMYFUNCTION("""COMPUTED_VALUE"""),14.4930882) -> 14.493088 | M40: =HYPERLINK("https://www.google.com/maps/search/"&ENCODEURL(A40&", "&21&", Italy")) -> https://www.google.com/maps/search/La%20Tagliata%20%28Positano%29%2C%2021%2C%20Italy | N40: ChatGPT - https://chatgpt.com/c/6846f0da-7884-8009-ad13-dba01dfa021d | O40: ChatGPT Itinerary 1 | P40: =VLOOKUP(B40,$V$3:$W$100,2,0) -> Positano | Q40: =VLOOKUP(P40,$X$3:$Y$6,2,0)&", "&P40&", Italy" -> Hotel Savoia, Positano, Italy | R40: =VLOOKUP(A40,'Travel Times'!$A$1:$E$1000,4,0) -> 47 mins | S40: =VLOOKUP(A40,'Travel Times'!$A$1:$E$1000,5,0) -> 17 mins
A41: Mamma Agata (Ravello) | B41: =substitute(RIGHT(A41,len(A41)-FIND("(",A41)),")","") -> Ravello | C41: Cooking Class | D41: 👩‍🍳 | E41: Charming home-based cooking school with sea views and legendary hosts. | F41: Home-style cooking in a villa garden; traditional Amalfi recipes. | G41: Lunch only (~12:00–14:30); closed Sun & Mon | H41: $200 for two | I41: Via San Francesco, 24, 84010 Ravello SA, Italy | J41: 40.6484534, 14.6118254 | K41: =IFERROR(__xludf.DUMMYFUNCTION("SPLIT(J41,"", "")"),40.6484534) -> 40.648453 | L41: =IFERROR(__xludf.DUMMYFUNCTION("""COMPUTED_VALUE"""),14.6118254) -> 14.611825 | M41: =HYPERLINK("https://www.google.com/maps/search/"&ENCODEURL(A41&", "&21&", Italy")) -> https://www.google.com/maps/search/Mamma%20Agata%20%28Ravello%29%2C%2021%2C%20Italy | N41: ChatGPT - https://chatgpt.com/c/6846f0da-7884-8009-ad13-dba01dfa021d | O41: ChatGPT Itinerary 1 | P41: =VLOOKUP(B41,$V$3:$W$100,2,0) -> Ravello | Q41: =VLOOKUP(P41,$X$3:$Y$6,2,0)&", "&P41&", Italy" -> Hotel Rufolo, Ravello, Italy | R41: =VLOOKUP(A41,'Travel Times'!$A$1:$E$1000,4,0) -> 12 mins | S41: =VLOOKUP(A41,'Travel Times'!$A$1:$E$1000,5,0) -> 5 mins
A42: Franco’s Bar (Positano) | B42: =substitute(RIGHT(A42,len(A42)-FIND("(",A42)),")","") -> Positano | C42: Bar | D42: 🍹 | E42: Trendy cocktail bar with jaw-dropping sunset views. | F42: Sunset cocktails with panoramic views; arrive early for best seats. | G42: ~16:00–00:00 | H42: $100 for two | I42: Via Pasitea, 300, 84017 Positano SA, Italy | J42: 40.6287893, 14.4815807 | K42: =IFERROR(__xludf.DUMMYFUNCTION("SPLIT(J42,"", "")"),40.6287893) -> 40.628789 | L42: =IFERROR(__xludf.DUMMYFUNCTION("""COMPUTED_VALUE"""),14.4815807) -> 14.481581 | M42: =HYPERLINK("https://www.google.com/maps/search/"&ENCODEURL(A42&", "&21&", Italy")) -> https://www.google.com/maps/search/Franco%E2%80%99s%20Bar%20%28Positano%29%2C%2021%2C%20Italy | N42: ChatGPT - https://chatgpt.com/c/6846f0da-7884-8009-ad13-dba01dfa021d | O42: ChatGPT Itinerary 1 | P42: =VLOOKUP(B42,$V$3:$W$100,2,0) -> Positano | Q42: =VLOOKUP(P42,$X$3:$Y$6,2,0)&", "&P42&", Italy" -> Hotel Savoia, Positano, Italy | R42: =VLOOKUP(A42,'Travel Times'!$A$1:$E$1000,4,0) -> 3 mins | S42: =VLOOKUP(A42,'Travel Times'!$A$1:$E$1000,5,0) -> 1 min
A43: Ristorante Il Pirata (Praiano) | B43: =substitute(RIGHT(A43,len(A43)-FIND("(",A43)),")","") -> Praiano | C43: Restaurant | D43: 🍽️ | E43: Dramatic sea cave restaurant serving fresh Mediterranean dishes. | F43: Dining in a seaside grotto; perfect at golden hour; reserve ahead. | G43: Lunch: 12:00–15:00; Dinner: 19:00–22:30 | H43: $150 for two | I43: Via Marina di Praia, 2, 84017 Praiano SA, Italy | J43: 40.6142489, 14.5392983 | K43: =IFERROR(__xludf.DUMMYFUNCTION("SPLIT(J43,"", "")"),40.6142489) -> 40.614249 | L43: =IFERROR(__xludf.DUMMYFUNCTION("""COMPUTED_VALUE"""),14.5392983) -> 14.539298 | M43: =HYPERLINK("https://www.google.com/maps/search/"&ENCODEURL(A43&", "&21&", Italy")) -> https://www.google.com/maps/search/Ristorante%20Il%20Pirata%20%28Praiano%29%2C%2021%2C%20Italy | N43: ChatGPT - https://chatgpt.com/c/6846f0da-7884-8009-ad13-dba01dfa021d | O43: ChatGPT Itinerary 1 | P43: =VLOOKUP(B43,$V$3:$W$100,2,0) -> Positano | Q43: =VLOOKUP(P43,$X$3:$Y$6,2,0)&", "&P43&", Italy" -> Hotel Savoia, Positano, Italy | R43: =VLOOKUP(A43,'Travel Times'!$A$1:$E$1000,4,0) -> 2 hours 0 mins | S43: =VLOOKUP(A43,'Travel Times'!$A$1:$E$1000,5,0) -> 20 mins
A44: Romeo Hotel Naples | B44: Naples | C44: Hotel | D44: 🏨 | E44: Luxury waterfront hotel with Michelin-starred dining, panoramic views of Bay of Naples and Vesuvius, modern design with sophisticated atmosphere | F44: Perfect for arrival/departure convenience, has Michelin dining on-site | G44: Check-in: 3:00 PM, Check-out: 11:00 AM | H44: 2000 | I44: Via Cristoforo Colombo, 45, 80133 Napoli NA, Italy | J44: 40.8403661, 14.2558654 | K44: 40.840366 | L44: 14.255865 | M44: =HYPERLINK("https://www.google.com/maps/search/"&ENCODEURL(A44)) -> https://www.google.com/maps/search/Romeo%20Hotel%20Naples | N44: Manus - https://manus.im/app/KJC6Ixn9ZFEgpriWR1GDzd | O44: Manus Itinerary 1 | P44: =VLOOKUP(B44,$V$3:$W$100,2,0) -> Naples | Q44: =VLOOKUP(P44,$X$3:$Y$6,2,0)&", "&P44&", Italy" -> Relais sul Mare Boutique Hotel, Naples, Italy | R44: =VLOOKUP(A44,'Travel Times'!$A$1:$E$1000,4,0) -> 19 mins | S44: =VLOOKUP(A44,'Travel Times'!$A$1:$E$1000,5,0) -> 9 mins
A45: Spaccanapoli | B45: Naples | C45: Historic Street | D45: 🏛️ | E45: Ancient Roman road cutting through Naples historic center, UNESCO World Heritage site | F45: Walk the entire length for authentic Naples experience | G45: Always open | H45: 2000 | I45: Naples, Metropolitan City of Naples, Italy | J45: 40.8517746, 14.2681244 | K45: 40.851775 | L45: 14.268124 | M45: =HYPERLINK("https://www.google.com/maps/search/"&ENCODEURL(A45)) -> https://www.google.com/maps/search/Spaccanapoli | N45: Manus - https://manus.im/app/KJC6Ixn9ZFEgpriWR1GDzd | O45: Manus Itinerary 1 | P45: =VLOOKUP(B45,$V$3:$W$100,2,0) -> Naples | Q45: =VLOOKUP(P45,$X$3:$Y$6,2,0)&", "&P45&", Italy" -> Relais sul Mare Boutique Hotel, Naples, Italy | R45: =VLOOKUP(A45,'Travel Times'!$A$1:$E$1000,4,0) -> 41 mins | S45: =VLOOKUP(A45,'Travel Times'!$A$1:$E$1000,5,0) -> 14 mins
A46: Naples Cathedral (Duomo) | B46: Naples | C46: Cathedral | D46: ⛪ | E46: Historic cathedral with San Gennaro chapel, beautiful architecture | F46: Free entry, dress modestly | G46: 8:00 AM - 12:30 PM, 4:30 PM - 7:00 PM | H46: $200 for two | I46: Vico Sedil Capuano, 48, 80138 Napoli NA, Italy | J46: 40.8531893, 14.2603334 | K46: 40.853189 | L46: 14.260333 | M46: =HYPERLINK("https://www.google.com/maps/search/"&ENCODEURL(A46)) -> https://www.google.com/maps/search/Naples%20Cathedral%20%28Duomo%29 | N46: Manus - https://manus.im/app/KJC6Ixn9ZFEgpriWR1GDzd | O46: Manus Itinerary 1 | P46: =VLOOKUP(B46,$V$3:$W$100,2,0) -> Naples | Q46: =VLOOKUP(P46,$X$3:$Y$6,2,0)&", "&P46&", Italy" -> Relais sul Mare Boutique Hotel, Naples, Italy | R46: =VLOOKUP(A46,'Travel Times'!$A$1:$E$1000,4,0) -> 43 mins | S46: =VLOOKUP(A46,'Travel Times'!$A$1:$E$1000,5,0) -> 13 mins
A47: San Gregorio Armeno | B47: Naples | C47: Artisan Street | D47: 🎨 | E47: Christmas artisan street with traditional Neapolitan nativity scenes | F47: Famous for handmade nativity figures year-round | G47: 9:00 AM - 7:00 PM | H47: 600 | I47: Via S. Gregorio Armeno, 80138 Napoli NA, Italy | J47: 40.8500804, 14.2578099 | K47: 40.85008 | L47: 14.25781 | M47: =HYPERLINK("https://www.google.com/maps/search/"&ENCODEURL(A47)) -> https://www.google.com/maps/search/San%20Gregorio%20Armeno | N47: Manus - https://manus.im/app/KJC6Ixn9ZFEgpriWR1GDzd | O47: Manus Itinerary 1 | P47: =VLOOKUP(B47,$V$3:$W$100,2,0) -> Naples | Q47: =VLOOKUP(P47,$X$3:$Y$6,2,0)&", "&P47&", Italy" -> Relais sul Mare Boutique Hotel, Naples, Italy | R47: =VLOOKUP(A47,'Travel Times'!$A$1:$E$1000,4,0) -> 39 mins | S47: =VLOOKUP(A47,'Travel Times'!$A$1:$E$1000,5,0) -> 18 mins
A48: Piazza del Gesù Nuovo | B48: Naples | C48: Historic Square | D48: 🏛️ | E48: Beautiful baroque square with historic churches | F48: Great for people watching and photos | G48: Always open | H48: 1200 | I48: Piazza del Gesù Nuovo, 80134 Napoli NA, Italy | J48: 40.8469688, 14.2517718 | K48: 40.846969 | L48: 14.251772 | M48: =HYPERLINK("https://www.google.com/maps/search/"&ENCODEURL(A48)) -> https://www.google.com/maps/search/Piazza%20del%20Ges%C3%B9%20Nuovo | N48: Manus - https://manus.im/app/KJC6Ixn9ZFEgpriWR1GDzd | O48: Manus Itinerary 1 | P48: =VLOOKUP(B48,$V$3:$W$100,2,0) -> Naples | Q48: =VLOOKUP(P48,$X$3:$Y$6,2,0)&", "&P48&", Italy" -> Relais sul Mare Boutique Hotel, Naples, Italy | R48: =VLOOKUP(A48,'Travel Times'!$A$1:$E$1000,4,0) -> 30 mins | S48: =VLOOKUP(A48,'Travel Times'!$A$1:$E$1000,5,0) -> 9 mins
A49: La Locanda Gesù Vecchio | B49: Naples | C49: Restaurant | D49: 🍝 | E49: Family-run trattoria near Piazza del Gesù, rustic yet refined atmosphere, warm hospitality | F49: Must-try: Paccheri al ragù napoletano, owner brings complimentary wine, feels like dining in someone's home | G49: Dinner: 7:00 PM - 11:00 PM | H49: $100 for two | I49: Via Giovanni Paladino, 26, 80138 Napoli NA, Italy | J49: 40.8472376, 14.2571481 | K49: 40.847238 | L49: 14.257148 | M49: =HYPERLINK("https://www.google.com/maps/search/"&ENCODEURL(A49)) -> https://www.google.com/maps/search/La%20Locanda%20Ges%C3%B9%20Vecchio | N49: Manus - https://manus.im/app/KJC6Ixn9ZFEgpriWR1GDzd | O49: Manus Itinerary 1 | P49: =VLOOKUP(B49,$V$3:$W$100,2,0) -> Naples | Q49: =VLOOKUP(P49,$X$3:$Y$6,2,0)&", "&P49&", Italy" -> Relais sul Mare Boutique Hotel, Naples, Italy | R49: =VLOOKUP(A49,'Travel Times'!$A$1:$E$1000,4,0) -> 38 mins | S49: =VLOOKUP(A49,'Travel Times'!$A$1:$E$1000,5,0) -> 12 mins
A50: Palazzo Petrucci | B50: Naples | C50: Fine Dining Restaurant | D50: 🍽️ | E50: Posillipo location with Gulf of Naples views, modern Italian cuisine with dramatic presentation | F50: Sea urchin risotto served in spiny shell, fine dining alternative | G50: Dinner: 7:30 PM - 11:00 PM | H50: $200 for two | I50: P.za S. Domenico Maggiore, 33, 80134 Napoli NA, Italy | J50: 40.8483036, 14.254577 | K50: 40.848304 | L50: 14.254577 | M50: =HYPERLINK("https://www.google.com/maps/search/"&ENCODEURL(A50)) -> https://www.google.com/maps/search/Palazzo%20Petrucci | N50: Manus - https://manus.im/app/KJC6Ixn9ZFEgpriWR1GDzd | O50: Manus Itinerary 1 | P50: =VLOOKUP(B50,$V$3:$W$100,2,0) -> Naples | Q50: =VLOOKUP(P50,$X$3:$Y$6,2,0)&", "&P50&", Italy" -> Relais sul Mare Boutique Hotel, Naples, Italy | R50: =VLOOKUP(A50,'Travel Times'!$A$1:$E$1000,4,0) -> 34 mins | S50: =VLOOKUP(A50,'Travel Times'!$A$1:$E$1000,5,0) -> 9 mins
A51: Veritas | B51: Naples | C51: Fine Dining Restaurant | D51: ⭐ | E51: Cerebral, meticulous cuisine with multiple tasting menus, wine pairings from Campania producers | F51: Artistic presentation, book 2-4 weeks advance | G51: Dinner: 7:30 PM - 11:00 PM | H51: 2000 | I51: C.so Vittorio Emanuele, 141, 80121 Napoli NA, Italy | J51: 40.8372389, 14.2313759 | K51: 40.837239 | L51: 14.231376 | M51: =HYPERLINK("https://www.google.com/maps/search/"&ENCODEURL(A51)) -> https://www.google.com/maps/search/Veritas | N51: Manus - https://manus.im/app/KJC6Ixn9ZFEgpriWR1GDzd | O51: Manus Itinerary 1 | P51: =VLOOKUP(B51,$V$3:$W$100,2,0) -> Naples | Q51: =VLOOKUP(P51,$X$3:$Y$6,2,0)&", "&P51&", Italy" -> Relais sul Mare Boutique Hotel, Naples, Italy | R51: =VLOOKUP(A51,'Travel Times'!$A$1:$E$1000,4,0) -> 37 mins | S51: =VLOOKUP(A51,'Travel Times'!$A$1:$E$1000,5,0) -> 10 mins
A52: Mimì alla Ferrovia | B52: Naples | C52: Traditional Restaurant | D52: 🍝 | E52: Operating since 1943, old-school Neapolitan elegance, classic atmosphere | F52: Classic ziti al ragù and parmigiana, traditional atmosphere | G52: Lunch & Dinner | H52: $150 for two | I52: Via Alfonso D'Aragona, 19/21, 80139 Napoli NA, Italy | J52: 40.8535418, 14.2671748 | K52: 40.853542 | L52: 14.267175 | M52: =HYPERLINK("https://www.google.com/maps/search/"&ENCODEURL(A52)) -> https://www.google.com/maps/search/Mim%C3%AC%20alla%20Ferrovia | N52: Manus - https://manus.im/app/KJC6Ixn9ZFEgpriWR1GDzd | O52: Manus Itinerary 1 | P52: =VLOOKUP(B52,$V$3:$W$100,2,0) -> Naples | Q52: =VLOOKUP(P52,$X$3:$Y$6,2,0)&", "&P52&", Italy" -> Relais sul Mare Boutique Hotel, Naples, Italy | R52: =VLOOKUP(A52,'Travel Times'!$A$1:$E$1000,4,0) -> 46 mins | S52: =VLOOKUP(A52,'Travel Times'!$A$1:$E$1000,5,0) -> 14 mins
A53: Caffè Gambrinus | B53: Naples | C53: Historic Café | D53: ☕ | F53: Perfect for final Naples coffee before departure | G53: 7:00 AM - 2:00 AM | H53: $100 for two | I53: Via Chiaia, 1, 80132 Napoli NA, Italy | J53: 40.8367945, 14.248479 | K53: 40.836795 | L53: 14.248479 | M53: =HYPERLINK("https://www.google.com/maps/search/"&ENCODEURL(A53)) -> https://www.google.com/maps/search/Caff%C3%A8%20Gambrinus | N53: Manus - https://manus.im/app/KJC6Ixn9ZFEgpriWR1GDzd | O53: Manus Itinerary 1 | P53: =VLOOKUP(B53,$V$3:$W$100,2,0) -> Naples | Q53: =VLOOKUP(P53,$X$3:$Y$6,2,0)&", "&P53&", Italy" -> Relais sul Mare Boutique Hotel, Naples, Italy | R53: =VLOOKUP(A53,'Travel Times'!$A$1:$E$1000,4,0) -> 12 mins | S53: =VLOOKUP(A53,'Travel Times'!$A$1:$E$1000,5,0) -> 10 mins
A54: Scaturchio | B54: Naples | C54: Pastry Shop | D54: 🥐 | E54: Famous pastry shop for traditional sfogliatelle | F54: Must-try: sfogliatelle, historic Naples institution | G54: 7:30 AM - 8:30 PM | H54: 2000 | I54: P.za S. Domenico Maggiore, 19, 80134 Napoli NA, Italy | J54: 40.8482509, 14.2549272 | K54: 40.848251 | L54: 14.254927 | M54: =HYPERLINK("https://www.google.com/maps/search/"&ENCODEURL(A54)) -> https://www.google.com/maps/search/Scaturchio | N54: Manus - https://manus.im/app/KJC6Ixn9ZFEgpriWR1GDzd | O54: Manus Itinerary 1 | P54: =VLOOKUP(B54,$V$3:$W$100,2,0) -> Naples | Q54: =VLOOKUP(P54,$X$3:$Y$6,2,0)&", "&P54&", Italy" -> Relais sul Mare Boutique Hotel, Naples, Italy | R54: =VLOOKUP(A54,'Travel Times'!$A$1:$E$1000,4,0) -> 44 mins | S54: =VLOOKUP(A54,'Travel Times'!$A$1:$E$1000,5,0) -> 11 mins
A55: National Archaeological Museum | B55: Naples | C55: Museum | D55: 🏛️ | E55: Houses Pompeii artifacts and ancient Roman treasures | F55: €15 entrance, world-class Pompeii collection | G55: 9:00 AM - 7:30 PM (closed Tuesdays) | H55: $200 for two | I55: Piazza Museo, 19, 80135 Napoli NA, Italy | J55: 40.8534745, 14.2512744 | K55: 40.853474 | L55: 14.251274 | M55: =HYPERLINK("https://www.google.com/maps/search/"&ENCODEURL(A55)) -> https://www.google.com/maps/search/National%20Archaeological%20Museum | N55: Manus - https://manus.im/app/KJC6Ixn9ZFEgpriWR1GDzd | O55: Manus Itinerary 1 | P55: =VLOOKUP(B55,$V$3:$W$100,2,0) -> Naples | Q55: =VLOOKUP(P55,$X$3:$Y$6,2,0)&", "&P55&", Italy" -> Relais sul Mare Boutique Hotel, Naples, Italy | R55: =VLOOKUP(A55,'Travel Times'!$A$1:$E$1000,4,0) -> 39 mins | S55: =VLOOKUP(A55,'Travel Times'!$A$1:$E$1000,5,0) -> 20 mins
A56: Palazzo Reale | B56: Naples | C56: Royal Palace | D56: 👑 | E56: Royal palace with gardens and historic rooms | F56: €4 entrance, beautiful royal apartments | G56: 9:00 AM - 8:00 PM (closed Wednesdays) | H56: $250 for two | I56: Piazza del Plebiscito, 1, 80132 Napoli NA, Italy | J56: 40.8369443, 14.2494124 | K56: 40.836944 | L56: 14.249412 | M56: =HYPERLINK("https://www.google.com/maps/search/"&ENCODEURL(A56)) -> https://www.google.com/maps/search/Palazzo%20Reale | N56: Manus - https://manus.im/app/KJC6Ixn9ZFEgpriWR1GDzd | O56: Manus Itinerary 1 | P56: =VLOOKUP(B56,$V$3:$W$100,2,0) -> Naples | Q56: =VLOOKUP(P56,$X$3:$Y$6,2,0)&", "&P56&", Italy" -> Relais sul Mare Boutique Hotel, Naples, Italy | R56: =VLOOKUP(A56,'Travel Times'!$A$1:$E$1000,4,0) -> 13 mins | S56: =VLOOKUP(A56,'Travel Times'!$A$1:$E$1000,5,0) -> 10 mins
A57: Castel dell'Ovo | B57: Naples | C57: Seaside Castle | D57: 🏰 | E57: Seaside castle with panoramic views of Bay of Naples | F57: Free entry, great for sunset photos | G57: 9:00 AM - 6:30 PM | H57: 500 | I57: Via Eldorado, 3, 80132 Napoli NA, Italy | J57: 40.8279173, 14.2484676 | K57: 40.827917 | L57: 14.248468 | M57: =HYPERLINK("https://www.google.com/maps/search/"&ENCODEURL(A57)) -> https://www.google.com/maps/search/Castel%20dell%27Ovo | N57: Manus - https://manus.im/app/KJC6Ixn9ZFEgpriWR1GDzd | O57: Manus Itinerary 1 | P57: =VLOOKUP(B57,$V$3:$W$100,2,0) -> Naples | Q57: =VLOOKUP(P57,$X$3:$Y$6,2,0)&", "&P57&", Italy" -> Relais sul Mare Boutique Hotel, Naples, Italy | R57: =VLOOKUP(A57,'Travel Times'!$A$1:$E$1000,4,0) -> 10 mins | S57: =VLOOKUP(A57,'Travel Times'!$A$1:$E$1000,5,0) -> 8 mins
A58: Via Toledo | B58: Naples | C58: Shopping Street | D58: 🛍️ | E58: Main shopping street with local and international brands | F58: Mix of shops and cafes, pedestrian-friendly | G58: 9:00 AM - 8:00 PM | H58: 2500 | I58: Via Toledo, Napoli NA, Italy | J58: 40.8428212, 14.248904 | K58: 40.842821 | L58: 14.248904 | M58: =HYPERLINK("https://www.google.com/maps/search/"&ENCODEURL(A58)) -> https://www.google.com/maps/search/Via%20Toledo | N58: Manus - https://manus.im/app/KJC6Ixn9ZFEgpriWR1GDzd | O58: Manus Itinerary 1 | P58: =VLOOKUP(B58,$V$3:$W$100,2,0) -> Naples | Q58: =VLOOKUP(P58,$X$3:$Y$6,2,0)&", "&P58&", Italy" -> Relais sul Mare Boutique Hotel, Naples, Italy | R58: =VLOOKUP(A58,'Travel Times'!$A$1:$E$1000,4,0) -> 21 mins | S58: =VLOOKUP(A58,'Travel Times'!$A$1:$E$1000,5,0) -> 12 mins
A59: Galleria Umberto I | B59: Naples | C59: Shopping Gallery | D59: 🏛️ | E59: Beautiful 19th-century shopping gallery with glass dome | F59: Architectural beauty, upscale shopping | G59: 9:00 AM - 8:00 PM | H59: $200 for two | I59: Galleria Umberto I, 80132 Napoli NA, Italy | J59: 40.8385287, 14.2494785 | K59: 40.838529 | L59: 14.249479 | M59: =HYPERLINK("https://www.google.com/maps/search/"&ENCODEURL(A59)) -> https://www.google.com/maps/search/Galleria%20Umberto%20I | N59: Manus - https://manus.im/app/KJC6Ixn9ZFEgpriWR1GDzd | O59: Manus Itinerary 1 | P59: =VLOOKUP(B59,$V$3:$W$100,2,0) -> Naples | Q59: =VLOOKUP(P59,$X$3:$Y$6,2,0)&", "&P59&", Italy" -> Relais sul Mare Boutique Hotel, Naples, Italy | R59: =VLOOKUP(A59,'Travel Times'!$A$1:$E$1000,4,0) -> 15 mins | S59: =VLOOKUP(A59,'Travel Times'!$A$1:$E$1000,5,0) -> 9 mins
A60: Casa d'Anna ai Cristallini | B60: Naples | C60: Boutique Hotel | D60: 🏨 | E60: Intimate boutique hotel in historic center | F60: Alternative to Romeo Hotel, more intimate setting | G60: Check-in: 2:00 PM, Check-out: 11:00 AM | H60: 1200 | I60: Via dei Cristallini, 138, 80137 Napoli NA, Italy | J60: 40.8575357, 14.2540213 | K60: 40.857536 | L60: 14.254021 | M60: =HYPERLINK("https://www.google.com/maps/search/"&ENCODEURL(A60)) -> https://www.google.com/maps/search/Casa%20d%27Anna%20ai%20Cristallini | N60: Manus - https://manus.im/app/KJC6Ixn9ZFEgpriWR1GDzd | O60: Manus Itinerary 1 | P60: =VLOOKUP(B60,$V$3:$W$100,2,0) -> Naples | Q60: =VLOOKUP(P60,$X$3:$Y$6,2,0)&", "&P60&", Italy" -> Relais sul Mare Boutique Hotel, Naples, Italy | R60: =VLOOKUP(A60,'Travel Times'!$A$1:$E$1000,4,0) -> 49 mins | S60: =VLOOKUP(A60,'Travel Times'!$A$1:$E$1000,5,0) -> 18 mins
A61: Naples Molo Beverello | B61: Naples | C61: Ferry Port | D61: ⛴️ | E61: Main ferry terminal for departures to Capri and Amalfi Coast | F61: Arrive 30 minutes early, buy tickets in advance | G61: Ferries: 6:20 AM - 7:20 PM | H61: 2000 | I61: Molo Beverello, 80133 Napoli NA, Italy | J61: 40.8382086, 14.2546268 | K61: 40.838209 | L61: 14.254627 | M61: =HYPERLINK("https://www.google.com/maps/search/"&ENCODEURL(A61)) -> https://www.google.com/maps/search/Naples%20Molo%20Beverello | N61: Manus - https://manus.im/app/KJC6Ixn9ZFEgpriWR1GDzd | O61: Manus Itinerary 1 | P61: =VLOOKUP(B61,$V$3:$W$100,2,0) -> Naples | Q61: =VLOOKUP(P61,$X$3:$Y$6,2,0)&", "&P61&", Italy" -> Relais sul Mare Boutique Hotel, Naples, Italy | R61: =VLOOKUP(A61,'Travel Times'!$A$1:$E$1000,4,0) -> 19 mins | S61: =VLOOKUP(A61,'Travel Times'!$A$1:$E$1000,5,0) -> 5 mins
A62: Naples International Airport (NAP) | B62: Naples | C62: Airport | D62: ✈️ | E62: Main airport serving Naples and Amalfi Coast region | F62: 30-40 minutes to city center by private transfer | G62: 24 hours | H62: 1200 | I62: Naples International Airport (NAP), Viale F. Ruffo di Calabria, 80144 Napoli NA, Italy | J62: 40.8846816, 14.2891552 | K62: 40.884682 | L62: 14.289155 | M62: =HYPERLINK("https://www.google.com/maps/search/"&ENCODEURL(A62)) -> https://www.google.com/maps/search/Naples%20International%20Airport%20%28NAP%29 | N62: Manus - https://manus.im/app/KJC6Ixn9ZFEgpriWR1GDzd | O62: Manus Itinerary 1 | P62: =VLOOKUP(B62,$V$3:$W$100,2,0) -> Naples | Q62: =VLOOKUP(P62,$X$3:$Y$6,2,0)&", "&P62&", Italy" -> Relais sul Mare Boutique Hotel, Naples, Italy | R62: =VLOOKUP(A62,'Travel Times'!$A$1:$E$1000,4,0) -> 1 hour 47 mins | S62: =VLOOKUP(A62,'Travel Times'!$A$1:$E$1000,5,0) -> 21 mins
A63: Hotel La Palma | B63: Capri | C63: Luxury Hotel | D63: 🏨 | E63: Newly opened 2023 Oetker Collection property, neoclassical design by Francis Sultana, revival of Capri's first hotel (built 1822) | F63: Opposite Dolce & Gabbana, has Da Gioia beach club, celebrity atmosphere | G63: Check-in: 3:00 PM, Check-out: 11:00 AM | H63: 3000 | I63: Via Vittorio Emanuele, 39, 80073 Capri NA, Italy | J63: 40.5503664, 14.2436652 | K63: 40.550366 | L63: 14.243665 | M63: =HYPERLINK("https://www.google.com/maps/search/"&ENCODEURL(A63)) -> https://www.google.com/maps/search/Hotel%20La%20Palma | N63: Manus - https://manus.im/app/KJC6Ixn9ZFEgpriWR1GDzd | O63: Manus Itinerary 1 | P63: =VLOOKUP(B63,$V$3:$W$100,2,0) -> Capri | Q63: =VLOOKUP(P63,$X$3:$Y$6,2,0)&", "&P63&", Italy" -> La Residenza, Capri, Italy | R63: =VLOOKUP(A63,'Travel Times'!$A$1:$E$1000,4,0) -> 3 mins | S63: =VLOOKUP(A63,'Travel Times'!$A$1:$E$1000,5,0) -> 1 min
A64: Capri Marina Grande | B64: Capri | C64: Ferry Port | D64: ⛴️ | E64: Main port for ferry arrivals and departures | F64: Take funicular to town center (5 minutes) | G64: Ferries: 6:30 AM - 7:50 PM | H64: $3000 for two | I64: 80076 Marina Grande, Metropolitan City of Naples, Italy | J64: 40.5533968, 14.2381784 | K64: 40.553397 | L64: 14.238178 | M64: =HYPERLINK("https://www.google.com/maps/search/"&ENCODEURL(A64)) -> https://www.google.com/maps/search/Capri%20Marina%20Grande | N64: Manus - https://manus.im/app/KJC6Ixn9ZFEgpriWR1GDzd | O64: Manus Itinerary 1 | P64: =VLOOKUP(B64,$V$3:$W$100,2,0) -> Capri | Q64: =VLOOKUP(P64,$X$3:$Y$6,2,0)&", "&P64&", Italy" -> La Residenza, Capri, Italy | R64: =VLOOKUP(A64,'Travel Times'!$A$1:$E$1000,4,0) -> 14 mins | S64: =VLOOKUP(A64,'Travel Times'!$A$1:$E$1000,5,0) -> 6 mins
A65: La Piazzetta | B65: Capri | C65: Famous Square | D65: 🏛️ | E65: Famous central square, people-watching hub, celebrity spotting | F65: Classic Capri atmosphere, aperitivo bars | G65: Always open | H65: $200 for two | I65: Via Longano, 14, 80073 Capri NA, Italy | J65: 40.551337, 14.2433926 | K65: 40.551337 | L65: 14.243393 | M65: =HYPERLINK("https://www.google.com/maps/search/"&ENCODEURL(A65)) -> https://www.google.com/maps/search/La%20Piazzetta | N65: Manus - https://manus.im/app/KJC6Ixn9ZFEgpriWR1GDzd | O65: Manus Itinerary 1 | P65: =VLOOKUP(B65,$V$3:$W$100,2,0) -> Capri | Q65: =VLOOKUP(P65,$X$3:$Y$6,2,0)&", "&P65&", Italy" -> La Residenza, Capri, Italy | R65: =VLOOKUP(A65,'Travel Times'!$A$1:$E$1000,4,0) -> 5 mins | S65: =VLOOKUP(A65,'Travel Times'!$A$1:$E$1000,5,0) -> 1 min
A66: Via Camerelle | B66: Capri | C66: Luxury Shopping Street | D66: 🛍️ | E66: Luxury shopping street with Hermès, Prada, Gucci | F66: Informal elegance dress code, flat sandals recommended | G66: 10:00 AM - 8:00 PM | H66: 3000 | I66: Via Camerelle, 80076 Capri NA, Italy | J66: 40.5498565, 14.2456523 | K66: 40.549856 | L66: 14.245652 | M66: =HYPERLINK("https://www.google.com/maps/search/"&ENCODEURL(A66)) -> https://www.google.com/maps/search/Via%20Camerelle | N66: Manus - https://manus.im/app/KJC6Ixn9ZFEgpriWR1GDzd | O66: Manus Itinerary 1 | P66: =VLOOKUP(B66,$V$3:$W$100,2,0) -> Capri | Q66: =VLOOKUP(P66,$X$3:$Y$6,2,0)&", "&P66&", Italy" -> La Residenza, Capri, Italy | R66: =VLOOKUP(A66,'Travel Times'!$A$1:$E$1000,4,0) -> 3 mins | S66: =VLOOKUP(A66,'Travel Times'!$A$1:$E$1000,5,0) -> 1 min
A67: Gardens of Augustus | B67: Capri | C67: Gardens | D67: 🌺 | E67: Panoramic gardens with views of Faraglioni rocks | F67: €1 entrance, best views of Faraglioni | G67: 9:00 AM - 7:30 PM | H67: $200 for two | I67: Gardens of Augustus, Via Matteotti, 2, 80076 Capri NA, Italy | J67: 40.5473022, 14.243206 | K67: 40.547302 | L67: 14.243206 | M67: =HYPERLINK("https://www.google.com/maps/search/"&ENCODEURL(A67)) -> https://www.google.com/maps/search/Gardens%20of%20Augustus | N67: Manus - https://manus.im/app/KJC6Ixn9ZFEgpriWR1GDzd | O67: Manus Itinerary 1 | P67: =VLOOKUP(B67,$V$3:$W$100,2,0) -> Capri | Q67: =VLOOKUP(P67,$X$3:$Y$6,2,0)&", "&P67&", Italy" -> La Residenza, Capri, Italy | R67: =VLOOKUP(A67,'Travel Times'!$A$1:$E$1000,4,0) -> 5 mins | S67: =VLOOKUP(A67,'Travel Times'!$A$1:$E$1000,5,0) -> 1 min
A68: Via Krupp | B68: Capri | C68: Scenic Path | D68: 🥾 | E68: Scenic winding path with coastal views | F68: Often closed for safety, check before visiting | G68: Weather dependent | H68: 3000 | I68: Via Krupp, 80076 Capri NA, Italy | J68: 40.5461187, 14.2380416 | K68: 40.546119 | L68: 14.238042 | M68: =HYPERLINK("https://www.google.com/maps/search/"&ENCODEURL(A68)) -> https://www.google.com/maps/search/Via%20Krupp | N68: Manus - https://manus.im/app/KJC6Ixn9ZFEgpriWR1GDzd | O68: Manus Itinerary 1 | P68: =VLOOKUP(B68,$V$3:$W$100,2,0) -> Capri | Q68: =VLOOKUP(P68,$X$3:$Y$6,2,0)&", "&P68&", Italy" -> La Residenza, Capri, Italy | R68: =VLOOKUP(A68,'Travel Times'!$A$1:$E$1000,4,0) -> 20 mins | S68: =VLOOKUP(A68,'Travel Times'!$A$1:$E$1000,5,0) -> 6 mins
A69: Aurora | B69: Capri | C69: Restaurant | D69: 🍽️ | E69: Historic restaurant frequented by entertainment and fashion personalities, traditional Capri cuisine | F69: Museum-like atmosphere, celebrity spotting, perfect for first night | G69: Dinner: 7:30 PM - 11:00 PM | H69: 3000 | I69: Via Fuorlovado, 18, 80073 Capri NA, Italy | J69: 40.550878, 14.2450572 | K69: 40.550878 | L69: 14.245057 | M69: =HYPERLINK("https://www.google.com/maps/search/"&ENCODEURL(A69)) -> https://www.google.com/maps/search/Aurora | N69: Manus - https://manus.im/app/KJC6Ixn9ZFEgpriWR1GDzd | O69: Manus Itinerary 1 | P69: =VLOOKUP(B69,$V$3:$W$100,2,0) -> Capri | Q69: =VLOOKUP(P69,$X$3:$Y$6,2,0)&", "&P69&", Italy" -> La Residenza, Capri, Italy | R69: =VLOOKUP(A69,'Travel Times'!$A$1:$E$1000,4,0) -> 5 mins | S69: =VLOOKUP(A69,'Travel Times'!$A$1:$E$1000,5,0) -> 1 min
A70: Blue Grotto | B70: Capri | C70: Sea Cave | D70: 🌊 | E70: Famous illuminated sea cave with electric blue waters | F70: €15 entrance + boat fees, weather dependent, can be crowded | G70: 9:00 AM - 5:00 PM (weather dependent) | H70: $500 for two | I70: Blue Grotto, 80071 Anacapri, Metropolitan City of Naples, Italy | J70: 40.5609849, 14.2055931 | K70: 40.560985 | L70: 14.205593 | M70: =HYPERLINK("https://www.google.com/maps/search/"&ENCODEURL(A70)) -> https://www.google.com/maps/search/Blue%20Grotto | N70: Manus - https://manus.im/app/KJC6Ixn9ZFEgpriWR1GDzd | O70: Manus Itinerary 1 | P70: =VLOOKUP(B70,$V$3:$W$100,2,0) -> Capri | Q70: =VLOOKUP(P70,$X$3:$Y$6,2,0)&", "&P70&", Italy" -> La Residenza, Capri, Italy | R70: =VLOOKUP(A70,'Travel Times'!$A$1:$E$1000,4,0) -> 1 hour 39 mins | S70: =VLOOKUP(A70,'Travel Times'!$A$1:$E$1000,5,0) -> 19 mins
A71: Faraglioni Rocks | B71: Capri | C71: Natural Formation | D71: 🗿 | E71: Iconic limestone rock formations rising from the sea | F71: Best viewed from boat or Gardens of Augustus | G71: Always visible | H71: 2500 | I71: 80076 Capri, Metropolitan City of Naples, Italy | J71: 40.5507259, 14.2429 | K71: 40.550726 | L71: 14.2429 | M71: =HYPERLINK("https://www.google.com/maps/search/"&ENCODEURL(A71)) -> https://www.google.com/maps/search/Faraglioni%20Rocks | N71: Manus - https://manus.im/app/KJC6Ixn9ZFEgpriWR1GDzd | O71: Manus Itinerary 1 | P71: =VLOOKUP(B71,$V$3:$W$100,2,0) -> Capri | Q71: =VLOOKUP(P71,$X$3:$Y$6,2,0)&", "&P71&", Italy" -> La Residenza, Capri, Italy | R71: =VLOOKUP(A71,'Travel Times'!$A$1:$E$1000,4,0) -> 24 mins | S71: =VLOOKUP(A71,'Travel Times'!$A$1:$E$1000,5,0) -> 1 min
A72: Green Grotto | B72: Capri | C72: Sea Cave | D72: 🌊 | E72: Less crowded alternative to Blue Grotto with emerald waters | F72: Included in boat tours, less crowded than Blue Grotto | G72: 9:00 AM - 5:00 PM (weather dependent) | H72: $750 for two | I72: Capri, Metropolitan City of Naples, Italy | J72: 40.5507259, 14.2429 | K72: 40.550726 | L72: 14.2429 | M72: =HYPERLINK("https://www.google.com/maps/search/"&ENCODEURL(A72)) -> https://www.google.com/maps/search/Green%20Grotto | N72: Manus - https://manus.im/app/KJC6Ixn9ZFEgpriWR1GDzd | O72: Manus Itinerary 1 | P72: =VLOOKUP(B72,$V$3:$W$100,2,0) -> Capri | Q72: =VLOOKUP(P72,$X$3:$Y$6,2,0)&", "&P72&", Italy" -> La Residenza, Capri, Italy | R72: =VLOOKUP(A72,'Travel Times'!$A$1:$E$1000,4,0) -> 1 hour 39 mins | S72: =VLOOKUP(A72,'Travel Times'!$A$1:$E$1000,5,0) -> 19 mins
A73: Il Riccio | B73: Capri | C73: Beach Club Restaurant | D73: 🍤 | E73: Fresh seafood restaurant on terrace overlooking Blue Grotto, breathtaking views | F73: Gourmet specialties, iconic "dessert room", chic Mediterranean style | G73: 12:30 PM - 3:30 PM | H73: $200 for two | I73: Via Gradola, 4, 80071 Anacapri NA, Italy | J73: 40.5608853, 14.203249 | K73: 40.560885 | L73: 14.203249 | M73: =HYPERLINK("https://www.google.com/maps/search/"&ENCODEURL(A73)) -> https://www.google.com/maps/search/Il%20Riccio | N73: Manus - https://manus.im/app/KJC6Ixn9ZFEgpriWR1GDzd | O73: Manus Itinerary 1 | P73: =VLOOKUP(B73,$V$3:$W$100,2,0) -> Capri | Q73: =VLOOKUP(P73,$X$3:$Y$6,2,0)&", "&P73&", Italy" -> La Residenza, Capri, Italy | R73: =VLOOKUP(A73,'Travel Times'!$A$1:$E$1000,4,0) -> 1 hour 38 mins | S73: =VLOOKUP(A73,'Travel Times'!$A$1:$E$1000,5,0) -> 19 mins
A74: Villa San Michele | B74: Anacapri | C74: Historic Villa | D74: 🏛️ | E74: Axel Munthe's villa with gardens and panoramic views | F74: €8 entrance, peaceful gardens, historic significance | G74: 9:00 AM - 6:00 PM | H74: 3000 | I74: Villa San Michele, Via Axel Munthe, 34, 80071 Anacapri NA, Italy | J74: 40.5572702, 14.2251246 | K74: 40.55727 | L74: 14.225125 | M74: =HYPERLINK("https://www.google.com/maps/search/"&ENCODEURL(A74)) -> https://www.google.com/maps/search/Villa%20San%20Michele | N74: Manus - https://manus.im/app/KJC6Ixn9ZFEgpriWR1GDzd | O74: Manus Itinerary 1 | P74: =VLOOKUP(B74,$V$3:$W$100,2,0) -> Capri | Q74: =VLOOKUP(P74,$X$3:$Y$6,2,0)&", "&P74&", Italy" -> La Residenza, Capri, Italy | R74: =VLOOKUP(A74,'Travel Times'!$A$1:$E$1000,4,0) -> 42 mins | S74: =VLOOKUP(A74,'Travel Times'!$A$1:$E$1000,5,0) -> 13 mins
A75: Monte Solaro Chairlift | B75: Anacapri | C75: Chairlift | D75: 🚡 | E75: Chairlift to highest point on Capri (589m) with panoramic views | F75: €11 round trip, spectacular 360-degree views | G75: 9:30 AM - 5:00 PM | H75: $100 for two | I75: Via Caposcuro, 10, 80071 Anacapri NA, Italy | J75: 40.5554465, 14.221584 | K75: 40.555447 | L75: 14.221584 | M75: =HYPERLINK("https://www.google.com/maps/search/"&ENCODEURL(A75)) -> https://www.google.com/maps/search/Monte%20Solaro%20Chairlift | N75: Manus - https://manus.im/app/KJC6Ixn9ZFEgpriWR1GDzd | O75: Manus Itinerary 1 | P75: =VLOOKUP(B75,$V$3:$W$100,2,0) -> Capri | Q75: =VLOOKUP(P75,$X$3:$Y$6,2,0)&", "&P75&", Italy" -> La Residenza, Capri, Italy | R75: =VLOOKUP(A75,'Travel Times'!$A$1:$E$1000,4,0) -> 47 mins | S75: =VLOOKUP(A75,'Travel Times'!$A$1:$E$1000,5,0) -> 11 mins
A76: da Paolino | B76: Capri | C76: Celebrity Restaurant | D76: 🍋 | E76: Dining under 130 fragrant lemon trees, celebrity hotspot | F76: Book months in advance, cash payments only, "Bomba" specialty pizza, legendary dessert buffet | G76: Dinner: 7:30 PM - 11:00 PM | H76: $200 for two | I76: Via Palazzo a Mare, 11, 80076 Capri NA, Italy | J76: 40.5585739, 14.2309054 | K76: 40.558574 | L76: 14.230905 | M76: =HYPERLINK("https://www.google.com/maps/search/"&ENCODEURL(A76)) -> https://www.google.com/maps/search/da%20Paolino | N76: Manus - https://manus.im/app/KJC6Ixn9ZFEgpriWR1GDzd | O76: Manus Itinerary 1 | P76: =VLOOKUP(B76,$V$3:$W$100,2,0) -> Capri | Q76: =VLOOKUP(P76,$X$3:$Y$6,2,0)&", "&P76&", Italy" -> La Residenza, Capri, Italy | R76: =VLOOKUP(A76,'Travel Times'!$A$1:$E$1000,4,0) -> 25 mins | S76: =VLOOKUP(A76,'Travel Times'!$A$1:$E$1000,5,0) -> 8 mins | T76: Dinner: Recommended by Repton
A77: La Fontelina Beach Club | B77: Capri | C77: Beach Club | D77: 🏖️ | E77: VIP beach club beneath Faraglioni rocks, celebrity favorite, "paradise on earth" | F77: €190 minimum spending (high season), famous sangria, celebrity spotting, closed July 4 & Sep 13 | G77: 9:00 AM - 7:00 PM (April 19 - Oct 12) | H77: $200 for two | I77: Via dei Faraglioni, 2, 80073 Capri NA, Italy | J77: 40.5437871, 14.2510518 | K77: 40.543787 | L77: 14.251052 | M77: =HYPERLINK("https://www.google.com/maps/search/"&ENCODEURL(A77)) -> https://www.google.com/maps/search/La%20Fontelina%20Beach%20Club | N77: Manus - https://manus.im/app/KJC6Ixn9ZFEgpriWR1GDzd | O77: Manus Itinerary 1 | P77: =VLOOKUP(B77,$V$3:$W$100,2,0) -> Capri | Q77: =VLOOKUP(P77,$X$3:$Y$6,2,0)&", "&P77&", Italy" -> La Residenza, Capri, Italy | R77: =VLOOKUP(A77,'Travel Times'!$A$1:$E$1000,4,0) -> 23 mins | S77: =VLOOKUP(A77,'Travel Times'!$A$1:$E$1000,5,0) -> 1 min
A78: Le Monzù | B78: Capri | C78: Michelin Restaurant | D78: ⭐ | E78: 1 Michelin Star restaurant at Hotel Punta Tragara, terrace designed by Le Corbusier | F78: €250 minimum per person, Faraglioni views "floating over the sea" | G78: Dinner: 7:30 PM - 11:00 PM | H78: 3000 | I78: Via Tragara, 57, 80073 Capri NA, Italy | J78: 40.5452777, 14.2505134 | K78: 40.545278 | L78: 14.250513 | M78: =HYPERLINK("https://www.google.com/maps/search/"&ENCODEURL(A78)) -> https://www.google.com/maps/search/Le%20Monz%C3%B9 | N78: Manus - https://manus.im/app/KJC6Ixn9ZFEgpriWR1GDzd | O78: Manus Itinerary 1 | P78: =VLOOKUP(B78,$V$3:$W$100,2,0) -> Capri | Q78: =VLOOKUP(P78,$X$3:$Y$6,2,0)&", "&P78&", Italy" -> La Residenza, Capri, Italy | R78: =VLOOKUP(A78,'Travel Times'!$A$1:$E$1000,4,0) -> 13 mins | S78: =VLOOKUP(A78,'Travel Times'!$A$1:$E$1000,5,0) -> 1 min
A79: L'Olivo | B79: Anacapri | C79: Michelin Restaurant | D79: ⭐ | E79: 2 Michelin Stars, highest rated restaurant on Capri, quiet village location | F79: €250 minimum per person, ultimate culinary excellence, book months ahead | G79: Dinner: 7:30 PM - 11:00 PM | H79: $200 for two | I79: Via Capodimonte, 14, 80071 Anacapri NA, Italy | J79: 40.5557415, 14.221837 | K79: 40.555742 | L79: 14.221837 | M79: =HYPERLINK("https://www.google.com/maps/search/"&ENCODEURL(A79)) -> https://www.google.com/maps/search/L%27Olivo | N79: Manus - https://manus.im/app/KJC6Ixn9ZFEgpriWR1GDzd | O79: Manus Itinerary 1 | P79: =VLOOKUP(B79,$V$3:$W$100,2,0) -> Capri | Q79: =VLOOKUP(P79,$X$3:$Y$6,2,0)&", "&P79&", Italy" -> La Residenza, Capri, Italy | R79: =VLOOKUP(A79,'Travel Times'!$A$1:$E$1000,4,0) -> 46 mins | S79: =VLOOKUP(A79,'Travel Times'!$A$1:$E$1000,5,0) -> 12 mins
A80: Palazzo Avino | B80: Ravello | C80: Luxury Hotel | D80: 🏨 | E80: Pink palace of Ravello with fairy-tale vista, 12th-century palace with Monte Avvocata valley views | F80: From £1,083/night, Michelin-starred Rossellini's restaurant, beach club | G80: Check-in: 3:00 PM, Check-out: 11:00 AM | H80: 3000 | I80: Via S. Giovanni del Toro, 28, 84010 Ravello SA, Italy | J80: 40.6508871, 14.6129698 | K80: 40.650887 | L80: 14.61297 | M80: =HYPERLINK("https://www.google.com/maps/search/"&ENCODEURL(A80)) -> https://www.google.com/maps/search/Palazzo%20Avino | N80: Manus - https://manus.im/app/KJC6Ixn9ZFEgpriWR1GDzd | O80: Manus Itinerary 1 | P80: =VLOOKUP(B80,$V$3:$W$100,2,0) -> Ravello | Q80: =VLOOKUP(P80,$X$3:$Y$6,2,0)&", "&P80&", Italy" -> Hotel Rufolo, Ravello, Italy | R80: =VLOOKUP(A80,'Travel Times'!$A$1:$E$1000,4,0) -> 8 mins | S80: =VLOOKUP(A80,'Travel Times'!$A$1:$E$1000,5,0) -> 2 mins
A81: Borgo Santandrea | B81: Amalfi | C81: Luxury Hotel | D81: 🏨 | E81: Perched high in cliffs, built into rock face, most plum address on the Amalfi | F81: From £700/night, Al Borgo beach club, views of Conca dei Marini | G81: Check-in: 3:00 PM, Check-out: 11:00 AM | H81: 3000 | I81: Via Giovanni Augustariccio, 33, 84011 Amalfi SA, Italy | J81: 40.6189299, 14.5764754 | K81: 40.61893 | L81: 14.576475 | M81: =HYPERLINK("https://www.google.com/maps/search/"&ENCODEURL(A81)) -> https://www.google.com/maps/search/Borgo%20Santandrea | N81: Manus - https://manus.im/app/KJC6Ixn9ZFEgpriWR1GDzd | O81: Manus Itinerary 1 | P81: =VLOOKUP(B81,$V$3:$W$100,2,0) -> Positano | Q81: =VLOOKUP(P81,$X$3:$Y$6,2,0)&", "&P81&", Italy" -> Hotel Savoia, Positano, Italy | R81: =VLOOKUP(A81,'Travel Times'!$A$1:$E$1000,4,0) -> 4 hours 12 mins | S81: =VLOOKUP(A81,'Travel Times'!$A$1:$E$1000,5,0) -> 28 mins
A82: Rossellini's | B82: Ravello | C82: Michelin Restaurant | D82: ⭐ | E82: Michelin-starred dining at Palazzo Avino with spectacular terrace | F82: Lemon ravioli by candlelight, one of most spectacular dining rooms on coast | G82: Dinner: 7:30 PM - 11:00 PM | H82: $200 for two | I82: Via S. Giovanni del Toro, 28, 84010 Ravello SA, Italy | J82: 40.6508871, 14.6129698 | K82: 40.650887 | L82: 14.61297 | M82: =HYPERLINK("https://www.google.com/maps/search/"&ENCODEURL(A82)) -> https://www.google.com/maps/search/Rossellini%27s | N82: Manus - https://manus.im/app/KJC6Ixn9ZFEgpriWR1GDzd | O82: Manus Itinerary 1 | P82: =VLOOKUP(B82,$V$3:$W$100,2,0) -> Ravello | Q82: =VLOOKUP(P82,$X$3:$Y$6,2,0)&", "&P82&", Italy" -> Hotel Rufolo, Ravello, Italy | R82: =VLOOKUP(A82,'Travel Times'!$A$1:$E$1000,4,0) -> 8 mins | S82: =VLOOKUP(A82,'Travel Times'!$A$1:$E$1000,5,0) -> 2 mins
A83: Al Borgo | B83: Amalfi | C83: Beach Club Restaurant | D83: 🍽️ | E83: Informal beach club at Borgo Santandrea with sunset Negronis | F83: Fritto misto, spaghetti alle vongole, caprese, sunset terrace | G83: Lunch & Dinner | H83: 3000 | I83: 84011 Amalfi, SA, Italy | J83: 40.6338303, 14.6027661 | K83: 40.63383 | L83: 14.602766 | M83: =HYPERLINK("https://www.google.com/maps/search/"&ENCODEURL(A83)) -> https://www.google.com/maps/search/Al%20Borgo | N83: Manus - https://manus.im/app/KJC6Ixn9ZFEgpriWR1GDzd | O83: Manus Itinerary 1 | P83: =VLOOKUP(B83,$V$3:$W$100,2,0) -> Positano | Q83: =VLOOKUP(P83,$X$3:$Y$6,2,0)&", "&P83&", Italy" -> Hotel Savoia, Positano, Italy | R83: =VLOOKUP(A83,'Travel Times'!$A$1:$E$1000,4,0) -> 4 hours 40 mins | S83: =VLOOKUP(A83,'Travel Times'!$A$1:$E$1000,5,0) -> 37 mins
A84: La Tagliata | B84: Positano | C84: Cooking Class & Restaurant | D84: 👨‍🍳 | E84: Authentic Italian family-style cooking class, 40-year family business | F84: Book months ahead, cash only, garden tour, farm animals, 3 terraces with views | G84: 10:00 AM - 3:15 PM | H84: $200 for two | I84: Via Tagliata, 32B, 84017 Positano SA, Italy | J84: 40.6311822, 14.4971535 | K84: 40.631182 | L84: 14.497153 | M84: =HYPERLINK("https://www.google.com/maps/search/"&ENCODEURL(A84)) -> https://www.google.com/maps/search/La%20Tagliata | N84: Manus - https://manus.im/app/KJC6Ixn9ZFEgpriWR1GDzd | O84: Manus Itinerary 1 | P84: =VLOOKUP(B84,$V$3:$W$100,2,0) -> Positano | Q84: =VLOOKUP(P84,$X$3:$Y$6,2,0)&", "&P84&", Italy" -> Hotel Savoia, Positano, Italy | R84: =VLOOKUP(A84,'Travel Times'!$A$1:$E$1000,4,0) -> 47 mins | S84: =VLOOKUP(A84,'Travel Times'!$A$1:$E$1000,5,0) -> 17 mins
A85: Spiaggia Grande | B85: Positano | C85: Main Beach | D85: 🏖️ | E85: Main beach with colorful umbrellas and iconic Positano backdrop | F85: Umbrella rentals available, most photographed beach | G85: 8:00 AM - 7:00 PM | H85: 4000 | I85: Via del Brigantino, 84017 Positano SA, Italy | J85: 40.6278423, 14.4880918 | K85: 40.627842 | L85: 14.488092 | M85: =HYPERLINK("https://www.google.com/maps/search/"&ENCODEURL(A85)) -> https://www.google.com/maps/search/Spiaggia%20Grande | N85: Manus - https://manus.im/app/KJC6Ixn9ZFEgpriWR1GDzd | O85: Manus Itinerary 1 | P85: =VLOOKUP(B85,$V$3:$W$100,2,0) -> Positano | Q85: =VLOOKUP(P85,$X$3:$Y$6,2,0)&", "&P85&", Italy" -> Hotel Savoia, Positano, Italy | R85: =VLOOKUP(A85,'Travel Times'!$A$1:$E$1000,4,0) -> 6 mins | S85: =VLOOKUP(A85,'Travel Times'!$A$1:$E$1000,5,0) -> 1 min
A86: Chiesa di Santa Maria Assunta | B86: Positano | C86: Church | D86: ⛪ | E86: Iconic dome church with ceramic tile dome, symbol of Positano | F86: Free entry, beautiful ceramics, historic significance | G86: 8:00 AM - 12:00 PM, 4:00 PM - 7:00 PM | H86: $500 for two | I86: P.za Flavio Gioia, 84017 Positano SA, Italy | J86: 40.6283686, 14.4865314 | K86: 40.628369 | L86: 14.486531 | M86: =HYPERLINK("https://www.google.com/maps/search/"&ENCODEURL(A86)) -> https://www.google.com/maps/search/Chiesa%20di%20Santa%20Maria%20Assunta | N86: Manus - https://manus.im/app/KJC6Ixn9ZFEgpriWR1GDzd | O86: Manus Itinerary 1 | P86: =VLOOKUP(B86,$V$3:$W$100,2,0) -> Positano | Q86: =VLOOKUP(P86,$X$3:$Y$6,2,0)&", "&P86&", Italy" -> Hotel Savoia, Positano, Italy | R86: =VLOOKUP(A86,'Travel Times'!$A$1:$E$1000,4,0) -> 4 mins | S86: =VLOOKUP(A86,'Travel Times'!$A$1:$E$1000,5,0) -> 1 min
A87: Via dei Mulini | B87: Positano | C87: Shopping Street | D87: 🛍️ | E87: Main shopping street with local boutiques and ceramics | F87: Positano fashion, local ceramics, steep vertical street | G87: 9:00 AM - 8:00 PM | H87: 3000 | I87: Via dei Mulini, 84017 Positano SA, Italy | J87: 40.6290779, 14.4866109 | K87: 40.629078 | L87: 14.486611 | M87: =HYPERLINK("https://www.google.com/maps/search/"&ENCODEURL(A87)) -> https://www.google.com/maps/search/Via%20dei%20Mulini | N87: Manus - https://manus.im/app/KJC6Ixn9ZFEgpriWR1GDzd | O87: Manus Itinerary 1 | P87: =VLOOKUP(B87,$V$3:$W$100,2,0) -> Positano | Q87: =VLOOKUP(P87,$X$3:$Y$6,2,0)&", "&P87&", Italy" -> Hotel Savoia, Positano, Italy | R87: =VLOOKUP(A87,'Travel Times'!$A$1:$E$1000,4,0) -> 3 mins | S87: =VLOOKUP(A87,'Travel Times'!$A$1:$E$1000,5,0) -> 1 min
A88: La Scogliera Beach Club | B88: Positano | C88: Beach Club | D88: 🏖️ | E88: Beach club set between rocks with Li Galli Islands views, romantic sunset transformation | F88: Day to night transformation, cocktails and sunbeds, romantic lounge bar | G88: 9:00 AM - 11:00 PM | H88: $500 for two | I88: Spiaggia, Via del Brigantino, 84017 Positano SA, Italy | J88: 40.6278423, 14.4880918 | K88: 40.627842 | L88: 14.488092 | M88: =HYPERLINK("https://www.google.com/maps/search/"&ENCODEURL(A88)) -> https://www.google.com/maps/search/La%20Scogliera%20Beach%20Club | N88: Manus - https://manus.im/app/KJC6Ixn9ZFEgpriWR1GDzd | O88: Manus Itinerary 1 | P88: =VLOOKUP(B88,$V$3:$W$100,2,0) -> Positano | Q88: =VLOOKUP(P88,$X$3:$Y$6,2,0)&", "&P88&", Italy" -> Hotel Savoia, Positano, Italy | R88: =VLOOKUP(A88,'Travel Times'!$A$1:$E$1000,4,0) -> 8 mins | S88: =VLOOKUP(A88,'Travel Times'!$A$1:$E$1000,5,0) -> 2 mins
A89: Da Ferdinando Beach Club | B89: Positano | C89: Beach Club | D89: 🏖️ | E89: More reasonably priced beach club at Fornillo Beach | F89: Away from main crowds, umbrella reservations for two, good value | G89: 9:00 AM - 7:00 PM | H89: $200 for two | I89: Spiaggia di Fornillo, 84017 Positano SA, Italy | J89: 40.6263545, 14.4822477 | K89: 40.626354 | L89: 14.482248 | M89: =HYPERLINK("https://www.google.com/maps/search/"&ENCODEURL(A89)) -> https://www.google.com/maps/search/Da%20Ferdinando%20Beach%20Club | N89: Manus - https://manus.im/app/KJC6Ixn9ZFEgpriWR1GDzd | O89: Manus Itinerary 1 | P89: =VLOOKUP(B89,$V$3:$W$100,2,0) -> Positano | Q89: =VLOOKUP(P89,$X$3:$Y$6,2,0)&", "&P89&", Italy" -> Hotel Savoia, Positano, Italy | R89: =VLOOKUP(A89,'Travel Times'!$A$1:$E$1000,4,0) -> 22 mins | S89: =VLOOKUP(A89,'Travel Times'!$A$1:$E$1000,5,0) -> 13 mins
A90: Villa Rufolo | B90: Ravello | C90: Historic Villa & Gardens | D90: 🌺 | E90: Historic 13th-century villa with magnificent gardens and coastal views | F90: €7 entrance, Wagner Terrace, concert venue for Ravello Festival | G90: 9:00 AM - 8:00 PM | H90: $500 for two | I90: Piazza Duomo, 1, 84010 Ravello SA, Italy | J90: 40.6490843, 14.6113693 | K90: 40.649084 | L90: 14.611369 | M90: =HYPERLINK("https://www.google.com/maps/search/"&ENCODEURL(A90)) -> https://www.google.com/maps/search/Villa%20Rufolo | N90: Manus - https://manus.im/app/KJC6Ixn9ZFEgpriWR1GDzd | O90: Manus Itinerary 1 | P90: =VLOOKUP(B90,$V$3:$W$100,2,0) -> Ravello | Q90: =VLOOKUP(P90,$X$3:$Y$6,2,0)&", "&P90&", Italy" -> Hotel Rufolo, Ravello, Italy | R90: =VLOOKUP(A90,'Travel Times'!$A$1:$E$1000,4,0) -> 2 mins | S90: =VLOOKUP(A90,'Travel Times'!$A$1:$E$1000,5,0) -> 1 min
A91: Villa Cimbrone | B91: Ravello | C91: Historic Villa & Gardens | D91: 🌺 | E91: Terrace of Infinity with panoramic views, English-style gardens | F91: €12 entrance, one of most photographed spots on Amalfi Coast | G91: 9:00 AM - sunset | H91: $4000 for two | I91: Via Santa Chiara, 26, 84010 Ravello SA, Italy | J91: 40.644269, 14.611034 | K91: 40.644269 | L91: 14.611034 | M91: =HYPERLINK("https://www.google.com/maps/search/"&ENCODEURL(A91)) -> https://www.google.com/maps/search/Villa%20Cimbrone | N91: Manus - https://manus.im/app/KJC6Ixn9ZFEgpriWR1GDzd | O91: Manus Itinerary 1 | P91: =VLOOKUP(B91,$V$3:$W$100,2,0) -> Ravello | Q91: =VLOOKUP(P91,$X$3:$Y$6,2,0)&", "&P91&", Italy" -> Hotel Rufolo, Ravello, Italy | R91: =VLOOKUP(A91,'Travel Times'!$A$1:$E$1000,4,0) -> 9 mins | S91: =VLOOKUP(A91,'Travel Times'!$A$1:$E$1000,5,0) -> 5 mins
A92: Duomo di Ravello | B92: Ravello | C92: Cathedral | D92: ⛪ | E92: 11th-century cathedral with beautiful bronze doors and intricate mosaics | F92: Free entry, peaceful spiritual atmosphere, historic pulpit | G92: 9:00 AM - 1:00 PM, 3:00 PM - 7:00 PM | H92: $500 for two | I92: Piazza Duomo, 84010 Ravello SA, Italy | J92: 40.6491825, 14.6116481 | K92: 40.649183 | L92: 14.611648 | M92: =HYPERLINK("https://www.google.com/maps/search/"&ENCODEURL(A92)) -> https://www.google.com/maps/search/Duomo%20di%20Ravello | N92: Manus - https://manus.im/app/KJC6Ixn9ZFEgpriWR1GDzd | O92: Manus Itinerary 1 | P92: =VLOOKUP(B92,$V$3:$W$100,2,0) -> Ravello | Q92: =VLOOKUP(P92,$X$3:$Y$6,2,0)&", "&P92&", Italy" -> Hotel Rufolo, Ravello, Italy | R92: =VLOOKUP(A92,'Travel Times'!$A$1:$E$1000,4,0) -> 2 mins | S92: =VLOOKUP(A92,'Travel Times'!$A$1:$E$1000,5,0) -> 1 min
A93: Path of the Gods (Sentiero degli Dei) | B93: Amalfi Coast | C93: Hiking Trail | D93: 🥾 | E93: Spectacular coastal hiking trail from Bomerano to Nocelle | F93: 3.5 hours, moderate difficulty, ancient mule paths, ends in Positano | G93: Dawn to dusk | H93: $600 for two | I93: 84011 Amalfi, SA, Italy | J93: 40.6338303, 14.6027661 | K93: 40.63383 | L93: 14.602766 | M93: =HYPERLINK("https://www.google.com/maps/search/"&ENCODEURL(A93)) -> https://www.google.com/maps/search/Path%20of%20the%20Gods%20%28Sentiero%20degli%20Dei%29 | N93: Manus - https://manus.im/app/KJC6Ixn9ZFEgpriWR1GDzd | O93: Manus Itinerary 1 | P93: =VLOOKUP(B93,$V$3:$W$100,2,0) -> Positano | Q93: =VLOOKUP(P93,$X$3:$Y$6,2,0)&", "&P93&", Italy" -> Hotel Savoia, Positano, Italy | R93: =VLOOKUP(A93,'Travel Times'!$A$1:$E$1000,4,0) -> 4 hours 39 mins | S93: =VLOOKUP(A93,'Travel Times'!$A$1:$E$1000,5,0) -> 37 mins
A94: Belmond Villa Margherita | B94: Ravello | C94: Ultra-Luxury Villa | D94: 🏰 | E94: Ultra-exclusive villa with spine-tingling views, can be rented whole | F94: From £3,403/night, huge windows framing lemon terraces, private villa atmosphere | G94: 24 hours | H94: 3000 | I94: Via Santa Margherita, 7, 84010 Ravello SA, Italy | J94: 40.651503, 14.6129517 | K94: 40.651503 | L94: 14.612952 | M94: =HYPERLINK("https://www.google.com/maps/search/"&ENCODEURL(A94)) -> https://www.google.com/maps/search/Belmond%20Villa%20Margherita | N94: Manus - https://manus.im/app/KJC6Ixn9ZFEgpriWR1GDzd | O94: Manus Itinerary 1 | P94: =VLOOKUP(B94,$V$3:$W$100,2,0) -> Ravello | Q94: =VLOOKUP(P94,$X$3:$Y$6,2,0)&", "&P94&", Italy" -> Hotel Rufolo, Ravello, Italy | R94: =VLOOKUP(A94,'Travel Times'!$A$1:$E$1000,4,0) -> 8 mins | S94: =VLOOKUP(A94,'Travel Times'!$A$1:$E$1000,5,0) -> 3 mins
A95: Li Galli Islands | B95: Amalfi Coast | C95: Islands | D95: 🏝️ | E95: Mythical sirens' islands, boat tour destination | F95: Private islands, beautiful for swimming stops, mythological significance | G95: Boat tours only | H95: 3000 | I95: 84011 Amalfi, SA, Italy | J95: 40.5828024, 14.4341215 | K95: 40.582802 | L95: 14.434121 | M95: =HYPERLINK("https://www.google.com/maps/search/"&ENCODEURL(A95)) -> https://www.google.com/maps/search/Li%20Galli%20Islands | N95: Manus - https://manus.im/app/KJC6Ixn9ZFEgpriWR1GDzd | O95: Manus Itinerary 1 | P95: =VLOOKUP(B95,$V$3:$W$100,2,0) -> Positano | Q95: =VLOOKUP(P95,$X$3:$Y$6,2,0)&", "&P95&", Italy" -> Hotel Savoia, Positano, Italy | R95: =VLOOKUP(A95,'Travel Times'!$A$1:$E$1000,4,0) -> 4 hours 39 mins | S95: =VLOOKUP(A95,'Travel Times'!$A$1:$E$1000,5,0) -> 37 mins
A96: Furore Fjord | B96: Amalfi Coast | C96: Natural Formation | D96: 🌊 | E96: Dramatic coastal inlet, boat tour highlight | F96: Spectacular natural formation, great for photos | G96: Boat tours only | H96: 3000 | I96: 84011 Amalfi, SA, Italy | J96: 40.6185726, 14.5509614 | K96: 40.618573 | L96: 14.550961 | M96: =HYPERLINK("https://www.google.com/maps/search/"&ENCODEURL(A96)) -> https://www.google.com/maps/search/Furore%20Fjord | N96: Manus - https://manus.im/app/KJC6Ixn9ZFEgpriWR1GDzd | O96: Manus Itinerary 1 | P96: =VLOOKUP(B96,$V$3:$W$100,2,0) -> Positano | Q96: =VLOOKUP(P96,$X$3:$Y$6,2,0)&", "&P96&", Italy" -> Hotel Savoia, Positano, Italy | R96: =VLOOKUP(A96,'Travel Times'!$A$1:$E$1000,4,0) -> 4 hours 39 mins | S96: =VLOOKUP(A96,'Travel Times'!$A$1:$E$1000,5,0) -> 37 mins
A97: Conca dei Marini | B97: Amalfi Coast | C97: Fishing Village | D97: 🎣 | E97: Picturesque fishing village, boat tour stop | F97: Authentic fishing village, views from Borgo Santandrea | G97: Always open | H97: 3000 | I97: 84011 Amalfi, SA, Italy | J97: 40.6163236, 14.5753912 | K97: 40.616324 | L97: 14.575391 | M97: =HYPERLINK("https://www.google.com/maps/search/"&ENCODEURL(A97)) -> https://www.google.com/maps/search/Conca%20dei%20Marini | N97: Manus - https://manus.im/app/KJC6Ixn9ZFEgpriWR1GDzd | O97: Manus Itinerary 1 | P97: =VLOOKUP(B97,$V$3:$W$100,2,0) -> Positano | Q97: =VLOOKUP(P97,$X$3:$Y$6,2,0)&", "&P97&", Italy" -> Hotel Savoia, Positano, Italy | R97: =VLOOKUP(A97,'Travel Times'!$A$1:$E$1000,4,0) -> 4 hours 39 mins | S97: =VLOOKUP(A97,'Travel Times'!$A$1:$E$1000,5,0) -> 37 mins
A98: Emerald Grotto | B98: Amalfi Coast | C98: Sea Cave | D98: 🌊 | E98: Alternative to Blue Grotto with emerald-colored waters | F98: Less crowded than Blue Grotto, included in boat tours | G98: 9:00 AM - 5:00 PM (weather dependent) | H98: 2500 | I98: 84011 Amalfi, SA, Italy | J98: 40.6150824, 14.5670273 | K98: 40.615082 | L98: 14.567027 | M98: =HYPERLINK("https://www.google.com/maps/search/"&ENCODEURL(A98)) -> https://www.google.com/maps/search/Emerald%20Grotto | N98: Manus - https://manus.im/app/KJC6Ixn9ZFEgpriWR1GDzd | O98: Manus Itinerary 1 | P98: =VLOOKUP(B98,$V$3:$W$100,2,0) -> Positano | Q98: =VLOOKUP(P98,$X$3:$Y$6,2,0)&", "&P98&", Italy" -> Hotel Savoia, Positano, Italy | R98: =VLOOKUP(A98,'Travel Times'!$A$1:$E$1000,4,0) -> 4 hours 31 mins | S98: =VLOOKUP(A98,'Travel Times'!$A$1:$E$1000,5,0) -> 24 mins
A99: Amalfi Town Historic Center | B99: Amalfi | C99: Historic Town | D99: 🏛️ | E99: Historic center with cathedral and Piazza del Duomo | F99: UNESCO World Heritage site, beautiful cathedral | G99: Always open | H99: $2000 for two | I99: 84011 Amalfi, SA, Italy | J99: 40.6338303, 14.6027661 | K99: 40.63383 | L99: 14.602766 | M99: =HYPERLINK("https://www.google.com/maps/search/"&ENCODEURL(A99)) -> https://www.google.com/maps/search/Amalfi%20Town%20Historic%20Center | N99: Manus - https://manus.im/app/KJC6Ixn9ZFEgpriWR1GDzd | O99: Manus Itinerary 1 | P99: =VLOOKUP(B99,$V$3:$W$100,2,0) -> Positano | Q99: =VLOOKUP(P99,$X$3:$Y$6,2,0)&", "&P99&", Italy" -> Hotel Savoia, Positano, Italy | R99: =VLOOKUP(A99,'Travel Times'!$A$1:$E$1000,4,0) -> 4 hours 40 mins | S99: =VLOOKUP(A99,'Travel Times'!$A$1:$E$1000,5,0) -> 37 mins
A100: Piazza del Duomo | B100: Amalfi | C100: Historic Square | D100: ⛪ | E100: Main square with stunning cathedral and historic atmosphere | F100: Heart of Amalfi, beautiful cathedral steps | G100: Always open | H100: 2500 | I100: Piazza Duomo, 84011 Amalfi SA, Italy | J100: 40.6342211, 14.6026726 | K100: 40.634221 | L100: 14.602673 | M100: =HYPERLINK("https://www.google.com/maps/search/"&ENCODEURL(A100)) -> https://www.google.com/maps/search/Piazza%20del%20Duomo | N100: Manus - https://manus.im/app/KJC6Ixn9ZFEgpriWR1GDzd | O100: Manus Itinerary 1 | P100: =VLOOKUP(B100,$V$3:$W$100,2,0) -> Positano | Q100: =VLOOKUP(P100,$X$3:$Y$6,2,0)&", "&P100&", Italy" -> Hotel Savoia, Positano, Italy | R100: =VLOOKUP(A100,'Travel Times'!$A$1:$E$1000,4,0) -> 4 hours 41 mins | S100: =VLOOKUP(A100,'Travel Times'!$A$1:$E$1000,5,0) -> 37 mins
...

Sheet Accomodations
A1: Hotel | B1: Price per Night (Aug/Sep) | C1: Beach Club | D1: Ferry Access (1-10) | E1: da Paolino (1-10) | F1: Il Riccio (1-10) | G1: La Fontelina (1-10) | H1: Boat Day (1-10) | I1: Da Gioia (1-10) | J1: L'Olivo & Monte Solaro (1-10)
A2: Hotel La Palma | B2: €800-1200 | C2: Yes (Da Gioia) | D2: 8 | E2: 6 | F2: 3 | G2: 9 | H2: 9 | I2: 10 | J2: 3 | K2: =AVERAGE(D2:J2) -> 6.8571429
A3: J.K. Place Capri | B3: €400-600 | C3: No | D3: 10 | E3: 9 | F3: 3 | G3: 7 | H3: 10 | I3: 7 | J3: 3 | K3: =AVERAGE(D3:J3) -> 7
A4: La Minerva | B4: €250-400 | C4: No | D4: 7 | E4: 5 | F4: 3 | G4: 8 | H4: 8 | I4: 8 | J4: 3 | K4: =AVERAGE(D4:J4) -> 6
A5: Punta Tragara | B5: €500-1200 | C5: No | D5: 6 | E5: 4 | F5: 3 | G5: 10 | H5: 8 | I5: 7 | J5: 3 | K5: =AVERAGE(D5:J5) -> 5.8571429
A6: Grand Hotel Quisisana | B6: €800-1500 | C6: No | D6: 8 | E6: 5 | F6: 3 | G6: 8 | H6: 9 | I6: 8 | J6: 3 | K6: =AVERAGE(D6:J6) -> 6.2857143
A7: Capri Tiberio Palace | B7: €400-800 | C7: No | D7: 7 | E7: 5 | F7: 3 | G7: 8 | H7: 8 | I7: 8 | J7: 3 | K7: =AVERAGE(D7:J7) -> 6
A8: Casa Boutique by Capri 5 Senses | B8: €200-350 | C8: No | D8: 8 | E8: 5 | F8: 3 | G8: 9 | H8: 8 | I8: 8 | J8: 3 | K8: =AVERAGE(D8:J8) -> 6.2857143
A9: Capri Palace Hotel | B9: €600-1500 | C9: No | D9: 4 | E9: 3 | F9: 10 | G9: 5 | H9: 6 | I9: 5 | J9: 10 | K9: =AVERAGE(D9:J9) -> 6.1428571
A10: Airbnb in Anacapri | B10: €100-300 | C10: No | D10: 4 | E10: 3 | F10: 9 | G10: 5 | H10: 6 | I10: 5 | J10: 9 | K10: =AVERAGE(D10:J10) -> 5.8571429
C11: Rating
A12: Hotel La Palma | B12: 8363 | C12: 9.6 | F12: Villa Margherita by Belmond | G12: =11082*1.1 -> 12190.2
A13: Palazzo M | B13: =4993*1.1 -> 5492.3 | C13: 9.6 | F13: Palazzo Avino | G13: =4457*1.1 -> 4902.7
A14: J.K. Place Capri | B14: 14547 | F14: Villa Barluzzi | G14: =1244*1.1 -> 1368.4
A15: Punta Tragara | B15: 10308 | C15: 8.9 | F15: Villa Maria | G15: =894*1.1 -> 983.4
A16: La Minerva | B16: Unavailable | F16: Hotel Rufolo* | G16: 1105-1072 | H16: 4 star | I16: Sea view on Chase
A17: Capri Tiberio Palace | B17: =4779*1.1 -> 5256.9 | C17: 9.3 | F17: La Moresca | G17: 638
A18: Villa Certosa | B18: =3463*1.1 -> 3809.3 | F18: Palazzo Confalone | G18: =1111*1.1 -> 1222.1 | H18: 5 star | I18: Sea view on Chase

Sheet Unstructured Notes
A1: 45813 | B1: Gemini: Amalfi vs Puglia or both | E1: Research TODO: | F1: Amalfi Towns: Ravello, Praiano, or Conca dei Marini, Capri
A2: 45812 | B2: ChatGPT: Initial Research | E2: ✅ | F2: Research individual towns in Puglia
A3: 45813 | B3: Apple Notes: Activity Ideas | E3: ✅ | F3: Ask Manus/Gemini to compile all best restaurants, cafes, activitys, thermal pools, wineries, wine tasting classes, cooking classes, etc popular on instagram
A4: 45812 | B4: Apple Notes: Instagram Inspiration Links | E4: ✅ | F4: Notebook LM: Ask it to extract all locations from YouTube videos added
A5: 45812 | B5: Manus: Initial Research | E5: ✅ | F5: Finalize list of towns and days in each
E7: Booking TODO
E8: ✅ | F8: Flights
A9: Prompts | E9: ✅ | F9: Time Off
A10: Itinerary | B10: Hi! My girlfriend (29F) and I (33M) are planning a romantic trip to the Amalfi Coast from August 30 to September 8 (9 nights, 10 days). It’s our first time in Italy, and we’re prioritizing relaxation, scenic beauty, romance, and well-curated experiences over high-effort city touring. We’re New Yorkers, so we want to avoid anything that feels like a Times Square/cruise ship/tourist trap vibe — no cheap souvenir stands, no English-only menus, no tourist junk zones. That said, we’re totally fine with places that are popular or Instagrammable as long as they’re visually stunning, tasteful, and offer a genuine or luxurious experience (like a cliffside restaurant or a boutique hotel with views). We’d like to: Fly into Naples (arriving Aug 30), spend 1 night for the culture and pizza Ferry to Capri for 1-3 nights to explore beaches, views, and maybe a boat day. Ferry to the Amalfi Coast, staying the reset of our nights in scenic towns like Ravello, Praiano, or Conca dei Marini — open to mixing between them. Fly out of Naples on Sept 8. We’re open to renting a car if it makes things easier, but it seems ferries with a mix of private transfers and vespas might be the simplest route. We’d love help finalizing: Which towns to base ourselves in (and for how long). A day-by-day structure using “anchor activities” and optional extras. Boutique hotel or lodging suggestions in each area. Restaurant, beach club, or boat day ideas that match our taste. Best use of ferries, private drivers, or transfer timing. Here were some high-level things we were interested in generally before settling on Amalfi as our destination: - [ ] Beach day (e.g. one lined with umbrellas) - [ ] Beach club - [ ] Vespa riding - [ ] Wine tasting tour (foot, bike, or vespa, or one single location without movement if easier) - [ ] Grotta Palazzese dinner (this is in Puglia, but we'd love something with a similar memorable stunning view) - [ ] Boat day - [ ] Aperol spritz rooftop sunset - [ ] Good authentic local food - [ ] Cooking class (normal/authentic or crazy and fun like La Tagliata cooking class in Positano) - [ ] Hike (e.g. along costal cliffside or in historic towns) - [ ] If there are any notable spas, thermal pools, or ancient bath houses in the region we might be up for checking them out but that's not a priority for diverting travel When planning think: romantic, adventurous, beautiful, and upscale — but never tacky. Thanks! | E10: ✅ | F10: Book essential spots
A11: Maps | B11: Thanks, can you compile all the places you recommended into a table with the following columns: Name: The name of the location Region: The town, city, neighborhood, or region Type: The type of location (e.g. hotel, Restaurant (lunch), Restaurant (dinner) Cafe, Gelateria, Rooftop Bar, Speakeasy, etc) Emoji: A representative emoji to be used on the map as an icon. Description: A description of the spot and its general vibe Special Notes: Any special considerations (must order items, dress code, cool historical facts, etc) Hours: Hours of operation (if applicable) Cost Range: Indication of how much 2 people would be expected to spend in a visit (in USD) Address: The full address (including country) if available LatLong: The latitude and Longitude separated by a comma and space | E11: ✅ | F11: https://paolinocapri.com/en/prenota-un-tavolo/
A12: Map Options | B12: Can you also recommend a mix of spots nearby that are in our general area and might be good to know about in case we are feeling spontaneous (so not as itinerary-oriented and more options list). Think places like renowned cafes, pizzerias, gelato shops, shopping places, wine windows, rooftop bars, wine bars, etc. Anything casual that might be fun to visit quickly while attending to a larger agenda. Can you come up with at least three (but preferably more reservations for each? | E12: ✅ | F12: Rent Boat
A13: Chiaia | B13: My girlfriend (29F) and I (33M) are staying a night or two in the Chiaia region of Naples before leaving to Capri for a few days. We are from NYC and like good food, good drinks, romantic scenery, exploring, and adventure. Can you recommend some hotels in the ~$200 to ~$400 USD range that are nice to stay in for dates 8/28 to 8/30? Can you also compile a list of good restaurants (pref a few on the water and a few inland that stand on their own merit), cool bars, cool cafes, cool rooftops for drinks, gelato spots, pizza spots, nightlife, and anything else that is a cool cultural experience for the area (or immediately adjacent) that we can explore while waiting to go to Capri? Think recommendations that would be suitable for theinfatuation.com, eater.com, or a well-regarded and chic travel blog or Instagram account.

Sheet Positano Night 1 Restaurants
A1: Name | B1: Type | C1: Vibe | D1: Notes | E1: Walking Distance | F1: Driving Distance | G1: Google Maps
A2: Ristorante La Cambusa | B2: Seafood / Italian | C2: Classic, casual seaside | D2: Right near the beach. Fresh fish, grilled veggies, pasta. Easy walk downhill. Great if you want a low-key but tasty dinner. | E2: 6 mins | F2: 1 min | G2: =HYPERLINK("https://www.google.com/maps/search/"&ENCODEURL(A2&", Positano, Italy")) -> https://www.google.com/maps/search/Ristorante%20La%20Cambusa%2C%20Positano%2C%20Italy
A3: Casa e Bottega | B3: Healthier / Light | C3: Bright, modern | D3: About 3–5 min from Savoia. Known for lighter Mediterranean dishes. Great if you want something refreshing post-cooking class. Open till ~9:30pm. | E3: 4 mins | F3: 16 mins | G3: =HYPERLINK("https://www.google.com/maps/search/"&ENCODEURL(A3&", Positano, Italy")) -> https://www.google.com/maps/search/Casa%20e%20Bottega%2C%20Positano%2C%20Italy
A4: Ristorante Il Capitano | B4: Seafood | C4: Romantic, sea view | D4: Slightly uphill (7–10 min walk), nice for a peaceful, scenic dinner if you still have an appetite. Good for wine and a shared dish. | E4: 11 mins | F4: 14 mins | G4: =HYPERLINK("https://www.google.com/maps/search/"&ENCODEURL(A4&", Positano, Italy")) -> https://www.google.com/maps/search/Ristorante%20Il%20Capitano%2C%20Positano%2C%20Italy
A5: Valle dei Mulini | B5: Pizzeria / trattoria | C5: Casual, quick | D5: Closed? Around the corner from Savoia. Simple pizza, pasta, and wine. Solid backup plan if you're tired. Affordable. | E5: 6 hours 7 mins | F5: 1 hour 2 mins | G5: =HYPERLINK("https://www.google.com/maps/search/"&ENCODEURL(A5&", Positano, Italy")) -> https://www.google.com/maps/search/Valle%20dei%20Mulini%2C%20Positano%2C%20Italy
A6: Ristorante Da Bruno | B6: Italian trattoria | C6: Casual-local | D6: Just up Viale Pasitea. Friendly, informal, traditional Amalfi fare. Good for post-travel ease. | E6: 5 mins | F6: 1 min | G6: =HYPERLINK("https://www.google.com/maps/search/"&ENCODEURL(A6&", Positano, Italy")) -> https://www.google.com/maps/search/Ristorante%20Da%20Bruno%2C%20Positano%2C%20Italy
A7: Il Tridente Positano | B7: Italian/Seafood | C7: Terrace, Mellow, Grown up | D7: Found on Maps, nearby, cool terrace outside. Later mentioned by ChatGPT - good for a nightcap. | E7: 8 mins | F7: 15 mins | G7: =HYPERLINK("https://www.google.com/maps/search/"&ENCODEURL(A7&", Positano, Italy")) -> https://www.google.com/maps/search/Il%20Tridente%20Positano%2C%20Positano%2C%20Italy
D9: ChatGPT Convo
A10: =HYPERLINK(G2,A2) -> Ristorante La Cambusa | D10: 🕰️ Hours
A11: =HYPERLINK(G3,A3) -> Casa e Bottega | D11: Most of these spots serve dinner starting 7:00–7:30 PM and remain open until 10:30–11:00 PM in September. No strict reservation needed for the casual ones, but call ahead for Il Capitano or La Cambusa if you'd prefer a terrace table.
A12: =HYPERLINK(G4,A4) -> Ristorante Il Capitano
A13: =HYPERLINK(G5,A5) -> Valle dei Mulini | D13: ✅ Recommendation
A14: =HYPERLINK(G6,A6) -> Ristorante Da Bruno | D14: If you're tired and full but want a good vibe, Casa e Bottega or Valle dei Mulini are perfect.
A15: =HYPERLINK(G7,A7) -> Il Tridente Positano
D16: If you still want a proper sit-down meal with some wine and views, La Cambusa is the best mix of ease + quality right on the beach.
D18: Let me know if you want help calling or emailing one of them to hold a table.

Sheet ChatGPT Itinerary 1
A1: Name | B1: Type | C1: Emoji | D1: Description | E1: Address | F1: Hours | G1: Google Maps | H1: Special Notes | I1: Recommended By | J1: LatLong | K1: Latitude | L1: Longitude
A2: Artemisia Domus (Naples) | B2: Hotel | C2: 🏨 | D2: Boutique hotel in central Naples with elegant design and great breakfast. | E2: Via dei Carrozzieri a Monteoliveto 13, 80134 Napoli, Italy | F2: 24/7 (hotel) | G2: =HYPERLINK("https://www.google.com/maps/search/"&ENCODEURL(A2)) -> https://www.google.com/maps/search/Artemisia%20Domus%20%28Naples%29 | H2: Boutique B&B with stylish rooms; complimentary breakfast and pre-arrival concierge. | I2: ChatGPT - https://chatgpt.com/c/6846f0da-7884-8009-ad13-dba01dfa021d | J2: 40.845634, 14.2517054 | K2: =IFERROR(__xludf.DUMMYFUNCTION("SPLIT(J2,"", "")"),40.845634) -> 40.845634 | L2: =IFERROR(__xludf.DUMMYFUNCTION("""COMPUTED_VALUE"""),14.2517054) -> 14.251705
A3: The Britannique by Hilton (Naples) | B3: Hotel | C3: 🏨 | D3: Modern hotel in Naples with panoramic rooftop bar and sea views. | E3: C.so Vittorio Emanuele, 133, 80121 Napoli NA, Italy | F3: 24/7 (hotel) | G3: =HYPERLINK("https://www.google.com/maps/search/"&ENCODEURL(A3)) -> https://www.google.com/maps/search/The%20Britannique%20by%20Hilton%20%28Naples%29 | H3: Modern hotel with rooftop bar & spa; reserve for sunset cocktails. | I3: ChatGPT - https://chatgpt.com/c/6846f0da-7884-8009-ad13-dba01dfa021d | J3: 40.836915, 14.2296809 | K3: =IFERROR(__xludf.DUMMYFUNCTION("SPLIT(J3,"", "")"),40.836915) -> 40.836915 | L3: =IFERROR(__xludf.DUMMYFUNCTION("""COMPUTED_VALUE"""),14.2296809) -> 14.229681
A4: Gino Sorbillo (Naples) | B4: Restaurant | C4: 🍕 | D4: One of Naples’ most iconic pizzerias in the historic center. | E4: Via dei Tribunali 32, 80138 Napoli, Italy | F4: Mon–Sat 12:00–15:30 & 19:00–23:30; Sun closed (fontelina-capri.com, happycow.net, perplexity.ai, tripadvisor.com) | G4: =HYPERLINK("https://www.google.com/maps/search/"&ENCODEURL(A4)) -> https://www.google.com/maps/search/Gino%20Sorbillo%20%28Naples%29 | H4: Famous Neapolitan pizza, long lines – best to arrive just before opening; try their pineapple pizza. | I4: ChatGPT - https://chatgpt.com/c/6846f0da-7884-8009-ad13-dba01dfa021d | J4: 40.850421, 14.2553143 | K4: =IFERROR(__xludf.DUMMYFUNCTION("SPLIT(J4,"", "")"),40.850421) -> 40.850421 | L4: =IFERROR(__xludf.DUMMYFUNCTION("""COMPUTED_VALUE"""),14.2553143) -> 14.255314
A5: L’Antica Pizzeria da Michele (Naples) | B5: Restaurant | C5: 🍕 | D5: Historic, no-frills spot for some of Naples’ best traditional pizza. | E5: Via Cesare Sersale 1, 80139 Napoli | F5: Typically 11:00–23:00, often closes Mon (confirm) | G5: =HYPERLINK("https://www.google.com/maps/search/"&ENCODEURL(A5)) -> https://www.google.com/maps/search/L%E2%80%99Antica%20Pizzeria%20da%20Michele%20%28Naples%29 | H5: Historic classic; very simple menu (Margherita/Marinara only). | I5: ChatGPT - https://chatgpt.com/c/6846f0da-7884-8009-ad13-dba01dfa021d | J5: 40.8497752, 14.2632371 | K5: =IFERROR(__xludf.DUMMYFUNCTION("SPLIT(J5,"", "")"),40.8497752) -> 40.849775 | L5: =IFERROR(__xludf.DUMMYFUNCTION("""COMPUTED_VALUE"""),14.2632371) -> 14.263237
A6: Gay‑Odin (Naples) | B6: Shop | C6: 🍦 | D6: Artisanal chocolate shop famous for its gelato and heritage sweets. | E6: Via San Biagio dei Librai 44, 80138 Napoli | F6: 10:00–20:00 daily | G6: =HYPERLINK("https://www.google.com/maps/search/"&ENCODEURL(A6)) -> https://www.google.com/maps/search/Gay%E2%80%91Odin%20%28Naples%29 | H6: Artisanal chocolates & gelato; great for gifting or a quick treat. | I6: ChatGPT - https://chatgpt.com/c/6846f0da-7884-8009-ad13-dba01dfa021d | J6: 40.84968560000001, 14.2589603 | K6: =IFERROR(__xludf.DUMMYFUNCTION("SPLIT(J6,"", "")"),40.8496856) -> 40.849686 | L6: =IFERROR(__xludf.DUMMYFUNCTION("""COMPUTED_VALUE"""),14.2589603) -> 14.25896
A7: Hotel Villa Brunella (Capri) | B7: Hotel | C7: 🏨 | D7: Romantic and quiet boutique hotel with stunning terrace views. | E7: 80073, Via Tragara, 24a, 80073 Capri NA, Italy | F7: 24/7 (hotel) | G7: =HYPERLINK("https://www.google.com/maps/search/"&ENCODEURL(A7)) -> https://www.google.com/maps/search/Hotel%20Villa%20Brunella%20%28Capri%29 | H7: Terrace views over Marina Piccola; request sea-view rooms and private shuttle to Capri town. | I7: ChatGPT - https://chatgpt.com/c/6846f0da-7884-8009-ad13-dba01dfa021d | J7: 40.5461439, 14.2495769 | K7: =IFERROR(__xludf.DUMMYFUNCTION("SPLIT(J7,"", "")"),40.5461439) -> 40.546144 | L7: =IFERROR(__xludf.DUMMYFUNCTION("""COMPUTED_VALUE"""),14.2495769) -> 14.249577
A8: JK Place Capri (Capri) | B8: Hotel | C8: 🏨 | D8: Luxury waterfront hotel near Marina Grande with impeccable service. | E8: Via Roma 71, 80073 Capri NA, Italy | F8: 24/7 (hotel) | G8: =HYPERLINK("https://www.google.com/maps/search/"&ENCODEURL(A8)) -> https://www.google.com/maps/search/JK%20Place%20Capri%20%28Capri%29 | H8: Luxury beachfront hotel; ideal for romantic dinners by the sea. | I8: ChatGPT - https://chatgpt.com/c/6846f0da-7884-8009-ad13-dba01dfa021d | J8: 40.54987939999999, 14.2401657 | K8: =IFERROR(__xludf.DUMMYFUNCTION("SPLIT(J8,"", "")"),40.5498793999999) -> 40.549879 | L8: =IFERROR(__xludf.DUMMYFUNCTION("""COMPUTED_VALUE"""),14.2401657) -> 14.240166
A9: La Fontelina (Capri) | B9: Beach Club | C9: ⛱️ | D9: Iconic beach club near Faraglioni rocks with chic loungers and fresh seafood. | E9: Località Faraglioni, 80073 Capri NA, Italy | F9: Beach: 9:00–19:00; Restaurant: 12:30–16:00 daily | G9: =HYPERLINK("https://www.google.com/maps/search/"&ENCODEURL(A9)) -> https://www.google.com/maps/search/La%20Fontelina%20%28Capri%29 | H9: Lunch-only in summer; €190 p.p. min. spend in high season; shuttle boat returns 15:00–18:30. | I9: ChatGPT - https://chatgpt.com/c/6846f0da-7884-8009-ad13-dba01dfa021d | J9: 40.5434303, 14.2523999 | K9: =IFERROR(__xludf.DUMMYFUNCTION("SPLIT(J9,"", "")"),40.5434303) -> 40.54343 | L9: =IFERROR(__xludf.DUMMYFUNCTION("""COMPUTED_VALUE"""),14.2523999) -> 14.2524
A10: Da Gelsomina (Capri) | B10: Restaurant | C10: 🍷 | D10: Charming vineyard-side restaurant in Anacapri with local dishes and wine. | E10: Via Migliara, 72, 80071 Anacapri NA, Italy | F10: ~12:00–15:00 & 19:00–22:00 | G10: =HYPERLINK("https://www.google.com/maps/search/"&ENCODEURL(A10)) -> https://www.google.com/maps/search/Da%20Gelsomina%20%28Capri%29 | H10: Hilltop Anacapri vineyard spot; dress smart-casual. | I10: ChatGPT - https://chatgpt.com/c/6846f0da-7884-8009-ad13-dba01dfa021d | J10: 40.5409493, 14.2102105 | K10: =IFERROR(__xludf.DUMMYFUNCTION("SPLIT(J10,"", "")"),40.5409493) -> 40.540949 | L10: =IFERROR(__xludf.DUMMYFUNCTION("""COMPUTED_VALUE"""),14.2102105) -> 14.210211
A11: Belmond Hotel Caruso (Ravello) | B11: Hotel | C11: 🏨 | D11: Historic palace hotel with an infinity pool overlooking the Amalfi Coast. | E11: Piazza San Giovanni del Toro 2, 84010 Ravello (SA), Italy | F11: Hotel: 24/7; Pool: 08:00–19:00 | G11: =HYPERLINK("https://www.google.com/maps/search/"&ENCODEURL(A11)) -> https://www.google.com/maps/search/Belmond%20Hotel%20Caruso%20%28Ravello%29 | H11: Iconic infinity pool; spa and morning yoga available. | I11: ChatGPT - https://chatgpt.com/c/6846f0da-7884-8009-ad13-dba01dfa021d | J11: 40.6514101, 14.6129723 | K11: =IFERROR(__xludf.DUMMYFUNCTION("SPLIT(J11,"", "")"),40.6514101) -> 40.65141 | L11: =IFERROR(__xludf.DUMMYFUNCTION("""COMPUTED_VALUE"""),14.6129723) -> 14.612972
A12: Villa Maria Ravello | B12: Hotel | C12: 🏨 | D12: Peaceful hotel with garden terraces and a focus on local cuisine. | E12: Via Santa Chiara, 2, 84010 Ravello SA, Italy | F12: 24/7 (hotel); breakfast until ~10:30 | G12: =HYPERLINK("https://www.google.com/maps/search/"&ENCODEURL(A12)) -> https://www.google.com/maps/search/Villa%20Maria%20Ravello | H12: Quiet boutique hotel; known for homegrown lemon-themed dishes. | I12: ChatGPT - https://chatgpt.com/c/6846f0da-7884-8009-ad13-dba01dfa021d | J12: 40.6468104, 14.6103006 | K12: =IFERROR(__xludf.DUMMYFUNCTION("SPLIT(J12,"", "")"),40.6468104) -> 40.64681 | L12: =IFERROR(__xludf.DUMMYFUNCTION("""COMPUTED_VALUE"""),14.6103006) -> 14.610301
A13: Villa Rufolo (Ravello) | B13: Attraction | C13: 🏛️ | D13: Historic villa and gardens with panoramic views and concerts. | E13: Piazza Duomo, 84010 Ravello (SA), Italy | F13: Gardens: ~09:00–19:00 | G13: =HYPERLINK("https://www.google.com/maps/search/"&ENCODEURL(A13)) -> https://www.google.com/maps/search/Villa%20Rufolo%20%28Ravello%29 | H13: Historic gardens with panoramic terrace; host of summer music festivals. | I13: ChatGPT - https://chatgpt.com/c/6846f0da-7884-8009-ad13-dba01dfa021d | J13: 40.6491825, 14.6116481 | K13: =IFERROR(__xludf.DUMMYFUNCTION("SPLIT(J13,"", "")"),40.6491825) -> 40.649183 | L13: =IFERROR(__xludf.DUMMYFUNCTION("""COMPUTED_VALUE"""),14.6116481) -> 14.611648
A14: Wagner Tours (Wine Experience, Ravello) | B14: Wine Tour | C14: 🍇 | D14: Guided wine experiences and tastings in Ravello. | E14: Via del Santuario, 84010 Ravello SA, Italy | F14: Wine tastings by appointment (~11:00–17:00) | G14: =HYPERLINK("https://www.google.com/maps/search/"&ENCODEURL(A14)) -> https://www.google.com/maps/search/Wagner%20Tours%20%28Wine%20Experience%2C%20Ravello%29 | H14: Boutique, garden-based tastings; reserve in advance. | I14: ChatGPT - https://chatgpt.com/c/6846f0da-7884-8009-ad13-dba01dfa021d | J14: 40.6515802, 14.6140606 | K14: =IFERROR(__xludf.DUMMYFUNCTION("SPLIT(J14,"", "")"),40.6515802) -> 40.65158 | L14: =IFERROR(__xludf.DUMMYFUNCTION("""COMPUTED_VALUE"""),14.6140606) -> 14.614061
A15: Rossellinis at Palazzo Avino (Ravello) | B15: Restaurant | C15: 🍽️ | D15: Michelin-starred restaurant with romantic cliffside dining. | E15: Via San Giovanni del Toro, 84010 Ravello SA, Italy | F15: Lunch: 12:30–17:00; Dinner: 18:30–22:30; closed Nov–Mar | G15: =HYPERLINK("https://www.google.com/maps/search/"&ENCODEURL(A15)) -> https://www.google.com/maps/search/Rossellinis%20at%20Palazzo%20Avino%20%28Ravello%29 | H15: 1-Michelin star; dress upscale; Chef’s & Sommelier’s Tables available. | I15: ChatGPT - https://chatgpt.com/c/6846f0da-7884-8009-ad13-dba01dfa021d | J15: 40.6504913, 14.6129035 | K15: =IFERROR(__xludf.DUMMYFUNCTION("SPLIT(J15,"", "")"),40.6504913) -> 40.650491 | L15: =IFERROR(__xludf.DUMMYFUNCTION("""COMPUTED_VALUE"""),14.6129035) -> 14.612903
A16: Casa Angelina (Praiano) | B16: Hotel | C16: 🏨 | D16: Minimalist, adults-only luxury hotel with modern art and sea views. | E16: Piazza Antiche Mura, 22, 84010 Praiano SA, Italy | F16: Hotel: 24/7; Pool: ~08:00–19:00 | G16: =HYPERLINK("https://www.google.com/maps/search/"&ENCODEURL(A16)) -> https://www.google.com/maps/search/Casa%20Angelina%20%28Praiano%29 | H16: Adults-only, minimalist luxury; great for spa days and rooftop cocktails. | I16: ChatGPT - https://chatgpt.com/c/6846f0da-7884-8009-ad13-dba01dfa021d | J16: 40.6117319, 14.5335099 | K16: =IFERROR(__xludf.DUMMYFUNCTION("SPLIT(J16,"", "")"),40.6117319) -> 40.611732 | L16: =IFERROR(__xludf.DUMMYFUNCTION("""COMPUTED_VALUE"""),14.5335099) -> 14.53351
A17: Monastero Santa Rosa Hotel (Conca dei Marini) | B17: Hotel | C17: 🏨 | D17: 5-star cliffside monastery-turned-hotel with a world-class spa. | E17: Via Krupp, 11, 84010 Conca dei Marini SA, Italy | F17: Hotel: 24/7; Spa & pool open ~09:00–19:00 | G17: =HYPERLINK("https://www.google.com/maps/search/"&ENCODEURL(A17)) -> https://www.google.com/maps/search/Monastero%20Santa%20Rosa%20Hotel%20%28Conca%20dei%20Marini%29 | H17: Ex-monastery with cliffside spa; Il Refettorio located onsite. | I17: ChatGPT - https://chatgpt.com/c/6846f0da-7884-8009-ad13-dba01dfa021d | J17: 40.6163236, 14.5753912 | K17: =IFERROR(__xludf.DUMMYFUNCTION("SPLIT(J17,"", "")"),40.6163236) -> 40.616324 | L17: =IFERROR(__xludf.DUMMYFUNCTION("""COMPUTED_VALUE"""),14.5753912) -> 14.575391
A18: One Fire Beach Club (Praiano) | B18: Beach Club | C18: ⛱️ | D18: Laid-back beach club known for music, fire shows, and chill vibes. | E18: Marina di Praia, 84017 Praiano SA, Italy | F18: ~09:00–18:00 | G18: =HYPERLINK("https://www.google.com/maps/search/"&ENCODEURL(A18)) -> https://www.google.com/maps/search/One%20Fire%20Beach%20Club%20%28Praiano%29 | H18: Casual beach club with fire shows & DJ sets; bring cash. | I18: ChatGPT - https://chatgpt.com/c/6846f0da-7884-8009-ad13-dba01dfa021d | J18: 40.6134729, 14.5394424 | K18: =IFERROR(__xludf.DUMMYFUNCTION("SPLIT(J18,"", "")"),40.6134729) -> 40.613473 | L18: =IFERROR(__xludf.DUMMYFUNCTION("""COMPUTED_VALUE"""),14.5394424) -> 14.539442
A19: Lido degli Artisti (Praiano) | B19: Beach Club | C19: ⛱️ | D19: Cozy beach with sunbeds and a dramatic cliff backdrop. | E19: Località La Gavitella, 84017 Praiano SA, Italy | F19: ~09:00–18:00 | G19: =HYPERLINK("https://www.google.com/maps/search/"&ENCODEURL(A19)) -> https://www.google.com/maps/search/Lido%20degli%20Artisti%20%28Praiano%29 | H19: Cliffside sunbeds for rent; small snack kiosk; relaxed vibe. | I19: ChatGPT - https://chatgpt.com/c/6846f0da-7884-8009-ad13-dba01dfa021d | J19: 40.6138362, 14.5204525 | K19: =IFERROR(__xludf.DUMMYFUNCTION("SPLIT(J19,"", "")"),40.6138362) -> 40.613836 | L19: =IFERROR(__xludf.DUMMYFUNCTION("""COMPUTED_VALUE"""),14.5204525) -> 14.520452
A20: Il Refettorio (Monastero Santa Rosa) | B20: Restaurant | C20: 🍽️ | D20: Michelin-starred dining within the Monastero Santa Rosa Hotel. | E20: Via Krupp, 11, 84010 Conca dei Marini SA, Italy | F20: Dinner only, ~19:00–22:00 | G20: =HYPERLINK("https://www.google.com/maps/search/"&ENCODEURL(A20)) -> https://www.google.com/maps/search/Il%20Refettorio%20%28Monastero%20Santa%20Rosa%29 | H20: Michelin-starred in monastery; dress smart-casual, reservations required. | I20: ChatGPT - https://chatgpt.com/c/6846f0da-7884-8009-ad13-dba01dfa021d | J20: 40.6163236, 14.5753912 | K20: =IFERROR(__xludf.DUMMYFUNCTION("SPLIT(J20,"", "")"),40.6163236) -> 40.616324 | L20: =IFERROR(__xludf.DUMMYFUNCTION("""COMPUTED_VALUE"""),14.5753912) -> 14.575391
A21: Kasai (Praiano) | B21: Restaurant | C21: 🍝 | D21: Locally loved spot with fresh seafood and sunset views. | E21: Via G. Capriglione, 2, 84017 Praiano SA, Italy | F21: ~12:00–15:00 & 19:00–22:00 | G21: =HYPERLINK("https://www.google.com/maps/search/"&ENCODEURL(A21)) -> https://www.google.com/maps/search/Kasai%20%28Praiano%29 | H21: Fresh seafood & sushi fusion; sunset tables book fast. | I21: ChatGPT - https://chatgpt.com/c/6846f0da-7884-8009-ad13-dba01dfa021d | J21: 40.6087328, 14.5268626 | K21: =IFERROR(__xludf.DUMMYFUNCTION("SPLIT(J21,"", "")"),40.6087328) -> 40.608733 | L21: =IFERROR(__xludf.DUMMYFUNCTION("""COMPUTED_VALUE"""),14.5268626) -> 14.526863
A22: La Tagliata (Positano) | B22: Cooking Class | C22: 👩‍🍳 | D22: Rustic, family-run restaurant offering fun and hearty cooking classes. | E22: Via Tagliata, 1, 84017 Positano SA, Italy | F22: Lunch & Dinner (check seasonally) | G22: =HYPERLINK("https://www.google.com/maps/search/"&ENCODEURL(A22)) -> https://www.google.com/maps/search/La%20Tagliata%20%28Positano%29 | H22: Rustic family meal & cooking class; farm-fresh ingredients; open-air terrace. | I22: ChatGPT - https://chatgpt.com/c/6846f0da-7884-8009-ad13-dba01dfa021d | J22: 40.6332256, 14.4930882 | K22: =IFERROR(__xludf.DUMMYFUNCTION("SPLIT(J22,"", "")"),40.6332256) -> 40.633226 | L22: =IFERROR(__xludf.DUMMYFUNCTION("""COMPUTED_VALUE"""),14.4930882) -> 14.493088
A23: Mamma Agata (Ravello) | B23: Cooking Class | C23: 👩‍🍳 | D23: Charming home-based cooking school with sea views and legendary hosts. | E23: Via San Francesco, 24, 84010 Ravello SA, Italy | F23: Lunch only (~12:00–14:30); closed Sun & Mon | G23: =HYPERLINK("https://www.google.com/maps/search/"&ENCODEURL(A23)) -> https://www.google.com/maps/search/Mamma%20Agata%20%28Ravello%29 | H23: Home-style cooking in a villa garden; traditional Amalfi recipes. | I23: ChatGPT - https://chatgpt.com/c/6846f0da-7884-8009-ad13-dba01dfa021d | J23: 40.6484534, 14.6118254 | K23: =IFERROR(__xludf.DUMMYFUNCTION("SPLIT(J23,"", "")"),40.6484534) -> 40.648453 | L23: =IFERROR(__xludf.DUMMYFUNCTION("""COMPUTED_VALUE"""),14.6118254) -> 14.611825
A24: Franco’s Bar (Positano) | B24: Bar | C24: 🍹 | D24: Trendy cocktail bar with jaw-dropping sunset views. | E24: Via Pasitea, 300, 84017 Positano SA, Italy | F24: ~16:00–00:00 | G24: =HYPERLINK("https://www.google.com/maps/search/"&ENCODEURL(A24)) -> https://www.google.com/maps/search/Franco%E2%80%99s%20Bar%20%28Positano%29 | H24: Sunset cocktails with panoramic views; arrive early for best seats. | I24: ChatGPT - https://chatgpt.com/c/6846f0da-7884-8009-ad13-dba01dfa021d | J24: 40.6287893, 14.4815807 | K24: =IFERROR(__xludf.DUMMYFUNCTION("SPLIT(J24,"", "")"),40.6287893) -> 40.628789 | L24: =IFERROR(__xludf.DUMMYFUNCTION("""COMPUTED_VALUE"""),14.4815807) -> 14.481581
A25: Ristorante Il Pirata (Praiano) | B25: Restaurant | C25: 🍽️ | D25: Dramatic sea cave restaurant serving fresh Mediterranean dishes. | E25: Via Marina di Praia, 2, 84017 Praiano SA, Italy | F25: Lunch: 12:00–15:00; Dinner: 19:00–22:30 | G25: =HYPERLINK("https://www.google.com/maps/search/"&ENCODEURL(A25)) -> https://www.google.com/maps/search/Ristorante%20Il%20Pirata%20%28Praiano%29 | H25: Dining in a seaside grotto; perfect at golden hour; reserve ahead. | I25: ChatGPT - https://chatgpt.com/c/6846f0da-7884-8009-ad13-dba01dfa021d | J25: 40.6142489, 14.5392983 | K25: =IFERROR(__xludf.DUMMYFUNCTION("SPLIT(J25,"", "")"),40.6142489) -> 40.614249 | L25: =IFERROR(__xludf.DUMMYFUNCTION("""COMPUTED_VALUE"""),14.5392983) -> 14.539298

Sheet Manus Itinerary 1
A1: Name | B1: City | C1: Type | D1: Emoji | E1: Description | F1: Hours of Operation | G1: Special Notes | H1: Google Maps | I1: Address | J1: Recommended By | K1: LatLong | L1: Latitude | M1: Longitude
A2: Romeo Hotel Naples | B2: Naples | C2: Hotel | D2: 🏨 | E2: Luxury waterfront hotel with Michelin-starred dining, panoramic views of Bay of Naples and Vesuvius, modern design with sophisticated atmosphere | F2: Check-in: 3:00 PM, Check-out: 11:00 AM | G2: Perfect for arrival/departure convenience, has Michelin dining on-site | H2: =HYPERLINK("https://www.google.com/maps/search/"&ENCODEURL(A2)) -> https://www.google.com/maps/search/Romeo%20Hotel%20Naples | I2: Via Cristoforo Colombo, 45, 80133 Napoli NA, Italy | J2: Manus - https://manus.im/app/KJC6Ixn9ZFEgpriWR1GDzd | K2: 40.8403661, 14.2558654 | L2: 40.840366 | M2: 14.255865
A3: Spaccanapoli | B3: Naples | C3: Historic Street | D3: 🏛️ | E3: Ancient Roman road cutting through Naples historic center, UNESCO World Heritage site | F3: Always open | G3: Walk the entire length for authentic Naples experience | H3: =HYPERLINK("https://www.google.com/maps/search/"&ENCODEURL(A3)) -> https://www.google.com/maps/search/Spaccanapoli | I3: Naples, Metropolitan City of Naples, Italy | J3: Manus - https://manus.im/app/KJC6Ixn9ZFEgpriWR1GDzd | K3: 40.8517746, 14.2681244 | L3: 40.851775 | M3: 14.268124
A4: Naples Cathedral (Duomo) | B4: Naples | C4: Cathedral | D4: ⛪ | E4: Historic cathedral with San Gennaro chapel, beautiful architecture | F4: 8:00 AM - 12:30 PM, 4:30 PM - 7:00 PM | G4: Free entry, dress modestly | H4: =HYPERLINK("https://www.google.com/maps/search/"&ENCODEURL(A4)) -> https://www.google.com/maps/search/Naples%20Cathedral%20%28Duomo%29 | I4: Vico Sedil Capuano, 48, 80138 Napoli NA, Italy | J4: Manus - https://manus.im/app/KJC6Ixn9ZFEgpriWR1GDzd | K4: 40.8531893, 14.2603334 | L4: 40.853189 | M4: 14.260333
A5: San Gregorio Armeno | B5: Naples | C5: Artisan Street | D5: 🎨 | E5: Christmas artisan street with traditional Neapolitan nativity scenes | F5: 9:00 AM - 7:00 PM | G5: Famous for handmade nativity figures year-round | H5: =HYPERLINK("https://www.google.com/maps/search/"&ENCODEURL(A5)) -> https://www.google.com/maps/search/San%20Gregorio%20Armeno | I5: Via S. Gregorio Armeno, 80138 Napoli NA, Italy | J5: Manus - https://manus.im/app/KJC6Ixn9ZFEgpriWR1GDzd | K5: 40.8500804, 14.2578099 | L5: 40.85008 | M5: 14.25781
A6: Piazza del Gesù Nuovo | B6: Naples | C6: Historic Square | D6: 🏛️ | E6: Beautiful baroque square with historic churches | F6: Always open | G6: Great for people watching and photos | H6: =HYPERLINK("https://www.google.com/maps/search/"&ENCODEURL(A6)) -> https://www.google.com/maps/search/Piazza%20del%20Ges%C3%B9%20Nuovo | I6: Piazza del Gesù Nuovo, 80134 Napoli NA, Italy | J6: Manus - https://manus.im/app/KJC6Ixn9ZFEgpriWR1GDzd | K6: 40.8469688, 14.2517718 | L6: 40.846969 | M6: 14.251772
A7: La Locanda Gesù Vecchio | B7: Naples | C7: Restaurant | D7: 🍝 | E7: Family-run trattoria near Piazza del Gesù, rustic yet refined atmosphere, warm hospitality | F7: Dinner: 7:00 PM - 11:00 PM | G7: Must-try: Paccheri al ragù napoletano, owner brings complimentary wine, feels like dining in someone's home | H7: =HYPERLINK("https://www.google.com/maps/search/"&ENCODEURL(A7)) -> https://www.google.com/maps/search/La%20Locanda%20Ges%C3%B9%20Vecchio | I7: Via Giovanni Paladino, 26, 80138 Napoli NA, Italy | J7: Manus - https://manus.im/app/KJC6Ixn9ZFEgpriWR1GDzd | K7: 40.8472376, 14.2571481 | L7: 40.847238 | M7: 14.257148
A8: Palazzo Petrucci | B8: Naples | C8: Fine Dining Restaurant | D8: 🍽️ | E8: Posillipo location with Gulf of Naples views, modern Italian cuisine with dramatic presentation | F8: Dinner: 7:30 PM - 11:00 PM | G8: Sea urchin risotto served in spiny shell, fine dining alternative | H8: =HYPERLINK("https://www.google.com/maps/search/"&ENCODEURL(A8)) -> https://www.google.com/maps/search/Palazzo%20Petrucci | I8: P.za S. Domenico Maggiore, 33, 80134 Napoli NA, Italy | J8: Manus - https://manus.im/app/KJC6Ixn9ZFEgpriWR1GDzd | K8: 40.8483036, 14.254577 | L8: 40.848304 | M8: 14.254577
A9: Veritas | B9: Naples | C9: Fine Dining Restaurant | D9: ⭐ | E9: Cerebral, meticulous cuisine with multiple tasting menus, wine pairings from Campania producers | F9: Dinner: 7:30 PM - 11:00 PM | G9: Artistic presentation, book 2-4 weeks advance | H9: =HYPERLINK("https://www.google.com/maps/search/"&ENCODEURL(A9)) -> https://www.google.com/maps/search/Veritas | I9: C.so Vittorio Emanuele, 141, 80121 Napoli NA, Italy | J9: Manus - https://manus.im/app/KJC6Ixn9ZFEgpriWR1GDzd | K9: 40.8372389, 14.2313759 | L9: 40.837239 | M9: 14.231376
A10: Mimì alla Ferrovia | B10: Naples | C10: Traditional Restaurant | D10: 🍝 | E10: Operating since 1943, old-school Neapolitan elegance, classic atmosphere | F10: Lunch & Dinner | G10: Classic ziti al ragù and parmigiana, traditional atmosphere | H10: =HYPERLINK("https://www.google.com/maps/search/"&ENCODEURL(A10)) -> https://www.google.com/maps/search/Mim%C3%AC%20alla%20Ferrovia | I10: Via Alfonso D'Aragona, 19/21, 80139 Napoli NA, Italy | J10: Manus - https://manus.im/app/KJC6Ixn9ZFEgpriWR1GDzd | K10: 40.8535418, 14.2671748 | L10: 40.853542 | M10: 14.267175
A11: Caffè Gambrinus | B11: Naples | C11: Historic Café | D11: ☕ | F11: 7:00 AM - 2:00 AM | G11: Perfect for final Naples coffee before departure | H11: =HYPERLINK("https://www.google.com/maps/search/"&ENCODEURL(A11)) -> https://www.google.com/maps/search/Caff%C3%A8%20Gambrinus | I11: Via Chiaia, 1, 80132 Napoli NA, Italy | J11: Manus - https://manus.im/app/KJC6Ixn9ZFEgpriWR1GDzd | K11: 40.8367945, 14.248479 | L11: 40.836795 | M11: 14.248479
A12: Scaturchio | B12: Naples | C12: Pastry Shop | D12: 🥐 | E12: Famous pastry shop for traditional sfogliatelle | F12: 7:30 AM - 8:30 PM | G12: Must-try: sfogliatelle, historic Naples institution | H12: =HYPERLINK("https://www.google.com/maps/search/"&ENCODEURL(A12)) -> https://www.google.com/maps/search/Scaturchio | I12: P.za S. Domenico Maggiore, 19, 80134 Napoli NA, Italy | J12: Manus - https://manus.im/app/KJC6Ixn9ZFEgpriWR1GDzd | K12: 40.8482509, 14.2549272 | L12: 40.848251 | M12: 14.254927
A13: National Archaeological Museum | B13: Naples | C13: Museum | D13: 🏛️ | E13: Houses Pompeii artifacts and ancient Roman treasures | F13: 9:00 AM - 7:30 PM (closed Tuesdays) | G13: €15 entrance, world-class Pompeii collection | H13: =HYPERLINK("https://www.google.com/maps/search/"&ENCODEURL(A13)) -> https://www.google.com/maps/search/National%20Archaeological%20Museum | I13: Piazza Museo, 19, 80135 Napoli NA, Italy | J13: Manus - https://manus.im/app/KJC6Ixn9ZFEgpriWR1GDzd | K13: 40.8534745, 14.2512744 | L13: 40.853474 | M13: 14.251274
A14: Palazzo Reale | B14: Naples | C14: Royal Palace | D14: 👑 | E14: Royal palace with gardens and historic rooms | F14: 9:00 AM - 8:00 PM (closed Wednesdays) | G14: €4 entrance, beautiful royal apartments | H14: =HYPERLINK("https://www.google.com/maps/search/"&ENCODEURL(A14)) -> https://www.google.com/maps/search/Palazzo%20Reale | I14: Piazza del Plebiscito, 1, 80132 Napoli NA, Italy | J14: Manus - https://manus.im/app/KJC6Ixn9ZFEgpriWR1GDzd | K14: 40.8369443, 14.2494124 | L14: 40.836944 | M14: 14.249412
A15: Castel dell'Ovo | B15: Naples | C15: Seaside Castle | D15: 🏰 | E15: Seaside castle with panoramic views of Bay of Naples | F15: 9:00 AM - 6:30 PM | G15: Free entry, great for sunset photos | H15: =HYPERLINK("https://www.google.com/maps/search/"&ENCODEURL(A15)) -> https://www.google.com/maps/search/Castel%20dell%27Ovo | I15: Via Eldorado, 3, 80132 Napoli NA, Italy | J15: Manus - https://manus.im/app/KJC6Ixn9ZFEgpriWR1GDzd | K15: 40.8279173, 14.2484676 | L15: 40.827917 | M15: 14.248468
A16: Via Toledo | B16: Naples | C16: Shopping Street | D16: 🛍️ | E16: Main shopping street with local and international brands | F16: 9:00 AM - 8:00 PM | G16: Mix of shops and cafes, pedestrian-friendly | H16: =HYPERLINK("https://www.google.com/maps/search/"&ENCODEURL(A16)) -> https://www.google.com/maps/search/Via%20Toledo | I16: Via Toledo, Napoli NA, Italy | J16: Manus - https://manus.im/app/KJC6Ixn9ZFEgpriWR1GDzd | K16: 40.8428212, 14.248904 | L16: 40.842821 | M16: 14.248904
A17: Galleria Umberto I | B17: Naples | C17: Shopping Gallery | D17: 🏛️ | E17: Beautiful 19th-century shopping gallery with glass dome | F17: 9:00 AM - 8:00 PM | G17: Architectural beauty, upscale shopping | H17: =HYPERLINK("https://www.google.com/maps/search/"&ENCODEURL(A17)) -> https://www.google.com/maps/search/Galleria%20Umberto%20I | I17: Galleria Umberto I, 80132 Napoli NA, Italy | J17: Manus - https://manus.im/app/KJC6Ixn9ZFEgpriWR1GDzd | K17: 40.8385287, 14.2494785 | L17: 40.838529 | M17: 14.249479
A18: Casa d'Anna ai Cristallini | B18: Naples | C18: Boutique Hotel | D18: 🏨 | E18: Intimate boutique hotel in historic center | F18: Check-in: 2:00 PM, Check-out: 11:00 AM | G18: Alternative to Romeo Hotel, more intimate setting | H18: =HYPERLINK("https://www.google.com/maps/search/"&ENCODEURL(A18)) -> https://www.google.com/maps/search/Casa%20d%27Anna%20ai%20Cristallini | I18: Via dei Cristallini, 138, 80137 Napoli NA, Italy | J18: Manus - https://manus.im/app/KJC6Ixn9ZFEgpriWR1GDzd | K18: 40.8575357, 14.2540213 | L18: 40.857536 | M18: 14.254021
A19: Naples Molo Beverello | B19: Naples | C19: Ferry Port | D19: ⛴️ | E19: Main ferry terminal for departures to Capri and Amalfi Coast | F19: Ferries: 6:20 AM - 7:20 PM | G19: Arrive 30 minutes early, buy tickets in advance | H19: =HYPERLINK("https://www.google.com/maps/search/"&ENCODEURL(A19)) -> https://www.google.com/maps/search/Naples%20Molo%20Beverello | I19: Molo Beverello, 80133 Napoli NA, Italy | J19: Manus - https://manus.im/app/KJC6Ixn9ZFEgpriWR1GDzd | K19: 40.8382086, 14.2546268 | L19: 40.838209 | M19: 14.254627
A20: Naples International Airport (NAP) | B20: Naples | C20: Airport | D20: ✈️ | E20: Main airport serving Naples and Amalfi Coast region | F20: 24 hours | G20: 30-40 minutes to city center by private transfer | H20: =HYPERLINK("https://www.google.com/maps/search/"&ENCODEURL(A20)) -> https://www.google.com/maps/search/Naples%20International%20Airport%20%28NAP%29 | I20: Naples International Airport (NAP), Viale F. Ruffo di Calabria, 80144 Napoli NA, Italy | J20: Manus - https://manus.im/app/KJC6Ixn9ZFEgpriWR1GDzd | K20: 40.8846816, 14.2891552 | L20: 40.884682 | M20: 14.289155
A21: Hotel La Palma | B21: Capri | C21: Luxury Hotel | D21: 🏨 | E21: Newly opened 2023 Oetker Collection property, neoclassical design by Francis Sultana, revival of Capri's first hotel (built 1822) | F21: Check-in: 3:00 PM, Check-out: 11:00 AM | G21: Opposite Dolce & Gabbana, has Da Gioia beach club, celebrity atmosphere | H21: =HYPERLINK("https://www.google.com/maps/search/"&ENCODEURL(A21)) -> https://www.google.com/maps/search/Hotel%20La%20Palma | I21: Via Vittorio Emanuele, 39, 80073 Capri NA, Italy | J21: Manus - https://manus.im/app/KJC6Ixn9ZFEgpriWR1GDzd | K21: 40.5503664, 14.2436652 | L21: 40.550366 | M21: 14.243665
A22: Capri Marina Grande | B22: Capri | C22: Ferry Port | D22: ⛴️ | E22: Main port for ferry arrivals and departures | F22: Ferries: 6:30 AM - 7:50 PM | G22: Take funicular to town center (5 minutes) | H22: =HYPERLINK("https://www.google.com/maps/search/"&ENCODEURL(A22)) -> https://www.google.com/maps/search/Capri%20Marina%20Grande | I22: 80076 Marina Grande, Metropolitan City of Naples, Italy | J22: Manus - https://manus.im/app/KJC6Ixn9ZFEgpriWR1GDzd | K22: 40.5533968, 14.2381784 | L22: 40.553397 | M22: 14.238178
A23: La Piazzetta | B23: Capri | C23: Famous Square | D23: 🏛️ | E23: Famous central square, people-watching hub, celebrity spotting | F23: Always open | G23: Classic Capri atmosphere, aperitivo bars | H23: =HYPERLINK("https://www.google.com/maps/search/"&ENCODEURL(A23)) -> https://www.google.com/maps/search/La%20Piazzetta | I23: Via Longano, 14, 80073 Capri NA, Italy | J23: Manus - https://manus.im/app/KJC6Ixn9ZFEgpriWR1GDzd | K23: 40.551337, 14.2433926 | L23: 40.551337 | M23: 14.243393
... A67: Da Gioia Beach Club | B67: Capri | C67: Beach Club | D67: 🏖️ | E67: Beach club associated with Hotel La Palma | F67: 9:00 AM - 7:00 PM | G67: Major advantage for hotel guests, sun loungers | H67: =HYPERLINK("https://www.google.com/maps/search/"&ENCODEURL(A67)) -> https://www.google.com/maps/search/Da%20Gioia%20Beach%20Club | I67: Via Mulo, 76, 80076 Capri NA, Italy | J67: Manus - https://manus.im/app/KJC6Ixn9ZFEgpriWR1GDzd | K67: 40.5453166, 14.2340931 | L67: 40.545317 | M67: 14.234093

Sheet YouTube
A1: Name | B1: Type | C1: Emoji | D1: Description | E1: City | F1: Address | G1: Hours | H1: Google Maps | I1: Special Notes | J1: Recommended By | K1: LatLong | L1: Latitude | M1: Longitude
A2: Da Luigi's | B2: Beach Club | C2: 🏖️ | D2: Thought to be really worth it2. This beach club is beautiful2. It's set amongst a giant rock2. It cost €100 to get in, but it came with a €60 credit2. The service here wasn't very good, but the food is good, and the location is very beautiful2. | E2: Capri | F2: Via dei Faraglioni, 5, 80073 Capri NA, Italy | H2: =HYPERLINK("https://www.google.com/maps/search/"&ENCODEURL(A2&", "&E2)) -> https://www.google.com/maps/search/Da%20Luigi%27s%2C%20Capri | J2: YouTube (Is The Amalfi Coast Worth It?) - https://www.youtube.com/watch?v=qEqWVNdIqKA&list=TLGGTjGW-qj9EhUxMDA2MjAyNQ | K2: 40.543128, 14.2525968 | L2: 40.543128 | M2: 14.252597
A3: Arienzo Beach Club | B3: Beach Club | C3: 🏖️ | D3: Spent $300 per person here, which was very expensive2. It was nice, but the speaker wouldn't really recommend it because there are really nice beach clubs for way less than this2. | E3: Positano | F3: Via Arienzo, 16, 84017 Positano SA, Italy | H3: =HYPERLINK("https://www.google.com/maps/search/"&ENCODEURL(A3&", "&E3)) -> https://www.google.com/maps/search/Arienzo%20Beach%20Club%2C%20Positano | J3: YouTube (Is The Amalfi Coast Worth It?) - https://www.youtube.com/watch?v=qEqWVNdIqKA&list=TLGGTjGW-qj9EhUxMDA2MjAyNQ | K3: 40.6247046, 14.500676 | L3: 40.624705 | M3: 14.500676
A4: Marina di Praia | B4: Beach Area | C4: 🏖️ | D4: A stunning little beach area in Praiano4. A great place to chill and swim8. It's down by the water, and using water taxis from here means you don't have to hike up to the road3. | E4: Praiano | F4: Marina di Praia, Via Praia, 84010 Praiano SA, Italy | H4: =HYPERLINK("https://www.google.com/maps/search/"&ENCODEURL(A4&", "&E4)) -> https://www.google.com/maps/search/Marina%20di%20Praia%2C%20Praiano | J4: YouTube (Is The Amalfi Coast Worth It?) - https://www.youtube.com/watch?v=qEqWVNdIqKA&list=TLGGTjGW-qj9EhUxMDA2MjAyNQ | K4: 40.6134729, 14.5394424 | L4: 40.613473 | M4: 14.539442
A5: Fiordo di Furore | B5: Beach / Fjord | C5: 🏖️ | D5: One of the coolest beaches1. Located in a little fjord complimented with an incredible arch bridge1. No car parking, best reached by bus or Vespa2. A paradise for cliff jumping2. Water felt good, swam under the bridge2. Honestly such an incredible spot2. | E5: Furore | F5: Via Marina di Praia, 84010 Furore SA, Italy | H5: =HYPERLINK("https://www.google.com/maps/search/"&ENCODEURL(A5&", "&E5)) -> https://www.google.com/maps/search/Fiordo%20di%20Furore%2C%20Furore | J5: YouTube (Top 10 Places on the Amalfi Coast) - https://www.youtube.com/watch?v=Mupom-sgjAU&list=TLGGuW2Fx0IJe4YxMDA2MjAyNQ | K5: 40.6141604, 14.5421669 | L5: 40.61416 | M5: 14.542167
A6: Path of the Gods (Sentiero degli Dei) | B6: Hiking Trail | C6: 🚶‍♀️ | D6: A super famous hike3. Starts in the town called Bomerano and ends in the village called Nocelle3. About 8 kilometers long and takes about 3 hours3. Incredible views basically the whole way3. Tons of ancient houses and hillside farms contrasted with coast views3. Basically all downhill3. Recommend doing it early to avoid the heat and crowds3. About halfway through you get a view of Positano4. Ends with over 1700 stairs to reach the main road in Arienzo4. | E6: Bomerano (start) to Nocelle (end) | F6: Sentiero degli Dei, Italy | G6: Recommended early | H6: =HYPERLINK("https://www.google.com/maps/search/"&ENCODEURL(A6&", "&E6)) -> https://www.google.com/maps/search/Path%20of%20the%20Gods%20%28Sentiero%20degli%20Dei%29%2C%20Bomerano%20%28start%29%20to%20Nocelle%20%28end%29 | J6: YouTube (Top 10 Places on the Amalfi Coast) - https://www.youtube.com/watch?v=Mupom-sgjAU&list=TLGGuW2Fx0IJe4YxMDA2MjAyNQ | K6: 40.6216598, 14.5208185 | L6: 40.62166 | M6: 14.520819
A7: Villa Rufolo | B7: Villa / Garden / Venue | C7: 🏛️ | D7: Located in Ravello9. A beautiful moorish style villa built during the 13th century10. Was one of the largest and most expensive villas10. Holds orchestra and opera concerts there with one of the most incredible views10. Cost a few euros to get in9. | E7: Ravello | F7: Piazza Duomo, 1, 84010 Ravello SA, Italy | H7: =HYPERLINK("https://www.google.com/maps/search/"&ENCODEURL(A7&", "&E7)) -> https://www.google.com/maps/search/Villa%20Rufolo%2C%20Ravello | J7: YouTube (Top 10 Places on the Amalfi Coast) - https://www.youtube.com/watch?v=Mupom-sgjAU&list=TLGGuW2Fx0IJe4YxMDA2MjAyNQ | K7: 40.6490843, 14.6113693 | L7: 40.649084 | M7: 14.611369
A8: Spiaggia di Praia | B8: Beach Area | C8: 🏖️ | D8: Down by the water in Praiano19. A stunning little beach area20. A great place to chill and swim1219. Using water taxis from here means you don't have to hike up to the road19. | E8: Praiano | F8: 84010 Praiano, SA, Italy | H8: =HYPERLINK("https://www.google.com/maps/search/"&ENCODEURL(A8&", "&E8)) -> https://www.google.com/maps/search/Spiaggia%20di%20Praia%2C%20Praiano | J8: YouTube (Top 10 Places on the Amalfi Coast) - https://www.youtube.com/watch?v=Mupom-sgjAU&list=TLGGuW2Fx0IJe4YxMDA2MjAyNQ | K8: 40.6117319, 14.5335099 | L8: 40.611732 | M8: 14.53351
A9: Faraglioni | B9: Rock Formations / Landmark | C9: 🪨 | D9: Incredible sea stacks that jut right out of the sea near Capri15. They were the main reason Ryan wanted to go to Capri15. Had a good time jumping off the boat there15. Was able to drive through the arch in one of them16. Looked so small from Monte Solaro17. | E9: Capri | F9: Faraglioni, Italy | G9: Accessible via boat during daylight hours | H9: =HYPERLINK("https://www.google.com/maps/search/"&ENCODEURL(A9&", "&E9)) -> https://www.google.com/maps/search/Faraglioni%2C%20Capri | J9: YouTube (Top 10 Places on the Amalfi Coast) - https://www.youtube.com/watch?v=Mupom-sgjAU&list=TLGGuW2Fx0IJe4YxMDA2MjAyNQ | K9: 40.540163, 14.2528574 | L9: 40.540163 | M9: 14.252857
A10: Grotta Bianca | B10: Grotto / Sea Cave | C10: 🌊 | D10: Sea cave/grotto near the eastern part of the island16. Anchored near here and had a great time swimming in the crystal clear Mediterranean waters16. | E10: Capri | F10: 80073 Capri, Metropolitan City of Naples, Italy | G10: Accessible via boat during daylight hours | H10: =HYPERLINK("https://www.google.com/maps/search/"&ENCODEURL(A10&", "&E10)) -> https://www.google.com/maps/search/Grotta%20Bianca%2C%20Capri | J10: YouTube (Top 10 Places on the Amalfi Coast) - https://www.youtube.com/watch?v=Mupom-sgjAU&list=TLGGuW2Fx0IJe4YxMDA2MjAyNQ | K10: 40.551155, 14.2479425 | L10: 40.551155 | M10: 14.247943
A11: Monte Solaro | B11: Mountain / Viewpoint | C11: 🚠 | D11: The highest point on the island of Capri with an elevation of 589 meters17. To get to the top you can take a chair lift for about 10 euros a person17. The views were absolutely incredible, especially nearing sunset17. You get astounding views of the whole island17. The Faraglioni looked so small from up there17. | E11: Anacapri | F11: Monte Solaro, 80071 Anacapri, Metropolitan City of Naples, Italy | H11: =HYPERLINK("https://www.google.com/maps/search/"&ENCODEURL(A11&", "&E11)) -> https://www.google.com/maps/search/Monte%20Solaro%2C%20Anacapri | J11: YouTube (Top 10 Places on the Amalfi Coast) - https://www.youtube.com/watch?v=Mupom-sgjAU&list=TLGGuW2Fx0IJe4YxMDA2MjAyNQ | K11: 40.5449719, 14.2229833 | L11: 40.544972 | M11: 14.222983

Sheet Manus All Chiaia
A1: Name | B1: Region | C1: Type | D1: Emoji | E1: Description | F1: Special Notes | G1: Hours | H1: Cost Range (USD for 2) | I1: Address | J1: Latitude | K1: Longitude
A2: Palazzo Alabardieri | B2: Chiaia | C2: Hotel | D2: 🏨 | E2: Historic converted cloister with elegant rooms, each featuring unique color themes. 2-minute walk from Via Chiaia shops. | F2: Multilingual staff, excellent breakfast included. Request room with seating area for romantic aperitivos. | G2: 24/7 check-in | H2: $250-400/night | I2: Via Alabardieri 38, 80121 Naples | J2: 40.837 | K2: 14.2468
A3: Hotel Poerio 25 Boutique Stay | B3: Chiaia | C3: Hotel | D3: 🏨 | E3: Sleek boutique property with contemporary design, feels like stylish friend's apartment. 10-min walk to beach. | F3: Personalized service, modern amenities | G3: 24/7 check-in | H3: $189-250/night | I3: Via Poerio 25, 80121 Naples | J3: 40.8355 | K3: 14.2445
A4: Prestige Rooms Chiaia | B4: Chiaia | C4: Hotel | D4: 🏨 | E4: Local favorite with exceptional value, beloved by locals and savvy travelers. Great location in Chiaia district. | F4: 10-minute walk from Mappatella Beach, excellent reviews | G4: 24/7 check-in | H4: $178-220/night | I4: Via Chiaia, Naples | J4: 40.838 | K4: 14.247
A5: Il Salotto della Regina | B5: Chiaia | C5: Hotel | D5: 🏨 | E5: Charming accommodation with shared lounge and bar, extremely kind staff. Close to Via Chiaia. | F5: Excellent location, very helpful staff | G5: 24/7 check-in | H5: $200-280/night | I5: Via Chiaia area, Naples | J5: 40.838 | K5: 14.247
A6: Grand Hotel Parker's | B6: Chiaia | C6: Hotel | D6: 🏨 | E6: Luxury 5-star hotel with amazing Gulf of Naples views. Houses Michelin-starred restaurant and rooftop bar. | F6: Extremely luxurious, above budget but worth noting for special occasions | G6: 24/7 check-in | H6: $635+/night | I6: Corso Vittorio Emanuele 135, 80121 Naples | J6: 40.8395 | K6: 14.2485
A7: Caruso Roof Garden | B7: Chiaia | C7: Restaurant (Dinner) | D7: 🍽️ | E7: Most romantic dining spot in Naples with unspoiled Mount Vesuvius views and refined atmosphere. | F7: 2 Michelin stars, refined neutral furnishings, soft lighting. Request window table when booking. | G7: Mon-Fri 19:30-22:00, Sat-Sun 13:00-15:00 & 19:30-22:00 | H7: $200-300 | I7: Via Partenope 45, Grand Hotel Vesuvio, 80121 Naples | J7: 40.832 | K7: 14.252
A8: A Fenestella | B8: Chiaia | C8: Restaurant (Lunch/Dinner) | D8: 🍽️ | E8: Sunset specialist with crisp white furnishings and incredible bay views. Perfect for romantic dinners. | F8: Sardinian-style lobster specialty, incredible sunset views | G8: Mon & Wed-Sun 12:00-16:00 & 19:00-00:00, Closed Tue | H8: $120-180 | I8: Calata Ponticello a Santa Lucia 1E, 80132 Naples | J8: 40.8315 | K8: 14.2515
A9: La Cantinella | B9: Chiaia | C9: Restaurant (Lunch/Dinner) | D9: 🍽️ | E9: Unique Italian tiki bar atmosphere with bamboo walls and Mount Vesuvius views. Seafood focus. | F9: Bamboo walls create unique atmosphere, outdoor tables for best views | G9: Mon-Sat 12:30-15:30 & 19:30-23:30, Sun 12:30-15:30 | H9: $100-150 | I9: Via Cuma 42, 80132 Naples | J9: 40.8325 | K9: 14.2525
A10: Palazzo Petrucci | B10: Chiaia | C10: Restaurant (Dinner) | D10: 🍽️ | E10: Michelin Guide-worthy fine dining with elegant decor and seafront views. Innovative Neapolitan cuisine. | F10: Full-length windows, request window spot for undisturbed vistas | G10: Mon-Thu 19:00-22:30, Fri-Sun 12:30-15:00 & 19:00-22:30 | H10: $180-250 | I10: Piazza San Domenico Maggiore 4, 80134 Naples | J10: 40.847 | K10: 14.255
A11: Transatlantico Ristorante Suite | B11: Chiaia | C11: Restaurant (Lunch/Dinner) | D11: 🍽️ | E11: Vibrant waterfront restaurant along lively marina with great views and energetic atmosphere. | F11: Mix of regional cuisines, vibrant atmosphere with views | G11: Varies | H11: $100-140 | I11: Via Luculliana 15, 80132 Naples | J11: 40.831 | K11: 14.251
A12: Osteria della Mattonella | B12: Naples Historic Center | C12: Restaurant (Dinner) | D12: 🍝 | E12: Classic traditional restaurant from films, extremely authentic with best pasta alla Genovese in Naples. | F12: Started as wine/olive oil shop in 1978, very busy after 8pm, difficult to get table | G12: Varies | H12: $60-90 | I12: Via Giovanni Nicotera 13, 80132 Naples | J12: 40.833 | K12: 14.253
A13: Pizzeria Brandi | B13: Chiaia | C13: Restaurant (Lunch/Dinner) | D13: 🍕 | E13: Historic pizzeria and birthplace of Pizza Margherita, created for Queen Margherita in 1889. | F13: Uses finest San Marzano tomatoes, original Pizza Margherita recipe | G13: Varies | H13: $40-60 | I13: Salita Sant'Anna di Palazzo 1/2, 80132 Naples | J13: 40.834 | K13: 14.248
... A70: Bancarelle di San Pasquale | B70: Chiaia | C70: Market | D70: 🛒 | E70: Local market stalls | F70: Discovering local products and souvenirs | G70: Varies | H70: $5-50 | I70: Piazza San Pasquale a Chiaia, 80121 Naples | J70: 40.8375 | K70: 14.2465

Sheet Manus Chiaia
A1: Name | B1: Type | C1: Emoji | D1: Description | E1: Special Notes | F1: Hours | G1: Cost Range (USD for 2) | H1: Address | I1: LatLong | J1: Latitude | K1: Longitude | L1: Google Maps | M1: Recommended By
A2: Palazzo Alabardieri | B2: Hotel | C2: 🏨 | D2: Historic converted cloister with elegant rooms, each featuring unique color themes. 2-minute walk from Via Chiaia shops. | E2: Multilingual staff, excellent breakfast included. Request room with seating area for romantic aperitivos. | F2: 24/7 check-in | G2: $250-400/night | H2: =VLOOKUP(A2,'Manus All Chiaia'!$A$1:$I$70,9,0)&", Italy" -> Via Alabardieri 38, 80121 Naples, Italy | I2: =IFERROR(__xludf.DUMMYFUNCTION("JOIN("", "",J2,K2)"),"40.837, 14.2468") -> 40.837, 14.2468 | J2: =VLOOKUP($A2,'Manus All Chiaia'!$A$1:$K$70,10,0) -> 40.837 | K2: =VLOOKUP($A2,'Manus All Chiaia'!$A$1:$K$70,11,0) -> 14.2468 | L2: =HYPERLINK("https://www.google.com/maps/search/"&ENCODEURL(A2&", Naples")) -> https://www.google.com/maps/search/Palazzo%20Alabardieri%2C%20Naples | M2: Manus (Chiaia) - https://chatgpt.com/c/6846f0da-7884-8009-ad13-dba01dfa021d
A3: Hotel Poerio 25 Boutique Stay | B3: Hotel | C3: 🏨 | D3: Sleek boutique property with contemporary design, feels like stylish friend's apartment. 10-min walk to beach. | E3: Personalized service, modern amenities | F3: 24/7 check-in | G3: $189-250/night | H3: =VLOOKUP(A3,'Manus All Chiaia'!$A$1:$I$70,9,0)&", Italy" -> Via Poerio 25, 80121 Naples, Italy | I3: =IFERROR(__xludf.DUMMYFUNCTION("JOIN("", "",J3,K3)"),"40.8355, 14.2445") -> 40.8355, 14.2445 | J3: =VLOOKUP($A3,'Manus All Chiaia'!$A$1:$K$70,10,0) -> 40.8355 | K3: =VLOOKUP($A3,'Manus All Chiaia'!$A$1:$K$70,11,0) -> 14.2445 | L3: =HYPERLINK("https://www.google.com/maps/search/"&ENCODEURL(A3&", Naples")) -> https://www.google.com/maps/search/Hotel%20Poerio%2025%20Boutique%20Stay%2C%20Naples | M3: Manus (Chiaia) - https://chatgpt.com/c/6846f0da-7884-8009-ad13-dba01dfa021d
A4: Prestige Rooms Chiaia | B4: Hotel | C4: 🏨 | D4: Local favorite with exceptional value, beloved by locals and savvy travelers. Great location in Chiaia district. | E4: 10-minute walk from Mappatella Beach, excellent reviews | F4: 24/7 check-in | G4: $178-220/night | H4: =VLOOKUP(A4,'Manus All Chiaia'!$A$1:$I$70,9,0)&", Italy" -> Via Chiaia, Naples, Italy | I4: =IFERROR(__xludf.DUMMYFUNCTION("JOIN("", "",J4,K4)"),"40.838, 14.247") -> 40.838, 14.247 | J4: =VLOOKUP($A4,'Manus All Chiaia'!$A$1:$K$70,10,0) -> 40.838 | K4: =VLOOKUP($A4,'Manus All Chiaia'!$A$1:$K$70,11,0) -> 14.247 | L4: =HYPERLINK("https://www.google.com/maps/search/"&ENCODEURL(A4&", Naples")) -> https://www.google.com/maps/search/Prestige%20Rooms%20Chiaia%2C%20Naples | M4: Manus (Chiaia) - https://chatgpt.com/c/6846f0da-7884-8009-ad13-dba01dfa021d
A5: Il Salotto della Regina | B5: Hotel | C5: 🏨 | D5: Charming accommodation with shared lounge and bar, extremely kind staff. Close to Via Chiaia. | E5: Excellent location, very helpful staff | F5: 24/7 check-in | G5: $200-280/night | H5: =VLOOKUP(A5,'Manus All Chiaia'!$A$1:$I$70,9,0)&", Italy" -> Via Chiaia area, Naples, Italy | I5: =IFERROR(__xludf.DUMMYFUNCTION("JOIN("", "",J5,K5)"),"40.838, 14.247") -> 40.838, 14.247 | J5: =VLOOKUP($A5,'Manus All Chiaia'!$A$1:$K$70,10,0) -> 40.838 | K5: =VLOOKUP($A5,'Manus All Chiaia'!$A$1:$K$70,11,0) -> 14.247 | L5: =HYPERLINK("https://www.google.com/maps/search/"&ENCODEURL(A5&", Naples")) -> https://www.google.com/maps/search/Il%20Salotto%20della%20Regina%2C%20Naples | M5: Manus (Chiaia) - https://chatgpt.com/c/6846f0da-7884-8009-ad13-dba01dfa021d
A6: Grand Hotel Parker's | B6: Hotel | C6: 🏨 | D6: Luxury 5-star hotel with amazing Gulf of Naples views. Houses Michelin-starred restaurant and rooftop bar. | E6: Extremely luxurious, above budget but worth noting for special occasions | F6: 24/7 check-in | G6: $635+/night | H6: =VLOOKUP(A6,'Manus All Chiaia'!$A$1:$I$70,9,0)&", Italy" -> Corso Vittorio Emanuele 135, 80121 Naples, Italy | I6: =IFERROR(__xludf.DUMMYFUNCTION("JOIN("", "",J6,K6)"),"40.8395, 14.2485") -> 40.8395, 14.2485 | J6: =VLOOKUP($A6,'Manus All Chiaia'!$A$1:$K$70,10,0) -> 40.8395 | K6: =VLOOKUP($A6,'Manus All Chiaia'!$A$1:$K$70,11,0) -> 14.2485 | L6: =HYPERLINK("https://www.google.com/maps/search/"&ENCODEURL(A6&", Naples")) -> https://www.google.com/maps/search/Grand%20Hotel%20Parker%27s%2C%20Naples | M6: Manus (Chiaia) - https://chatgpt.com/c/6846f0da-7884-8009-ad13-dba01dfa021d
A7: Caruso Roof Garden | B7: Restaurant (Dinner) | C7: 🍽️ | D7: Most romantic dining spot in Naples with unspoiled Mount Vesuvius views and refined atmosphere. | E7: 2 Michelin stars, refined neutral furnishings, soft lighting. Request window table when booking. | F7: Mon-Fri 19:30-22:00, Sat-Sun 13:00-15:00 & 19:30-22:00 | G7: $200-300 | H7: =VLOOKUP(A7,'Manus All Chiaia'!$A$1:$I$70,9,0)&", Italy" -> Via Partenope 45, Grand Hotel Vesuvio, 80121 Naples, Italy | I7: =IFERROR(__xludf.DUMMYFUNCTION("JOIN("", "",J7,K7)"),"40.832, 14.252") -> 40.832, 14.252 | J7: =VLOOKUP($A7,'Manus All Chiaia'!$A$1:$K$70,10,0) -> 40.832 | K7: =VLOOKUP($A7,'Manus All Chiaia'!$A$1:$K$70,11,0) -> 14.252 | L7: =HYPERLINK("https://www.google.com/maps/search/"&ENCODEURL(A7&", Naples")) -> https://www.google.com/maps/search/Caruso%20Roof%20Garden%2C%20Naples | M7: Manus (Chiaia) - https://chatgpt.com/c/6846f0da-7884-8009-ad13-dba01dfa021d
A8: A Fenestella | B8: Restaurant (Lunch/Dinner) | C8: 🍽️ | D8: Sunset specialist with crisp white furnishings and incredible bay views. Perfect for romantic dinners. | E8: Sardinian-style lobster specialty, incredible sunset views | F8: Mon & Wed-Sun 12:00-16:00 & 19:00-00:00, Closed Tue | G8: $120-180 | H8: =VLOOKUP(A8,'Manus All Chiaia'!$A$1:$I$70,9,0)&", Italy" -> Calata Ponticello a Santa Lucia 1E, 80132 Naples, Italy | I8: =IFERROR(__xludf.DUMMYFUNCTION("JOIN("", "",J8,K8)"),"40.8315, 14.2515") -> 40.8315, 14.2515 | J8: =VLOOKUP($A8,'Manus All Chiaia'!$A$1:$K$70,10,0) -> 40.8315 | K8: =VLOOKUP($A8,'Manus All Chiaia'!$A$1:$K$70,11,0) -> 14.2515 | L8: =HYPERLINK("https://www.google.com/maps/search/"&ENCODEURL(A8&", Naples")) -> https://www.google.com/maps/search/A%20Fenestella%2C%20Naples | M8: Manus (Chiaia) - https://chatgpt.com/c/6846f0da-7884-8009-ad13-dba01dfa021d
A9: La Cantinella | B9: Restaurant (Lunch/Dinner) | C9: 🍽️ | D9: Unique Italian tiki bar atmosphere with bamboo walls and Mount Vesuvius views. Seafood focus. | E9: Bamboo walls create unique atmosphere, outdoor tables for best views | F9: Mon-Sat 12:30-15:30 & 19:30-23:30, Sun 12:30-15:30 | G9: $100-150 | H9: =VLOOKUP(A9,'Manus All Chiaia'!$A$1:$I$70,9,0)&", Italy" -> Via Cuma 42, 80132 Naples, Italy | I9: =IFERROR(__xludf.DUMMYFUNCTION("JOIN("", "",J9,K9)"),"40.8325, 14.2525") -> 40.8325, 14.2525 | J9: =VLOOKUP($A9,'Manus All Chiaia'!$A$1:$K$70,10,0) -> 40.8325 | K9: =VLOOKUP($A9,'Manus All Chiaia'!$A$1:$K$70,11,0) -> 14.2525 | L9: =HYPERLINK("https://www.google.com/maps/search/"&ENCODEURL(A9&", Naples")) -> https://www.google.com/maps/search/La%20Cantinella%2C%20Naples | M9: Manus (Chiaia) - https://chatgpt.com/c/6846f0da-7884-8009-ad13-dba01dfa021d
A10: Palazzo Petrucci | B10: Restaurant (Dinner) | C10: 🍽️ | D10: Michelin Guide-worthy fine dining with elegant decor and seafront views. Innovative Neapolitan cuisine. | E10: Full-length windows, request window spot for undisturbed vistas | F10: Mon-Thu 19:00-22:30, Fri-Sun 12:30-15:00 & 19:00-22:30 | G10: $180-250 | H10: =VLOOKUP(A10,'Manus All Chiaia'!$A$1:$I$70,9,0)&", Italy" -> Piazza San Domenico Maggiore 4, 80134 Naples, Italy | I10: =IFERROR(__xludf.DUMMYFUNCTION("JOIN("", "",J10,K10)"),"40.847, 14.255") -> 40.847, 14.255 | J10: =VLOOKUP($A10,'Manus All Chiaia'!$A$1:$K$70,10,0) -> 40.847 | K10: =VLOOKUP($A10,'Manus All Chiaia'!$A$1:$K$70,11,0) -> 14.255 | L10: =HYPERLINK("https://www.google.com/maps/search/"&ENCODEURL(A10&", Naples")) -> https://www.google.com/maps/search/Palazzo%20Petrucci%2C%20Naples | M10: Manus (Chiaia) - https://chatgpt.com/c/6846f0da-7884-8009-ad13-dba01dfa021d
A11: Transatlantico Ristorante Suite | B11: Restaurant (Lunch/Dinner) | C11: 🍽️ | D11: Vibrant waterfront restaurant along lively marina with great views and energetic atmosphere. | E11: Mix of regional cuisines, vibrant atmosphere with views | F11: Varies | G11: $100-140 | H11: =VLOOKUP(A11,'Manus All Chiaia'!$A$1:$I$70,9,0)&", Italy" -> Via Luculliana 15, 80132 Naples, Italy | I11: =IFERROR(__xludf.DUMMYFUNCTION("JOIN("", "",J11,K11)"),"40.831, 14.251") -> 40.831, 14.251 | J11: =VLOOKUP($A11,'Manus All Chiaia'!$A$1:$K$70,10,0) -> 40.831 | K11: =VLOOKUP($A11,'Manus All Chiaia'!$A$1:$K$70,11,0) -> 14.251 | L11: =HYPERLINK("https://www.google.com/maps/search/"&ENCODEURL(A11&", Naples")) -> https://www.google.com/maps/search/Transatlantico%20Ristorante%20Suite%2C%20Naples | M11: Manus (Chiaia) - https://chatgpt.com/c/6846f0da-7884-8009-ad13-dba01dfa021d
A12: Osteria della Mattonella | B12: Restaurant (Dinner) | C12: 🍝 | D12: Classic traditional restaurant from films, extremely authentic with best pasta alla Genovese in Naples. | E12: Started as wine/olive oil shop in 1978, very busy after 8pm, difficult to get table | F12: Varies | G12: $60-90 | H12: =VLOOKUP(A12,'Manus All Chiaia'!$A$1:$I$70,9,0)&", Italy" -> Via Giovanni Nicotera 13, 80132 Naples, Italy | I12: =IFERROR(__xludf.DUMMYFUNCTION("JOIN("", "",J12,K12)"),"40.833, 14.253") -> 40.833, 14.253 | J12: =VLOOKUP($A12,'Manus All Chiaia'!$A$1:$K$70,10,0) -> 40.833 | K12: =VLOOKUP($A12,'Manus All Chiaia'!$A$1:$K$70,11,0) -> 14.253 | L12: =HYPERLINK("https://www.google.com/maps/search/"&ENCODEURL(A12&", Naples")) -> https://www.google.com/maps/search/Osteria%20della%20Mattonella%2C%20Naples | M12: Manus (Chiaia) - https://chatgpt.com/c/6846f0da-7884-8009-ad13-dba01dfa021d
A13: Pizzeria Brandi | B13: Restaurant (Lunch/Dinner) | C13: 🍕 | D13: Historic pizzeria and birthplace of Pizza Margherita, created for Queen Margherita in 1889. | E13: Uses finest San Marzano tomatoes, original Pizza Margherita recipe | F13: Varies | G13: $40-60 | H13: =VLOOKUP(A13,'Manus All Chiaia'!$A$1:$I$70,9,0)&", Italy" -> Salita Sant'Anna di Palazzo 1/2, 80132 Naples, Italy | I13: =IFERROR(__xludf.DUMMYFUNCTION("JOIN("", "",J13,K13)"),"40.834, 14.248") -> 40.834, 14.248 | J13: =VLOOKUP($A13,'Manus All Chiaia'!$A$1:$K$70,10,0) -> 40.834 | K13: =VLOOKUP($A13,'Manus All Chiaia'!$A$1:$K$70,11,0) -> 14.248 | L13: =HYPERLINK("https://www.google.com/maps/search/"&ENCODEURL(A13&", Naples")) -> https://www.google.com/maps/search/Pizzeria%20Brandi%2C%20Naples | M13: Manus (Chiaia) - https://chatgpt.com/c/6846f0da-7884-8009-ad13-dba01dfa021d
A14: George Restaurant | B14: Restaurant (Dinner) | C14: ⭐ | D14: First 2 Michelin stars restaurant in Naples offering '360° unforgettable sensorial experience'. | E14: 2 Michelin stars 2024, fine dining, dress code likely required | F14: Mon-Fri 19:30-22:00, Sat-Sun 13:00-15:00 & 19:30-22:00 | G14: $300-400 | H14: =VLOOKUP(A14,'Manus All Chiaia'!$A$1:$I$70,9,0)&", Italy" -> Corso Vittorio Emanuele 135, Grand Hotel Parker's, 80121 Naples, Italy | I14: =IFERROR(__xludf.DUMMYFUNCTION("JOIN("", "",J14,K14)"),"40.8395, 14.2485") -> 40.8395, 14.2485 | J14: =VLOOKUP($A14,'Manus All Chiaia'!$A$1:$K$70,10,0) -> 40.8395 | K14: =VLOOKUP($A14,'Manus All Chiaia'!$A$1:$K$70,11,0) -> 14.2485 | L14: =HYPERLINK("https://www.google.com/maps/search/"&ENCODEURL(A14&", Naples")) -> https://www.google.com/maps/search/George%20Restaurant%2C%20Naples | M14: Manus (Chiaia) - https://chatgpt.com/c/6846f0da-7884-8009-ad13-dba01dfa021d
A15: Bidder Terrace | B15: Rooftop Bar | C15: 🍹 | D15: Relaxing rooftop cocktail terrace with mixology cocktails and Neapolitan street food. Amazing city views. | E15: Part of Grand Hotel Parker's, views over Gulf of Naples, Vesuvius, Capri | F15: Mon-Fri 19:30-22:00, Sat-Sun 13:00-15:00 & 19:30-22:00 | G15: $80-120 | H15: =VLOOKUP(A15,'Manus All Chiaia'!$A$1:$I$70,9,0)&", Italy" -> Corso Vittorio Emanuele 135, Grand Hotel Parker's, 80121 Naples, Italy | I15: =IFERROR(__xludf.DUMMYFUNCTION("JOIN("", "",J15,K15)"),"40.8395, 14.2485") -> 40.8395, 14.2485 | J15: =VLOOKUP($A15,'Manus All Chiaia'!$A$1:$K$70,10,0) -> 40.8395 | K15: =VLOOKUP($A15,'Manus All Chiaia'!$A$1:$K$70,11,0) -> 14.2485 | L15: =HYPERLINK("https://www.google.com/maps/search/"&ENCODEURL(A15&", Naples")) -> https://www.google.com/maps/search/Bidder%20Terrace%2C%20Naples | M15: Manus (Chiaia) - https://chatgpt.com/c/6846f0da-7884-8009-ad13-dba01dfa021d
A16: Riserva Rooftop | B16: Rooftop Bar | C16: 🍹 | D16: Elegant rooftop on Posillipo Hill with luxury Italian restaurant and international cocktail bar. | E16: Elevated position, amazing Naples and ocean views, haute cuisine available | F16: Varies | G16: $100-150 | H16: =VLOOKUP(A16,'Manus All Chiaia'!$A$1:$I$70,9,0)&", Italy" -> Via Orazio 10, 80123 Naples, Italy | I16: =IFERROR(__xludf.DUMMYFUNCTION("JOIN("", "",J16,K16)"),"40.815, 14.218") -> 40.815, 14.218 | J16: =VLOOKUP($A16,'Manus All Chiaia'!$A$1:$K$70,10,0) -> 40.815 | K16: =VLOOKUP($A16,'Manus All Chiaia'!$A$1:$K$70,11,0) -> 14.218 | L16: =HYPERLINK("https://www.google.com/maps/search/"&ENCODEURL(A16&", Naples")) -> https://www.google.com/maps/search/Riserva%20Rooftop%2C%20Naples | M16: Manus (Chiaia) - https://chatgpt.com/c/6846f0da-7884-8009-ad13-dba01dfa021d
A17: Romeo Hotel Naples | B17: Rooftop Bar | C17: 🍹 | D17: Chic rooftop experience with pool access and perfect location by Port of Naples. | E17: Michelin star restaurant, rooftop pool, port views | F17: Varies | G17: $80-120 | H17: =VLOOKUP(A17,'Manus All Chiaia'!$A$1:$I$70,9,0)&", Italy" -> Via Cristoforo Colombo 45, 80133 Naples, Italy | I17: =IFERROR(__xludf.DUMMYFUNCTION("JOIN("", "",J17,K17)"),"40.838, 14.268") -> 40.838, 14.268 | J17: =VLOOKUP($A17,'Manus All Chiaia'!$A$1:$K$70,10,0) -> 40.838 | K17: =VLOOKUP($A17,'Manus All Chiaia'!$A$1:$K$70,11,0) -> 14.268 | L17: =HYPERLINK("https://www.google.com/maps/search/"&ENCODEURL(A17&", Naples")) -> https://www.google.com/maps/search/Romeo%20Hotel%20Naples%2C%20Naples | M17: Manus (Chiaia) - https://chatgpt.com/c/6846f0da-7884-8009-ad13-dba01dfa021d
A18: L'Antiquario | B18: Speakeasy | C18: 🚪 | D18: Secret underground speakeasy accessed through antique store door with retro American atmosphere. | E18: Secret door entrance, retro speakeasy feel, book online ahead of time | F18: Varies | G18: $60-100 | H18: =VLOOKUP(A18,'Manus All Chiaia'!$A$1:$I$70,9,0)&", Italy" -> Via Vannella Gaetani 2, 80121 Naples, Italy | I18: =IFERROR(__xludf.DUMMYFUNCTION("JOIN("", "",J18,K18)"),"40.8365, 14.2455") -> 40.8365, 14.2455 | J18: =VLOOKUP($A18,'Manus All Chiaia'!$A$1:$K$70,10,0) -> 40.8365 | K18: =VLOOKUP($A18,'Manus All Chiaia'!$A$1:$K$70,11,0) -> 14.2455 | L18: =HYPERLINK("https://www.google.com/maps/search/"&ENCODEURL(A18&", Naples")) -> https://www.google.com/maps/search/L%27Antiquario%2C%20Naples | M18: Manus (Chiaia) - https://chatgpt.com/c/6846f0da-7884-8009-ad13-dba01dfa021d
A19: Barril Garden Bar | B19: Cocktail Bar | C19: 🍹 | D19: Key bar in famous Chiaia nightlife district with sophisticated cocktail scene. | E19: Part of "i barretti di Chiaia" area, chic atmosphere | F19: Varies | G19: $50-80 | H19: =VLOOKUP(A19,'Manus All Chiaia'!$A$1:$I$70,9,0)&", Italy" -> Via Giuseppe Fiorelli 11, 80121 Naples, Italy | I19: =IFERROR(__xludf.DUMMYFUNCTION("JOIN("", "",J19,K19)"),"40.8375, 14.2465") -> 40.8375, 14.2465 | J19: =VLOOKUP($A19,'Manus All Chiaia'!$A$1:$K$70,10,0) -> 40.8375 | K19: =VLOOKUP($A19,'Manus All Chiaia'!$A$1:$K$70,11,0) -> 14.2465 | L19: =HYPERLINK("https://www.google.com/maps/search/"&ENCODEURL(A19&", Naples")) -> https://www.google.com/maps/search/Barril%20Garden%20Bar%2C%20Naples | M19: Manus (Chiaia) - https://chatgpt.com/c/6846f0da-7884-8009-ad13-dba01dfa021d
A20: Ba-Bar | B20: Cocktail Bar | C20: 🍹 | D20: Sophisticated cocktail bar in the heart of Chiaia's famous bar district. | E20: Located in Via Bisignano, part of local nightlife scene | F20: Varies | G20: $50-80 | H20: =VLOOKUP(A20,'Manus All Chiaia'!$A$1:$I$70,9,0)&", Italy" -> Via Bisignano 20, 80121 Naples, Italy | I20: =IFERROR(__xludf.DUMMYFUNCTION("JOIN("", "",J20,K20)"),"40.837, 14.246") -> 40.837, 14.246 | J20: =VLOOKUP($A20,'Manus All Chiaia'!$A$1:$K$70,10,0) -> 40.837 | K20: =VLOOKUP($A20,'Manus All Chiaia'!$A$1:$K$70,11,0) -> 14.246 | L20: =HYPERLINK("https://www.google.com/maps/search/"&ENCODEURL(A20&", Naples")) -> https://www.google.com/maps/search/Ba-Bar%2C%20Naples | M20: Manus (Chiaia) - https://chatgpt.com/c/6846f0da-7884-8009-ad13-dba01dfa021d
A21: Swig Chiaia | B21: Cocktail Bar | C21: 🍸 | D21: Naples' top cocktail bar known for creative drinks and vibrant nightlife atmosphere. | E21: Creative drinks, vibrant atmosphere, perfect for tourists | F21: Varies | G21: $60-90 | H21: =VLOOKUP(A21,'Manus All Chiaia'!$A$1:$I$70,9,0)&", Italy" -> Via Giuseppe Martucci 30, 80121 Naples, Italy | I21: =IFERROR(__xludf.DUMMYFUNCTION("JOIN("", "",J21,K21)"),"40.8385, 14.2475") -> 40.8385, 14.2475 | J21: =VLOOKUP($A21,'Manus All Chiaia'!$A$1:$K$70,10,0) -> 40.8385 | K21: =VLOOKUP($A21,'Manus All Chiaia'!$A$1:$K$70,11,0) -> 14.2475 | L21: =HYPERLINK("https://www.google.com/maps/search/"&ENCODEURL(A21&", Naples")) -> https://www.google.com/maps/search/Swig%20Chiaia%2C%20Naples | M21: Manus (Chiaia) - https://chatgpt.com/c/6846f0da-7884-8009-ad13-dba01dfa021d
A22: Twins - Cocktail Wine Coffee | B22: Cocktail Bar | C22: ☕ | D22: Multi-concept venue offering cocktails, wine, and coffee throughout the day. | E22: Versatile venue for different times of day | F22: Varies | G22: $40-70 | H22: =VLOOKUP(A22,'Manus All Chiaia'!$A$1:$I$70,9,0)&", Italy" -> Via Chiaia area, Naples, Italy | I22: =IFERROR(__xludf.DUMMYFUNCTION("JOIN("", "",J22,K22)"),"40.838, 14.247") -> 40.838, 14.247 | J22: =VLOOKUP($A22,'Manus All Chiaia'!$A$1:$K$70,10,0) -> 40.838 | K22: =VLOOKUP($A22,'Manus All Chiaia'!$A$1:$K$70,11,0) -> 14.247 | L22: =HYPERLINK("https://www.google.com/maps/search/"&ENCODEURL(A22&", Naples")) -> https://www.google.com/maps/search/Twins%20-%20Cocktail%20Wine%20Coffee%2C%20Naples | M22: Manus (Chiaia) - https://chatgpt.com/c/6846f0da-7884-8009-ad13-dba01dfa021d
A23: Enoteca Belledonne | B23: Wine Bar | C23: 🍷 | D23: Fodor's Choice wine bar in the heart of Chiaia district. | E23: Fodor's Choice rating, intimate wine experience | F23: Varies | G23: $50-80 | H23: =VLOOKUP(A23,'Manus All Chiaia'!$A$1:$I$70,9,0)&", Italy" -> Vico Belledonne a Chiaia 18, 80121 Naples, Italy | I23: =IFERROR(__xludf.DUMMYFUNCTION("JOIN("", "",J23,K23)"),"40.8372, 14.2462") -> 40.8372, 14.2462 | J23: =VLOOKUP($A23,'Manus All Chiaia'!$A$1:$K$70,10,0) -> 40.8372 | K23: =VLOOKUP($A23,'Manus All Chiaia'!$A$1:$K$70,11,0) -> 14.2462 | L23: =HYPERLINK("https://www.google.com/maps/search/"&ENCODEURL(A23&", Naples")) -> https://www.google.com/maps/search/Enoteca%20Belledonne%2C%20Naples | M23: Manus (Chiaia) - https://chatgpt.com/c/6846f0da-7884-8009-ad13-dba01dfa021d
A24: Chandelier | B24: Cocktail Bar | C24: 🍸 | D24: Hip bar with cool drinks and free appetizers if arriving early. Opens at aperitivo time. | E24: Free appetizers if you come early, hip atmosphere | F24: Opens 18:30 | G24: $40-60 | H24: =VLOOKUP(A24,'Manus All Chiaia'!$A$1:$I$70,9,0)&", Italy" -> Vico Belledonne a Chiaia 34-35, 80121 Naples, Italy | I24: =IFERROR(__xludf.DUMMYFUNCTION("JOIN("", "",J24,K24)"),"40.8372, 14.2462") -> 40.8372, 14.2462 | J24: =VLOOKUP($A24,'Manus All Chiaia'!$A$1:$K$70,10,0) -> 40.8372 | K24: =VLOOKUP($A24,'Manus All Chiaia'!$A$1:$K$70,11,0) -> 14.2462 | L24: =HYPERLINK("https://www.google.com/maps/search/"&ENCODEURL(A24&", Naples")) -> https://www.google.com/maps/search/Chandelier%2C%20Naples | M24: Manus (Chiaia) - https://chatgpt.com/c/6846f0da-7884-8009-ad13-dba01dfa021d
A25: Bluestone | B25: Bar | C25: 🥃 | D25: Casual bar in upscale Chiaia area for relaxed drinks. | E25: Located on Via Alabardieri, casual atmosphere | F25: Varies | G25: $40-60 | H25: =VLOOKUP(A25,'Manus All Chiaia'!$A$1:$I$70,9,0)&", Italy" -> Via Alabardieri 10, 80121 Naples, Italy | I25: =IFERROR(__xludf.DUMMYFUNCTION("JOIN("", "",J25,K25)"),"40.837, 14.2468") -> 40.837, 14.2468 | J25: =VLOOKUP($A25,'Manus All Chiaia'!$A$1:$K$70,10,0) -> 40.837 | K25: =VLOOKUP($A25,'Manus All Chiaia'!$A$1:$K$70,11,0) -> 14.2468 | L25: =HYPERLINK("https://www.google.com/maps/search/"&ENCODEURL(A25&", Naples")) -> https://www.google.com/maps/search/Bluestone%2C%20Naples | M25: Manus (Chiaia) - https://chatgpt.com/c/6846f0da-7884-8009-ad13-dba01dfa021d
A26: Cap'Alice | B26: Wine Bar | C26: 🍷 | D26: High-quality wines from Campania and Sicily with Rock&Wine nights featuring live music. | E26: Freshly baked bread, fried fish cornetti, live music nights | F26: Varies | G26: $60-90 | H26: =VLOOKUP(A26,'Manus All Chiaia'!$A$1:$I$70,9,0)&", Italy" -> Via Chiaia area, Naples, Italy | I26: =IFERROR(__xludf.DUMMYFUNCTION("JOIN("", "",J26,K26)"),"40.838, 14.247") -> 40.838, 14.247 | J26: =VLOOKUP($A26,'Manus All Chiaia'!$A$1:$K$70,10,0) -> 40.838 | K26: =VLOOKUP($A26,'Manus All Chiaia'!$A$1:$K$70,11,0) -> 14.247 | L26: =HYPERLINK("https://www.google.com/maps/search/"&ENCODEURL(A26&", Naples")) -> https://www.google.com/maps/search/Cap%27Alice%2C%20Naples | M26: Manus (Chiaia) - https://chatgpt.com/c/6846f0da-7884-8009-ad13-dba01dfa021d
A27: Mennella Il Gelato | B27: Gelateria | C27: 🍦 | D27: Best gelato in Naples according to locals, craft ice cream factory founded in 1969. | E27: Multiple locations, wide variety from classic to seasonal flavors | F27: Mon-Sat 11:00-02:00, Sun 11:00-late | G27: $8-15 | H27: =VLOOKUP(A27,'Manus All Chiaia'!$A$1:$I$70,9,0)&", Italy" -> Via Giosuè Carducci 43, 80121 Naples, Italy | I27: =IFERROR(__xludf.DUMMYFUNCTION("JOIN("", "",J27,K27)"),"40.836, 14.245") -> 40.836, 14.245 | J27: =VLOOKUP($A27,'Manus All Chiaia'!$A$1:$K$70,10,0) -> 40.836 | K27: =VLOOKUP($A27,'Manus All Chiaia'!$A$1:$K$70,11,0) -> 14.245 | L27: =HYPERLINK("https://www.google.com/maps/search/"&ENCODEURL(A27&", Naples")) -> https://www.google.com/maps/search/Mennella%20Il%20Gelato%2C%20Naples | M27: Manus (Chiaia) - https://chatgpt.com/c/6846f0da-7884-8009-ad13-dba01dfa021d
A28: Gay-Odin | B28: Gelateria | C28: 🍦 | D28: Historic chocolate shop serving the city's best chocolate gelato and traditional sweets. | E28: Best chocolate gelato in the city, historic shop | F28: Varies | G28: $8-15 | H28: =VLOOKUP(A28,'Manus All Chiaia'!$A$1:$I$70,9,0)&", Italy" -> Via Benedetto Croce 61, 80134 Naples, Italy | I28: =IFERROR(__xludf.DUMMYFUNCTION("JOIN("", "",J28,K28)"),"40.8485, 14.2565") -> 40.8485, 14.2565 | J28: =VLOOKUP($A28,'Manus All Chiaia'!$A$1:$K$70,10,0) -> 40.8485 | K28: =VLOOKUP($A28,'Manus All Chiaia'!$A$1:$K$70,11,0) -> 14.2565 | L28: =HYPERLINK("https://www.google.com/maps/search/"&ENCODEURL(A28&", Naples")) -> https://www.google.com/maps/search/Gay-Odin%2C%20Naples | M28: Manus (Chiaia) - https://chatgpt.com/c/6846f0da-7884-8009-ad13-dba01dfa021d
A29: Casa Infante | B29: Gelateria | C29: 🍦 | D29: Traditional gelateria with multiple locations for classic gelato experience. | E29: Traditional approach, multiple locations | F29: Varies | G29: $8-15 | H29: =VLOOKUP(A29,'Manus All Chiaia'!$A$1:$I$70,9,0)&", Italy" -> Multiple locations in Naples, Italy | I29: =IFERROR(__xludf.DUMMYFUNCTION("JOIN("", "",J29,K29)"),"40.852, 14.268") -> 40.852, 14.268 | J29: =VLOOKUP($A29,'Manus All Chiaia'!$A$1:$K$70,10,0) -> 40.852 | K29: =VLOOKUP($A29,'Manus All Chiaia'!$A$1:$K$70,11,0) -> 14.268 | L29: =HYPERLINK("https://www.google.com/maps/search/"&ENCODEURL(A29&", Naples")) -> https://www.google.com/maps/search/Casa%20Infante%2C%20Naples | M29: Manus (Chiaia) - https://chatgpt.com/c/6846f0da-7884-8009-ad13-dba01dfa021d
A30: Il Gelatiere | B30: Gelateria | C30: 🍦 | D30: Sophisticated gelato experience in Chiaia with blend of old and new interior design. | E30: Located in upscale Chiaia, sophisticated atmosphere | F30: Varies | G30: $8-15 | H30: =VLOOKUP(A30,'Manus All Chiaia'!$A$1:$I$70,9,0)&", Italy" -> Via Chiaia area, Naples, Italy | I30: =IFERROR(__xludf.DUMMYFUNCTION("JOIN("", "",J30,K30)"),"40.838, 14.247") -> 40.838, 14.247 | J30: =VLOOKUP($A30,'Manus All Chiaia'!$A$1:$K$70,10,0) -> 40.838 | K30: =VLOOKUP($A30,'Manus All Chiaia'!$A$1:$K$70,11,0) -> 14.247 | L30: =HYPERLINK("https://www.google.com/maps/search/"&ENCODEURL(A30&", Naples")) -> https://www.google.com/maps/search/Il%20Gelatiere%2C%20Naples | M30: Manus (Chiaia) - https://chatgpt.com/c/6846f0da-7884-8009-ad13-dba01dfa021d
A31: Villa Comunale | B31: Park | C31: 🌳 | D31: Most prestigious park in Naples, former Royal Garden with seafront location and aquarium. | E31: Former Royal Garden, houses 1870s aquarium, romantic strolls | F31: Daily 7:00-24:00 | G31: Free | H31: =VLOOKUP(A31,'Manus All Chiaia'!$A$1:$I$70,9,0)&", Italy" -> Via Caracciolo, 80121 Naples, Italy | I31: =IFERROR(__xludf.DUMMYFUNCTION("JOIN("", "",J31,K31)"),"40.832, 14.248") -> 40.832, 14.248 | J31: =VLOOKUP($A31,'Manus All Chiaia'!$A$1:$K$70,10,0) -> 40.832 | K31: =VLOOKUP($A31,'Manus All Chiaia'!$A$1:$K$70,11,0) -> 14.248 | L31: =HYPERLINK("https://www.google.com/maps/search/"&ENCODEURL(A31&", Naples")) -> https://www.google.com/maps/search/Villa%20Comunale%2C%20Naples | M31: Manus (Chiaia) - https://chatgpt.com/c/6846f0da-7884-8009-ad13-dba01dfa021d
A32: Anton Dohrn Aquarium | B32: Aquarium | C32: 🐠 | D32: One of world's best marine biology research facilities, opened in 1872. | E32: Educational experience, unique date activity, scientific facility | F32: Varies | G32: $15-25 | H32: =VLOOKUP(A32,'Manus All Chiaia'!$A$1:$I$70,9,0)&", Italy" -> Villa Comunale, Via Caracciolo, 80121 Naples, Italy | I32: =IFERROR(__xludf.DUMMYFUNCTION("JOIN("", "",J32,K32)"),"40.832, 14.248") -> 40.832, 14.248 | J32: =VLOOKUP($A32,'Manus All Chiaia'!$A$1:$K$70,10,0) -> 40.832 | K32: =VLOOKUP($A32,'Manus All Chiaia'!$A$1:$K$70,11,0) -> 14.248 | L32: =HYPERLINK("https://www.google.com/maps/search/"&ENCODEURL(A32&", Naples")) -> https://www.google.com/maps/search/Anton%20Dohrn%20Aquarium%2C%20Naples | M32: Manus (Chiaia) - https://chatgpt.com/c/6846f0da-7884-8009-ad13-dba01dfa021d
A33: Villa Pignatelli | B33: Museum | C33: 🏛️ | D33: 19th-century villa-turned-museum with Doric columns, sea views, and beautiful gardens. | F33: Varies | G33: $10-20 | H33: =VLOOKUP(A33,'Manus All Chiaia'!$A$1:$I$70,9,0)&", Italy" -> Riviera di Chiaia 200, 80121 Naples, Italy | I33: =IFERROR(__xludf.DUMMYFUNCTION("JOIN("", "",J33,K33)"),"40.831, 14.247") -> 40.831, 14.247 | J33: =VLOOKUP($A33,'Manus All Chiaia'!$A$1:$K$70,10,0) -> 40.831 | K33: =VLOOKUP($A33,'Manus All Chiaia'!$A$1:$K$70,11,0) -> 14.247 | L33: =HYPERLINK("https://www.google.com/maps/search/"&ENCODEURL(A33&", Naples")) -> https://www.google.com/maps/search/Villa%20Pignatelli%2C%20Naples | M33: Manus (Chiaia) - https://chatgpt.com/c/6846f0da-7884-8009-ad13-dba01dfa021d
A34: Museum D'Aragona Pignatelli Cortes | B34: Museum | C34: 🎨 | D34: Neapolitan "house museum" with art collection, donated by Princess Rosina in 1952. | E34: Art collection, intimate cultural experience | F34: Daily except Tuesday 9:00-14:00 | G34: $10-15 | H34: =VLOOKUP(A34,'Manus All Chiaia'!$A$1:$I$70,9,0)&", Italy" -> Riviera di Chiaia 200, 80121 Naples, Italy | I34: =IFERROR(__xludf.DUMMYFUNCTION("JOIN("", "",J34,K34)"),"40.831, 14.247") -> 40.831, 14.247 | J34: =VLOOKUP($A34,'Manus All Chiaia'!$A$1:$K$70,10,0) -> 40.831 | K34: =VLOOKUP($A34,'Manus All Chiaia'!$A$1:$K$70,11,0) -> 14.247 | L34: =HYPERLINK("https://www.google.com/maps/search/"&ENCODEURL(A34&", Naples")) -> https://www.google.com/maps/search/Museum%20D%27Aragona%20Pignatelli%20Cortes%2C%20Naples | M34: Manus (Chiaia) - https://chatgpt.com/c/6846f0da-7884-8009-ad13-dba01dfa021d
A35: Museum Marchese Mario d'Alessandro | B35: Museum | C35: 🎨 | D35: Unique carriage museum with collection of old carriages and harnesses. | E35: Collection of historical transportation, inaugurated 1975 | F35: Varies | G35: $8-12 | H35: =VLOOKUP(A35,'Manus All Chiaia'!$A$1:$I$70,9,0)&", Italy" -> Riviera di Chiaia 200, Villa Pignatelli, 80121 Naples, Italy | I35: =IFERROR(__xludf.DUMMYFUNCTION("JOIN("", "",J35,K35)"),"40.831, 14.247") -> 40.831, 14.247 | J35: =VLOOKUP($A35,'Manus All Chiaia'!$A$1:$K$70,10,0) -> 40.831 | K35: =VLOOKUP($A35,'Manus All Chiaia'!$A$1:$K$70,11,0) -> 14.247 | L35: =HYPERLINK("https://www.google.com/maps/search/"&ENCODEURL(A35&", Naples")) -> https://www.google.com/maps/search/Museum%20Marchese%20Mario%20d%27Alessandro%2C%20Naples | M35: Manus (Chiaia) - https://chatgpt.com/c/6846f0da-7884-8009-ad13-dba01dfa021d
A36: Funicolare Centrale | B36: Transportation | C36: 🚠 | D36: One of world's longest and busiest funiculars offering dramatic city views to Vomero Hill. | E36: 10+ million passengers annually, dramatic engineering feat | F36: Varies | G36: $3-5 | H36: =VLOOKUP(A36,'Manus All Chiaia'!$A$1:$I$70,9,0)&", Italy" -> Via Toledo, 80134 Naples, Italy | I36: =IFERROR(__xludf.DUMMYFUNCTION("JOIN("", "",J36,K36)"),"40.8485, 14.2565") -> 40.8485, 14.2565 | J36: =VLOOKUP($A36,'Manus All Chiaia'!$A$1:$K$70,10,0) -> 40.8485 | K36: =VLOOKUP($A36,'Manus All Chiaia'!$A$1:$K$70,11,0) -> 14.2565 | L36: =HYPERLINK("https://www.google.com/maps/search/"&ENCODEURL(A36&", Naples")) -> https://www.google.com/maps/search/Funicolare%20Centrale%2C%20Naples | M36: Manus (Chiaia) - https://chatgpt.com/c/6846f0da-7884-8009-ad13-dba01dfa021d
A37: Lungomare Caracciolo | B37: Promenade | C37: 🌅 | D37: Romantic waterfront promenade with stunning Castel dell'Ovo and Mount Vesuvius views. | E37: Best at sunset, golden coastline views, hand-in-hand strolls | F37: 24/7 | G37: Free | H37: =VLOOKUP(A37,'Manus All Chiaia'!$A$1:$I$70,9,0)&", Italy" -> Via Caracciolo, 80121 Naples, Italy | I37: =IFERROR(__xludf.DUMMYFUNCTION("JOIN("", "",J37,K37)"),"40.832, 14.248") -> 40.832, 14.248 | J37: =VLOOKUP($A37,'Manus All Chiaia'!$A$1:$K$70,10,0) -> 40.832 | K37: =VLOOKUP($A37,'Manus All Chiaia'!$A$1:$K$70,11,0) -> 14.248 | L37: =HYPERLINK("https://www.google.com/maps/search/"&ENCODEURL(A37&", Naples")) -> https://www.google.com/maps/search/Lungomare%20Caracciolo%2C%20Naples | M37: Manus (Chiaia) - https://chatgpt.com/c/6846f0da-7884-8009-ad13-dba01dfa021d
A38: Via Chiaia | B38: Shopping Street | C38: 🛍️ | D38: Elegant shopping street with luxury boutiques and beautiful architecture. | E38: Designer boutiques, historic palazzos, romantic window shopping | F38: Varies by shop | G38: $50-500+ | H38: =VLOOKUP(A38,'Manus All Chiaia'!$A$1:$I$70,9,0)&", Italy" -> Via Chiaia, 80121 Naples, Italy | I38: =IFERROR(__xludf.DUMMYFUNCTION("JOIN("", "",J38,K38)"),"40.838, 14.247") -> 40.838, 14.247 | J38: =VLOOKUP($A38,'Manus All Chiaia'!$A$1:$K$70,10,0) -> 40.838 | K38: =VLOOKUP($A38,'Manus All Chiaia'!$A$1:$K$70,11,0) -> 14.247 | L38: =HYPERLINK("https://www.google.com/maps/search/"&ENCODEURL(A38&", Naples")) -> https://www.google.com/maps/search/Via%20Chiaia%2C%20Naples | M38: Manus (Chiaia) - https://chatgpt.com/c/6846f0da-7884-8009-ad13-dba01dfa021d
A39: Rubinacci | B39: Shopping | C39: 🛍️ | D39: Home of men's tailoring with colorful ties, silk scarves, and vintage suits. | E39: Italian couture, luxury fashion, men's focus | F39: Varies | G39: $200-2000+ | H39: =VLOOKUP(A39,'Manus All Chiaia'!$A$1:$I$70,9,0)&", Italy" -> Via Chiaia 149/A, 80121 Naples, Italy | I39: =IFERROR(__xludf.DUMMYFUNCTION("JOIN("", "",J39,K39)"),"40.8385, 14.2475") -> 40.8385, 14.2475 | J39: =VLOOKUP($A39,'Manus All Chiaia'!$A$1:$K$70,10,0) -> 40.8385 | K39: =VLOOKUP($A39,'Manus All Chiaia'!$A$1:$K$70,11,0) -> 14.2475 | L39: =HYPERLINK("https://www.google.com/maps/search/"&ENCODEURL(A39&", Naples")) -> https://www.google.com/maps/search/Rubinacci%2C%20Naples | M39: Manus (Chiaia) - https://chatgpt.com/c/6846f0da-7884-8009-ad13-dba01dfa021d
A40: Gemelli da Polsi | B40: Shopping | C40: 🛍️ | D40: Luxury cuff links from simple silver to diamond-embedded designs. | E40: Unique luxury accessories, from silver to diamond options | F40: Varies | G40: $100-1000+ | H40: =VLOOKUP(A40,'Manus All Chiaia'!$A$1:$I$70,9,0)&", Italy" -> Via Chiaia area, Naples, Italy | I40: =IFERROR(__xludf.DUMMYFUNCTION("JOIN("", "",J40,K40)"),"40.838, 14.247") -> 40.838, 14.247 | J40: =VLOOKUP($A40,'Manus All Chiaia'!$A$1:$K$70,10,0) -> 40.838 | K40: =VLOOKUP($A40,'Manus All Chiaia'!$A$1:$K$70,11,0) -> 14.247 | L40: =HYPERLINK("https://www.google.com/maps/search/"&ENCODEURL(A40&", Naples")) -> https://www.google.com/maps/search/Gemelli%20da%20Polsi%2C%20Naples | M40: Manus (Chiaia) - https://chatgpt.com/c/6846f0da-7884-8009-ad13-dba01dfa021d

Sheet Chiaia
A1: Name | B1: Type | C1: Emoji | D1: Description | E1: Special Notes | F1: Hours | G1: Cost Range (USD for 2) | H1: Address | I1: LatLong | J1: Latitude | K1: Longitude | L1: Google Maps | M1: Recommended By
A2: Birdy's Bakery | B2: Cafe | C2: ☕ | D2: American-style breakfast spot with Italian charm, cozy and refined atmosphere | E2: Pancakes, French toast, avocado toast, excellent coffee | F2: Mon-Tue 7:00-21:00, Wed 7:00-23:00 | G2: $15-25 | H2: Vico Belledonne a Chiaia, 14b, 80121 Napoli NA, Italy | I2: 40.8352328, 14.2388971 | J2: 40.835233 | K2: 14.238897 | L2: =HYPERLINK("https://www.google.com/maps/search/"&ENCODEURL(A2&", Naples, Italy")) -> https://www.google.com/maps/search/Birdy%27s%20Bakery%2C%20Naples%2C%20Italy | M2: Manus (Chiaia More Options) - https://chatgpt.com/c/6846f0da-7884-8009-ad13-dba01dfa021d
A3: Caffè Sansone | B3: Cafe | C3: ☕ | D3: Known for preparing some of the best coffee in Naples | E3: Authentic Neapolitan coffee experience | F3: Varies | G3: $5-10 | H3: C.so Vittorio Emanuele, 269, 80135 Napoli NA, Italy | I3: 40.8403652, 14.2434381 | J3: 40.840365 | K3: 14.243438 | L3: =HYPERLINK("https://www.google.com/maps/search/"&ENCODEURL(A3&", Naples, Italy")) -> https://www.google.com/maps/search/Caff%C3%A8%20Sansone%2C%20Naples%2C%20Italy | M3: Manus (Chiaia More Options) - https://chatgpt.com/c/6846f0da-7884-8009-ad13-dba01dfa021d
A4: Blue Turtle Caffeteria | B4: Cafe | C4: ☕ | D4: Hipster spot with excellent coffee and modern atmosphere | E4: Instagram-worthy coffee and casual hangout | F4: Varies | G4: $10-15 | H4: Passeggiata Colonna, P.za Amedeo, 16c, 80121 Napoli NA, Italy | I4: 40.8368152, 14.2346448 | J4: 40.836815 | K4: 14.234645 | L4: =HYPERLINK("https://www.google.com/maps/search/"&ENCODEURL(A4&", Naples, Italy")) -> https://www.google.com/maps/search/Blue%20Turtle%20Caffeteria%2C%20Naples%2C%20Italy | M4: Manus (Chiaia More Options) - https://chatgpt.com/c/6846f0da-7884-8009-ad13-dba01dfa021d
A5: Pasticceria Mennella | B5: Cafe | C5: 🥐 | D5: Classic Neapolitan pastries and excellent coffee | E5: Traditional Italian breakfast experience | F5: Varies | G5: $8-12 | H5: Via Giosuè Carducci, 50/52, 80121 Napoli NA, Italy | I5: 40.8364836, 14.2371015 | J5: 40.836484 | K5: 14.237101 | L5: =HYPERLINK("https://www.google.com/maps/search/"&ENCODEURL(A5&", Naples, Italy")) -> https://www.google.com/maps/search/Pasticceria%20Mennella%2C%20Naples%2C%20Italy | M5: Manus (Chiaia More Options) - https://chatgpt.com/c/6846f0da-7884-8009-ad13-dba01dfa021d
A6: La Feltrinelli Bookstore Cafe | B6: Cafe | C6: 📚 | D6: Bookstore cafe perfect for browsing and coffee | E6: Quiet coffee break while book shopping | F6: Varies | G6: $8-15 | H6: Naples, Metropolitan City of Naples, Italy | I6: 40.8517746, 14.2681244 | J6: 40.851775 | K6: 14.268124 | L6: =HYPERLINK("https://www.google.com/maps/search/"&ENCODEURL(A6&", Naples, Italy")) -> https://www.google.com/maps/search/La%20Feltrinelli%20Bookstore%20Cafe%2C%20Naples%2C%20Italy | M6: Manus (Chiaia More Options) - https://chatgpt.com/c/6846f0da-7884-8009-ad13-dba01dfa021d
A7: 50 Kaló | B7: Pizzeria | C7: 🍕 | D7: Upscale casual pizza, popular with wealthy locals | E7: Gourmet pizza with premium ingredients, border of Chiaia and Posillipo | F7: Varies | G7: $25-35 | H7: P.za Sannazaro, 201/c, 80121 Napoli NA, Italy | I7: 40.8283749, 14.2202568 | J7: 40.828375 | K7: 14.220257 | L7: =HYPERLINK("https://www.google.com/maps/search/"&ENCODEURL(A7&", Naples, Italy")) -> https://www.google.com/maps/search/50%20Kal%C3%B3%2C%20Naples%2C%20Italy | M7: Manus (Chiaia More Options) - https://chatgpt.com/c/6846f0da-7884-8009-ad13-dba01dfa021d
A8: Pizzeria Donna Sofia a Chiaia | B8: Pizzeria | C8: 🍕 | D8: Fantastic fried pizza specialist | E8: Thin crust fried pizza with excellent ingredients | F8: Varies | G8: $15-25 | H8: Via Chiaia, 188, 80132 Napoli NA, Italy | I8: 40.8360475, 14.2452463 | J8: 40.836047 | K8: 14.245246 | L8: =HYPERLINK("https://www.google.com/maps/search/"&ENCODEURL(A8&", Naples, Italy")) -> https://www.google.com/maps/search/Pizzeria%20Donna%20Sofia%20a%20Chiaia%2C%20Naples%2C%20Italy | M8: Manus (Chiaia More Options) - https://chatgpt.com/c/6846f0da-7884-8009-ad13-dba01dfa021d
A9: Mama Eat - Napoli | B9: Pizzeria | C9: 🍕 | D9: Highly rated casual pizza spot | E9: 4.5/5 on TripAdvisor rating | F9: Varies | G9: $20-30 | H9: Via Alessandro Manzoni, 6, 80123 Napoli NA, Italy | I9: 40.83663, 14.2132139 | J9: 40.83663 | K9: 14.213214 | L9: =HYPERLINK("https://www.google.com/maps/search/"&ENCODEURL(A9&", Naples, Italy")) -> https://www.google.com/maps/search/Mama%20Eat%20-%20Napoli%2C%20Naples%2C%20Italy | M9: Manus (Chiaia More Options) - https://chatgpt.com/c/6846f0da-7884-8009-ad13-dba01dfa021d
A10: Pizzeria Gaetano Genovesi | B10: Pizzeria | C10: 🍕 | D10: Traditional pizzeria with excellent reputation | E10: Authentic Neapolitan pizza experience | F10: Varies | G10: $18-28 | H10: Via Alessandro Manzoni, 26/i, 80123 Napoli NA, Italy | I10: 40.8353744, 14.2112749 | J10: 40.835374 | K10: 14.211275 | L10: =HYPERLINK("https://www.google.com/maps/search/"&ENCODEURL(A10&", Naples, Italy")) -> https://www.google.com/maps/search/Pizzeria%20Gaetano%20Genovesi%2C%20Naples%2C%20Italy | M10: Manus (Chiaia More Options) - https://chatgpt.com/c/6846f0da-7884-8009-ad13-dba01dfa021d
A11: Umberto | B11: Restaurant | C11: 🍝 | D11: Traditional restaurant serving both pizza and other dishes | E11: Versatile dining option | F11: Varies | G11: $25-40 | H11: Via Foria, Napoli NA, Italy | I11: 40.8585895, 14.2607189 | J11: 40.85859 | K11: 14.260719 | L11: =HYPERLINK("https://www.google.com/maps/search/"&ENCODEURL(A11&", Naples, Italy")) -> https://www.google.com/maps/search/Umberto%2C%20Naples%2C%20Italy | M11: Manus (Chiaia More Options) - https://chatgpt.com/c/6846f0da-7884-8009-ad13-dba01dfa021d
A12: Kestè | B12: Wine Bar | C12: 🍷 | D12: Popular student spot with live music calendar | E12: Casual drinks with potential live entertainment | F12: Varies | G12: $20-35 | H12: Via S. Giovanni Maggiore Pignatelli, 26/27, 80134 Napoli NA, Italy | I12: 40.8458993, 14.2557424 | J12: 40.845899 | K12: 14.255742 | L12: =HYPERLINK("https://www.google.com/maps/search/"&ENCODEURL(A12&", Naples, Italy")) -> https://www.google.com/maps/search/Kest%C3%A8%2C%20Naples%2C%20Italy | M12: Manus (Chiaia More Options) - https://chatgpt.com/c/6846f0da-7884-8009-ad13-dba01dfa021d
A13: Vineria San Sebastiano | B13: Wine Bar | C13: 🍷 | D13: Classic wine bar with local atmosphere | E13: Traditional Italian wine experience | F13: Varies | G13: $25-40 | H13: Via S. Sebastiano, 11, 80134 Napoli NA, Italy | I13: 40.8489422, 14.2523447 | J13: 40.848942 | K13: 14.252345 | L13: =HYPERLINK("https://www.google.com/maps/search/"&ENCODEURL(A13&", Naples, Italy")) -> https://www.google.com/maps/search/Vineria%20San%20Sebastiano%2C%20Naples%2C%20Italy | M13: Manus (Chiaia More Options) - https://chatgpt.com/c/6846f0da-7884-8009-ad13-dba01dfa021d
... A35: La Scialuppa | B35: Restaurant (Dinner) | C35: 🍽️ | D35: - Classic Neapolitan seafood spot - Located in the Castel dell'Ovo marina - Scenic views and lively energy | E35: Great choice for lighter fare or shared dishes. | F35: 12:00–15:30, 19:00–23:30 | G35: $70–110 | H35: Piazzetta Marinari, 5, 80132 Napoli NA, Italy | I35: 40.8278216, 14.2485845 | J35: 40.827822 | K35: 14.248584 | L35: =HYPERLINK("https://www.google.com/maps/search/"&ENCODEURL(A35&", Naples, Italy")) -> https://www.google.com/maps/search/La%20Scialuppa%2C%20Naples%2C%20Italy | M35: Chat GPT - https://chatgpt.com/c/6846f0da-7884-8009-ad13-dba01dfa021d

Sheet Travel Times
A1: Destination | B1: Region | D1: Walk Time | E1: Drive Time | F1: Origin
A2: Belmond Hotel Caruso (Ravello) | B2: Ravello | D2: 8 mins | E2: 3 mins | F2: Hotel Rufolo, Ravello, Italy
A3: Villa Maria Ravello | B3: Ravello | D3: 4 mins | E3: 1 min | F3: Hotel Rufolo, Ravello, Italy
A4: Villa Rufolo (Ravello) | B4: Ravello | D4: 2 mins | E4: 1 min | F4: Hotel Rufolo, Ravello, Italy
A5: Wagner Tours (Wine Experience, Ravello) | B5: Ravello | D5: 1 min | E5: 1 min | F5: Hotel Rufolo, Ravello, Italy
A6: Rossellinis at Palazzo Avino (Ravello) | B6: Ravello | D6: 8 mins | E6: 2 mins | F6: Hotel Rufolo, Ravello, Italy
